[
  {
    "type": "product",
    "title": "Banana Lolly Sticks 12 Pcs",
    "url": "https://eshop.kddc.com/en/Ice-Cream",
    "category": "ice cream",
    "text": "Banana Lolly Sticks 12 Pcs | ice cream | 0.54 KWD | None | banana | | | 12 pcs | Carton - 12 Pieces | 12 pieces | KWD 0.54 | Exciting banana flavored ice lolly, a favourite among kids. No artifical colours KD 0.540",
    "meta": {
      "dedup_key": "https://eshop.kddc.com/en/Ice-Cream",
      "name": "Banana Lolly Sticks 12 Pcs",
      "brand": null,
      "category": "ice cream",
      "flavor": "banana",
      "volume_ml": null,
      "weight_g": null,
      "pack_units": 12,
      "product_url": "https://eshop.kddc.com/en/Ice-Cream",
      "product_code": "FICSTL12BANSTK",
      "sku": "FICSTL12BANSTK",
      "availability": "in_stock",
      "price_now_kwd": 0.54,
      "options_text": "Carton - 12 Pieces | 12 pieces | KWD 0.54",
      "price_notes": "carton_per_piece≈0.045 KWD",
      "reviews_count": 0,
      "rating_stars": null,
      "desc": "Exciting banana flavored ice lolly, a favourite among kids. No artifical colours  KD 0.540 "
    }
  },
  {
    "type": "product",
    "title": "Banana Lolly Sticks 48 Pcs",
    "url": "https://eshop.kddc.com/en/Ice-Cream/Banana-Lolly-Sticks-48-Pcs-8699",
    "category": "ice cream",
    "text": "Banana Lolly Sticks 48 Pcs | ice cream | 2.16 KWD | None | banana | | | 48 pcs | Carton - 48 Pieces | 48 pieces | KWD 2.16 | Exciting banana flavored ice lolly, a favourite among kids. No artifical colours Nutrition Facts Per 1 Piece Nutrition Value Energy (Calories) 90 Calories from Fat (g) 22.5 Total Fat (g) 2.5 Saturated Fat (g) 2 Unsaturated Fat (g) 0.5 Trans Fat (g) 0 Cholesterol (g) 0 Sodium (mg) 0.025 Total Carbohydrate (g) 17 Dietary Fibres (g) 0 Total Sugars (g) 16 Added Sugar (g) 13 Protein (g) 2 KD 2.160",
    "meta": {
      "dedup_key": "https://eshop.kddc.com/en/Ice-Cream/Banana-Lolly-Sticks-48-Pcs-8699",
      "name": "Banana Lolly Sticks 48 Pcs",
      "brand": null,
      "category": "ice cream",
      "flavor": "banana",
      "volume_ml": null,
      "weight_g": null,
      "pack_units": 48,
      "product_url": "https://eshop.kddc.com/en/Ice-Cream/Banana-Lolly-Sticks-48-Pcs-8699",
      "product_code": "FICSTL48BANSTK",
      "sku": "FICSTL48BANSTK",
      "availability": "in_stock",
      "price_now_kwd": 2.16,
      "options_text": "Carton - 48 Pieces | 48 pieces | KWD 2.16",
      "price_notes": "carton_per_piece≈0.045 KWD",
      "reviews_count": 0,
      "rating_stars": null,
      "desc": "Exciting banana flavored ice lolly, a favourite among kids. No artifical colours Nutrition Facts Per 1 Piece Nutrition Value Energy (Calories) 90 Calories from Fat (g) 22.5 Total Fat (g) 2.5 Saturated Fat (g) 2 Unsaturated Fat (g) 0.5 Trans Fat (g) 0 Cholesterol (g) 0 Sodium (mg) 0.025 Total Carbohydrate (g) 17 Dietary Fibres (g) 0 Total Sugars (g) 16 Added Sugar (g) 13 Protein (g) 2  KD 2.160 "
    }
  },
  {
    "type": "product",
    "title": "Blitz Mango With Vanilla",
    "url": "https://eshop.kddc.com/en/Ice-Cream/Blitz--Mango-With-Vanilla-7541",
    "category": "ice cream",
    "text": "Blitz Mango With Vanilla | ice cream | 2.4 KWD | None | vanilla | | | | Carton - 24 Pieces | 24 pieces | KWD 2.4 | A blend of creamy vanilla ice cream with the real taste of mango. Nutrition Facts Per 1 Piece Nutrition Value Energy (Calories) 70 Calories from Fat (g) 27 Total Fat (g) 3 Saturated Fat (g) 2.5 Unsaturated Fat (g) 0.5 Trans Fat (g) 0 Cholesterol (g) 0 Sodium (mg) 0.015 Total Carbohydrate (g) 12 Dietary Fibres (g) 0 Total Sugars (g) 11 Added Sugar (g) 9 Protein (g) 1 KD 2.400",
    "meta": {
      "dedup_key": "https://eshop.kddc.com/en/Ice-Cream/Blitz--Mango-With-Vanilla-7541",
      "name": "Blitz Mango With Vanilla",
      "brand": null,
      "category": "ice cream",
      "flavor": "vanilla",
      "volume_ml": null,
      "weight_g": null,
      "pack_units": null,
      "product_url": "https://eshop.kddc.com/en/Ice-Cream/Blitz--Mango-With-Vanilla-7541",
      "product_code": "FICSTLVNMG24BZ",
      "sku": "FICSTLVNMG24BZ",
      "availability": "in_stock",
      "price_now_kwd": 2.4,
      "options_text": "Carton - 24 Pieces | 24 pieces | KWD 2.4",
      "price_notes": "carton_per_piece≈0.100 KWD",
      "reviews_count": 0,
      "rating_stars": null,
      "desc": "A blend of creamy vanilla ice cream with the real taste of mango. Nutrition Facts Per 1 Piece Nutrition Value Energy (Calories) 70 Calories from Fat (g) 27 Total Fat (g) 3 Saturated Fat (g) 2.5 Unsaturated Fat (g) 0.5 Trans Fat (g) 0 Cholesterol (g) 0 Sodium (mg) 0.015 Total Carbohydrate (g) 12 Dietary Fibres (g) 0 Total Sugars (g) 11 Added Sugar (g) 9 Protein (g) 1  KD 2.400 "
    }
  },
  {
    "type": "product",
    "title": "Blitz Raspberry With Vanilla",
    "url": "https://eshop.kddc.com/en/Ice-Cream/Blitz--Raspberry-With-Vanilla-7544",
    "category": "ice cream",
    "text": "Blitz Raspberry With Vanilla | ice cream | 2.4 KWD | None | vanilla | | 55 g | | Carton - 24 Pieces | 24 pieces | KWD 2.4 | A blend of delicious Vanilla Ice Cream coated with the tangy Raspberry Nutrition Facts Per 55 g Nutrition Value Energy (Calories) 70 Calories from Fat (g) 27 Total Fat (g) 3 Saturated Fat (g) 2.5 Unsaturated Fat (g) 0.5 Trans Fat (g) 0 Cholesterol (g) 0 Sodium (mg) 0.015 Total Carbohydrate (g) 11 Dietary Fibres (g) 0 Total Sugars (g) 11 Added Sugar (g) 9 Protein (g) 1 KD 2.400 55 g",
    "meta": {
      "dedup_key": "https://eshop.kddc.com/en/Ice-Cream/Blitz--Raspberry-With-Vanilla-7544",
      "name": "Blitz Raspberry With Vanilla",
      "brand": null,
      "category": "ice cream",
      "flavor": "vanilla",
      "volume_ml": null,
      "weight_g": 55,
      "pack_units": null,
      "product_url": "https://eshop.kddc.com/en/Ice-Cream/Blitz--Raspberry-With-Vanilla-7544",
      "product_code": "FICSTLVNRB24BZ",
      "sku": "FICSTLVNRB24BZ",
      "availability": "in_stock",
      "price_now_kwd": 2.4,
      "options_text": "Carton - 24 Pieces | 24 pieces | KWD 2.4",
      "price_notes": "carton_per_piece≈0.100 KWD",
      "reviews_count": 0,
      "rating_stars": null,
      "desc": "A blend of delicious Vanilla Ice Cream coated with the tangy Raspberry Nutrition Facts Per 55 g Nutrition Value Energy (Calories) 70 Calories from Fat (g) 27 Total Fat (g) 3 Saturated Fat (g) 2.5 Unsaturated Fat (g) 0.5 Trans Fat (g) 0 Cholesterol (g) 0 Sodium (mg) 0.015 Total Carbohydrate (g) 11 Dietary Fibres (g) 0 Total Sugars (g) 11 Added Sugar (g) 9 Protein (g) 1  KD 2.400 55 g"
    }
  },
  {
    "type": "product",
    "title": "Blitz Boysenberry With Vanilla",
    "url": "https://eshop.kddc.com/en/Ice-Cream/Blitz-Boysenberry-With-Vanilla-7536",
    "category": "ice cream",
    "text": "Blitz Boysenberry With Vanilla | ice cream | 2.4 KWD | None | vanilla | | 55 g | | Carton - 24 Pieces | 24 pieces | KWD 2.4 | A blend of delicious Vanilla Ice Cream coated with fruity boysenberry. Nutrition Facts Per 55 g Nutrition Value Energy (Calories) 80 Calories from Fat (g) 27 Total Fat (g) 3 Saturated Fat (g) 2.5 Unsaturated Fat (g) 0.5 Trans Fat (g) 0 Cholesterol (g) 0 Sodium (mg) 0.015 Total Carbohydrate (g) 12 Dietary Fibres (g) 0 Total Sugars (g) 12 Added Sugar (g) 9 Protein (g) 1 KD 2.400 55 g",
    "meta": {
      "dedup_key": "https://eshop.kddc.com/en/Ice-Cream/Blitz-Boysenberry-With-Vanilla-7536",
      "name": "Blitz Boysenberry With Vanilla",
      "brand": null,
      "category": "ice cream",
      "flavor": "vanilla",
      "volume_ml": null,
      "weight_g": 55,
      "pack_units": null,
      "product_url": "https://eshop.kddc.com/en/Ice-Cream/Blitz-Boysenberry-With-Vanilla-7536",
      "product_code": "FICSTLVNBB24BZ",
      "sku": "FICSTLVNBB24BZ",
      "availability": "in_stock",
      "price_now_kwd": 2.4,
      "options_text": "Carton - 24 Pieces | 24 pieces | KWD 2.4",
      "price_notes": "carton_per_piece≈0.100 KWD",
      "reviews_count": 0,
      "rating_stars": null,
      "desc": "A blend of delicious Vanilla Ice Cream coated with fruity boysenberry. Nutrition Facts Per 55 g Nutrition Value Energy (Calories) 80 Calories from Fat (g) 27 Total Fat (g) 3 Saturated Fat (g) 2.5 Unsaturated Fat (g) 0.5 Trans Fat (g) 0 Cholesterol (g) 0 Sodium (mg) 0.015 Total Carbohydrate (g) 12 Dietary Fibres (g) 0 Total Sugars (g) 12 Added Sugar (g) 9 Protein (g) 1  KD 2.400 55 g"
    }
  },
  {
    "type": "product",
    "title": "Blitz Chocolate Stick",
    "url": "https://eshop.kddc.com/en/Ice-Cream/Blitz-Chocolate-Stick-7524",
    "category": "ice cream",
    "text": "Blitz Chocolate Stick | ice cream | 2.4 KWD | None | chocolate | | | | Carton - 24 Pieces | 24 pieces | KWD 2.4 | A blend of creamy chocolate ice cream coated with milk chocolate Nutrition Facts Per 1 Piece Nutrition Value Energy (Calories) 160 Calories from Fat (g) 99 Total Fat (g) 11 Saturated Fat (g) 9 Unsaturated Fat (g) 2 Trans Fat (g) 0 Cholesterol (g) 0 Sodium (mg) 0.03 Total Carbohydrate (g) 13 Dietary Fibres (g) 1 Total Sugars (g) 12 Added Sugar (g) 10 Protein (g) 2 KD 2.400",
    "meta": {
      "dedup_key": "https://eshop.kddc.com/en/Ice-Cream/Blitz-Chocolate-Stick-7524",
      "name": "Blitz Chocolate Stick",
      "brand": null,
      "category": "ice cream",
      "flavor": "chocolate",
      "volume_ml": null,
      "weight_g": null,
      "pack_units": null,
      "product_url": "https://eshop.kddc.com/en/Ice-Cream/Blitz-Chocolate-Stick-7524",
      "product_code": "FICSTLCHMCH24BZ",
      "sku": "FICSTLCHMCH24BZ",
      "availability": "in_stock",
      "price_now_kwd": 2.4,
      "options_text": "Carton - 24 Pieces | 24 pieces | KWD 2.4",
      "price_notes": "carton_per_piece≈0.100 KWD",
      "reviews_count": 0,
      "rating_stars": null,
      "desc": "A blend of creamy chocolate ice cream coated with milk chocolate Nutrition Facts Per 1 Piece Nutrition Value Energy (Calories) 160 Calories from Fat (g) 99 Total Fat (g) 11 Saturated Fat (g) 9 Unsaturated Fat (g) 2 Trans Fat (g) 0 Cholesterol (g) 0 Sodium (mg) 0.03 Total Carbohydrate (g) 13 Dietary Fibres (g) 1 Total Sugars (g) 12 Added Sugar (g) 10 Protein (g) 2  KD 2.400 "
    }
  },
  {
    "type": "product",
    "title": "Blitz Chocolate With Vanilla",
    "url": "https://eshop.kddc.com/en/Ice-Cream/Blitz-Chocolate-With-Vanilla-7538",
    "category": "ice cream",
    "text": "Blitz Chocolate With Vanilla | ice cream | 2.4 KWD | None | chocolate | | | | Carton - 24 Pieces | 24 pieces | KWD 2.4 | A blend of creamy chocolate ice cream coated with milk chocolate Nutrition Facts Per 1 Piece Nutrition Value Energy (Calories) 160 Calories from Fat (g) 99 Total Fat (g) 11 Saturated Fat (g) 9 Unsaturated Fat (g) 2 Trans Fat (g) 0 Cholesterol (g) 0 Sodium (mg) 0.03 Total Carbohydrate (g) 13 Dietary Fibres (g) 1 Total Sugars (g) 12 Added Sugar (g) 10 Protein (g) 2 KD 2.400",
    "meta": {
      "dedup_key": "https://eshop.kddc.com/en/Ice-Cream/Blitz-Chocolate-With-Vanilla-7538",
      "name": "Blitz Chocolate With Vanilla",
      "brand": null,
      "category": "ice cream",
      "flavor": "chocolate",
      "volume_ml": null,
      "weight_g": null,
      "pack_units": null,
      "product_url": "https://eshop.kddc.com/en/Ice-Cream/Blitz-Chocolate-With-Vanilla-7538",
      "product_code": "FICSTLVNCH24BZ",
      "sku": "FICSTLVNCH24BZ",
      "availability": "in_stock",
      "price_now_kwd": 2.4,
      "options_text": "Carton - 24 Pieces | 24 pieces | KWD 2.4",
      "price_notes": "carton_per_piece≈0.100 KWD",
      "reviews_count": 0,
      "rating_stars": null,
      "desc": "A blend of creamy chocolate ice cream coated with milk chocolate Nutrition Facts Per 1 Piece Nutrition Value Energy (Calories) 160 Calories from Fat (g) 99 Total Fat (g) 11 Saturated Fat (g) 9 Unsaturated Fat (g) 2 Trans Fat (g) 0 Cholesterol (g) 0 Sodium (mg) 0.03 Total Carbohydrate (g) 13 Dietary Fibres (g) 1 Total Sugars (g) 12 Added Sugar (g) 10 Protein (g) 2  KD 2.400 "
    }
  },
  {
    "type": "product",
    "title": "Bubble Top Vanilla",
    "url": "https://eshop.kddc.com/en/Ice-Cream/Bubble-Top-Vanilla--7458",
    "category": "ice cream",
    "text": "Bubble Top Vanilla | ice cream | 2.4 KWD | None | vanilla | | 54 g | | Carton - 24 Pieces | 24 pieces | KWD 2.4 | It takes two to tango, vanilla ice cream on the top, bubble gum below. Nutrition Facts Per 54 g Nutrition Value Energy (Calories) 110 Calories from Fat (g) 54 Total Fat (g) 6 Saturated Fat (g) 5 Unsaturated Fat (g) 1 Trans Fat (g) 0 Cholesterol (g) 5 Sodium (mg) 0.025 Total Carbohydrate (g) 12 Dietary Fibres (g) 0 Total Sugars (g) 12 Added Sugar (g) 9 Protein (g) 2 KD 2.400 54 g",
    "meta": {
      "dedup_key": "https://eshop.kddc.com/en/Ice-Cream/Bubble-Top-Vanilla--7458",
      "name": "Bubble Top Vanilla",
      "brand": null,
      "category": "ice cream",
      "flavor": "vanilla",
      "volume_ml": null,
      "weight_g": 54,
      "pack_units": null,
      "product_url": "https://eshop.kddc.com/en/Ice-Cream/Bubble-Top-Vanilla--7458",
      "product_code": "FICCCB10BT",
      "sku": "FICCCB10BT",
      "availability": "in_stock",
      "price_now_kwd": 2.4,
      "options_text": "Carton - 24 Pieces | 24 pieces | KWD 2.4",
      "price_notes": "carton_per_piece≈0.100 KWD",
      "reviews_count": 0,
      "rating_stars": null,
      "desc": "It takes two to tango, vanilla ice cream on the top, bubble gum below. Nutrition Facts Per 54 g Nutrition Value Energy (Calories) 110 Calories from Fat (g) 54 Total Fat (g) 6 Saturated Fat (g) 5 Unsaturated Fat (g) 1 Trans Fat (g) 0 Cholesterol (g) 5 Sodium (mg) 0.025 Total Carbohydrate (g) 12 Dietary Fibres (g) 0 Total Sugars (g) 12 Added Sugar (g) 9 Protein (g) 2  KD 2.400 54 g"
    }
  },
  {
    "type": "product",
    "title": "Burgan Sticks",
    "url": "https://eshop.kddc.com/en/Ice-Cream/Burgan-Sticks-8724",
    "category": "ice cream",
    "text": "Burgan Sticks | ice cream | 0.595 KWD | None | chocolate | | | | Carton - 6 Pieces | 6 pieces | KWD 0.595 | A blend of creamy chocolate ice cream coated with milk chocolate Nutrition Facts Per 1 Piece Nutrition Value Energy (Calories) 160 Calories from Fat (g) 99 Total Fat (g) 11 Saturated Fat (g) 9 Unsaturated Fat (g) 2 Trans Fat (g) 0 Cholesterol (g) 0 Sodium (mg) 0.03 Total Carbohydrate (g) 13 Dietary Fibres (g) 1 Total Sugars (g) 12 Added Sugar (g) 10 Protein (g) 2 KD 0.595",
    "meta": {
      "dedup_key": "https://eshop.kddc.com/en/Ice-Cream/Burgan-Sticks-8724",
      "name": "Burgan Sticks",
      "brand": null,
      "category": "ice cream",
      "flavor": "chocolate",
      "volume_ml": null,
      "weight_g": null,
      "pack_units": null,
      "product_url": "https://eshop.kddc.com/en/Ice-Cream/Burgan-Sticks-8724",
      "product_code": "FICSTL6BURGAN",
      "sku": "FICSTL6BURGAN",
      "availability": "in_stock",
      "price_now_kwd": 0.595,
      "options_text": "Carton - 6 Pieces | 6 pieces | KWD 0.595",
      "price_notes": "carton_per_piece≈0.099 KWD",
      "reviews_count": 0,
      "rating_stars": null,
      "desc": "A blend of creamy chocolate ice cream coated with milk chocolate Nutrition Facts Per 1 Piece Nutrition Value Energy (Calories) 160 Calories from Fat (g) 99 Total Fat (g) 11 Saturated Fat (g) 9 Unsaturated Fat (g) 2 Trans Fat (g) 0 Cholesterol (g) 0 Sodium (mg) 0.03 Total Carbohydrate (g) 13 Dietary Fibres (g) 1 Total Sugars (g) 12 Added Sugar (g) 10 Protein (g) 2  KD 0.595 "
    }
  },
  {
    "type": "product",
    "title": "Cacao Stick",
    "url": "https://eshop.kddc.com/en/Ice-Cream/Cacao-Stick-7527",
    "category": "ice cream",
    "text": "Cacao Stick | ice cream | 5.0 KWD | None | chocolate | | 56 g | | Carton - 50 Pieces | 50 pieces | KWD 5.0 | Keep it cool with tasty chocolate milk ice Nutrition Facts Per 56 g Nutrition Value Energy (Calories) 90 Calories from Fat (g) 18 Total Fat (g) 2 Saturated Fat (g) 1 Unsaturated Fat (g) 1 Trans Fat (g) 0 Cholesterol (g) 0 Sodium (mg) 0.025 Total Carbohydrate (g) 16 Dietary Fibres (g) 0 Total Sugars (g) 15 Added Sugar (g) 12.99 Protein (g) 1 KD 5.000 56 g",
    "meta": {
      "dedup_key": "https://eshop.kddc.com/en/Ice-Cream/Cacao-Stick-7527",
      "name": "Cacao Stick",
      "brand": null,
      "category": "ice cream",
      "flavor": "chocolate",
      "volume_ml": null,
      "weight_g": 56,
      "pack_units": null,
      "product_url": "https://eshop.kddc.com/en/Ice-Cream/Cacao-Stick-7527",
      "product_code": "FICSTLCOCOA",
      "sku": "FICSTLCOCOA",
      "availability": "in_stock",
      "price_now_kwd": 5.0,
      "options_text": "Carton - 50 Pieces | 50 pieces | KWD 5.0",
      "price_notes": "carton_per_piece≈0.100 KWD",
      "reviews_count": 0,
      "rating_stars": null,
      "desc": "Keep it cool with tasty chocolate milk ice Nutrition Facts Per 56 g Nutrition Value Energy (Calories) 90 Calories from Fat (g) 18 Total Fat (g) 2 Saturated Fat (g) 1 Unsaturated Fat (g) 1 Trans Fat (g) 0 Cholesterol (g) 0 Sodium (mg) 0.025 Total Carbohydrate (g) 16 Dietary Fibres (g) 0 Total Sugars (g) 15 Added Sugar (g) 12.99 Protein (g) 1  KD 5.000 56 g"
    }
  },
  {
    "type": "product",
    "title": "Choco Rico Stick",
    "url": "https://eshop.kddc.com/en/Ice-Cream/Choco-Rico-Stick-7526",
    "category": "ice cream",
    "text": "Choco Rico Stick | ice cream | 4.8 KWD | None | vanilla | | 69 g | | Carton - 48 Pieces | 48 pieces | KWD 4.8 | Keep it cool with Vanilla and Chocolate Milk Ice Nutrition Facts Per 69 g Nutrition Value Energy (Calories) 100 Calories from Fat (g) 22.5 Total Fat (g) 2.5 Saturated Fat (g) 1.5 Unsaturated Fat (g) 1 Trans Fat (g) 0 Cholesterol (g) 0 Sodium (mg) 0.035 Total Carbohydrate (g) 17 Dietary Fibres (g) 0 Total Sugars (g) 16 Added Sugar (g) 13 Protein (g) 2 KD 4.800 69 g",
    "meta": {
      "dedup_key": "https://eshop.kddc.com/en/Ice-Cream/Choco-Rico-Stick-7526",
      "name": "Choco Rico Stick",
      "brand": null,
      "category": "ice cream",
      "flavor": "vanilla",
      "volume_ml": null,
      "weight_g": 69,
      "pack_units": null,
      "product_url": "https://eshop.kddc.com/en/Ice-Cream/Choco-Rico-Stick-7526",
      "product_code": "FICSTLCHRI",
      "sku": "FICSTLCHRI",
      "availability": "in_stock",
      "price_now_kwd": 4.8,
      "options_text": "Carton - 48 Pieces | 48 pieces | KWD 4.8",
      "price_notes": "carton_per_piece≈0.100 KWD",
      "reviews_count": 0,
      "rating_stars": null,
      "desc": "Keep it cool with Vanilla and Chocolate Milk Ice Nutrition Facts Per 69 g Nutrition Value Energy (Calories) 100 Calories from Fat (g) 22.5 Total Fat (g) 2.5 Saturated Fat (g) 1.5 Unsaturated Fat (g) 1 Trans Fat (g) 0 Cholesterol (g) 0 Sodium (mg) 0.035 Total Carbohydrate (g) 17 Dietary Fibres (g) 0 Total Sugars (g) 16 Added Sugar (g) 13 Protein (g) 2  KD 4.800 69 g"
    }
  },
  {
    "type": "product",
    "title": "Chocolate Cup",
    "url": "https://eshop.kddc.com/en/Ice-Cream/Chocolate-Cup-7460",
    "category": "ice cream",
    "text": "Chocolate Cup | ice cream | 2.4 KWD | None | chocolate | | 56 g | | Carton - 24 Pieces | 24 pieces | KWD 2.4 | Classic chocolate ice cream. Always a pleasure Nutrition Facts Per 56 g Nutrition Value Energy (Calories) 110 Calories from Fat (g) 54 Total Fat (g) 6 Saturated Fat (g) 5 Unsaturated Fat (g) 1 Trans Fat (g) 0 Cholesterol (g) 5 Sodium (mg) 0.03 Total Carbohydrate (g) 13 Dietary Fibres (g) 1 Total Sugars (g) 12 Added Sugar (g) 9 Protein (g) 2 KD 2.400 56 g",
    "meta": {
      "dedup_key": "https://eshop.kddc.com/en/Ice-Cream/Chocolate-Cup-7460",
      "name": "Chocolate Cup",
      "brand": null,
      "category": "ice cream",
      "flavor": "chocolate",
      "volume_ml": null,
      "weight_g": 56,
      "pack_units": null,
      "product_url": "https://eshop.kddc.com/en/Ice-Cream/Chocolate-Cup-7460",
      "product_code": "FICCCB1CH",
      "sku": "FICCCB1CH",
      "availability": "in_stock",
      "price_now_kwd": 2.4,
      "options_text": "Carton - 24 Pieces | 24 pieces | KWD 2.4",
      "price_notes": "carton_per_piece≈0.100 KWD",
      "reviews_count": 0,
      "rating_stars": null,
      "desc": "Classic chocolate ice cream. Always a pleasure Nutrition Facts Per 56 g Nutrition Value Energy (Calories) 110 Calories from Fat (g) 54 Total Fat (g) 6 Saturated Fat (g) 5 Unsaturated Fat (g) 1 Trans Fat (g) 0 Cholesterol (g) 5 Sodium (mg) 0.03 Total Carbohydrate (g) 13 Dietary Fibres (g) 1 Total Sugars (g) 12 Added Sugar (g) 9 Protein (g) 2  KD 2.400 56 g"
    }
  },
  {
    "type": "product",
    "title": "Chocolate Ice Cream 1 LTR",
    "url": "https://eshop.kddc.com/en/Ice-Cream/Chocolate-Ice-Cream-1-LTR-7467",
    "category": "ice cream",
    "text": "Chocolate Ice Cream 1 LTR | ice cream | 1.0 KWD | None | chocolate | 1000 ml | 100 g | | Piece | 1 piece | KWD 1.0 | Classic chocolate ice cream. Always a pleasure Nutrition Facts Per 100 g Nutrition Value Energy (Calories) 210 Calories from Fat (g) 99 Total Fat (g) 11 Saturated Fat (g) 9 Unsaturated Fat (g) 2 Trans Fat (g) 0 Cholesterol (g) 5 Sodium (mg) 0.065 Total Carbohydrate (g) 27 Dietary Fibres (g) 1 Total Sugars (g) 24 Added Sugar (g) 19 Protein (g) 4 KD 1.000 100 g",
    "meta": {
      "dedup_key": "https://eshop.kddc.com/en/Ice-Cream/Chocolate-Ice-Cream-1-LTR-7467",
      "name": "Chocolate Ice Cream 1 LTR",
      "brand": null,
      "category": "ice cream",
      "flavor": "chocolate",
      "volume_ml": 1000,
      "weight_g": 100,
      "pack_units": null,
      "product_url": "https://eshop.kddc.com/en/Ice-Cream/Chocolate-Ice-Cream-1-LTR-7467",
      "product_code": "FICFMS1LCHRCUP",
      "sku": "FICFMS1LCHRCUP",
      "availability": "in_stock",
      "price_now_kwd": 1.0,
      "options_text": "Piece | 1 piece | KWD 1.0",
      "price_notes": null,
      "reviews_count": 0,
      "rating_stars": null,
      "desc": "Classic chocolate ice cream. Always a pleasure Nutrition Facts Per 100 g Nutrition Value Energy (Calories) 210 Calories from Fat (g) 99 Total Fat (g) 11 Saturated Fat (g) 9 Unsaturated Fat (g) 2 Trans Fat (g) 0 Cholesterol (g) 5 Sodium (mg) 0.065 Total Carbohydrate (g) 27 Dietary Fibres (g) 1 Total Sugars (g) 24 Added Sugar (g) 19 Protein (g) 4  KD 1.000 100 g"
    }
  },
  {
    "type": "product",
    "title": "Chocolate Ice Cream 5 LTR",
    "url": "https://eshop.kddc.com/en/Ice-Cream/Chocolate-Ice-Cream-5-LTR-7479",
    "category": "ice cream",
    "text": "Chocolate Ice Cream 5 LTR | ice cream | 4.4 KWD | None | chocolate | 5000 ml | 100 g | | Piece | 1 piece | KWD 4.4 | Classic chocolate ice cream. Always a pleasure Nutrition Facts Per 100 g Nutrition Value Energy (Calories) 210 Calories from Fat (g) 99 Total Fat (g) 11 Saturated Fat (g) 9 Unsaturated Fat (g) 2 Trans Fat (g) 0 Cholesterol (g) 5 Sodium (mg) 0.065 Total Carbohydrate (g) 27 Dietary Fibres (g) 1 Total Sugars (g) 24 Added Sugar (g) 19 Protein (g) 4 KD 4.400 100 g",
    "meta": {
      "dedup_key": "https://eshop.kddc.com/en/Ice-Cream/Chocolate-Ice-Cream-5-LTR-7479",
      "name": "Chocolate Ice Cream 5 LTR",
      "brand": null,
      "category": "ice cream",
      "flavor": "chocolate",
      "volume_ml": 5000,
      "weight_g": 100,
      "pack_units": null,
      "product_url": "https://eshop.kddc.com/en/Ice-Cream/Chocolate-Ice-Cream-5-LTR-7479",
      "product_code": "FICFMS5LCH",
      "sku": "FICFMS5LCH",
      "availability": "in_stock",
      "price_now_kwd": 4.4,
      "options_text": "Piece | 1 piece | KWD 4.4",
      "price_notes": null,
      "reviews_count": 0,
      "rating_stars": null,
      "desc": "Classic chocolate ice cream. Always a pleasure Nutrition Facts Per 100 g Nutrition Value Energy (Calories) 210 Calories from Fat (g) 99 Total Fat (g) 11 Saturated Fat (g) 9 Unsaturated Fat (g) 2 Trans Fat (g) 0 Cholesterol (g) 5 Sodium (mg) 0.065 Total Carbohydrate (g) 27 Dietary Fibres (g) 1 Total Sugars (g) 24 Added Sugar (g) 19 Protein (g) 4  KD 4.400 100 g"
    }
  },
  {
    "type": "product",
    "title": "Chocolate Ice Cream 500 ML",
    "url": "https://eshop.kddc.com/en/Ice-Cream/Chocolate-Ice-Cream-500-ML-7483",
    "category": "ice cream",
    "text": "Chocolate Ice Cream 500 ML | ice cream | 0.5 KWD | None | chocolate | 500 ml | 100 g | | Piece | 1 piece | KWD 0.5 | Classic chocolate ice cream. Always a pleasure Nutrition Facts Per 100 g Nutrition Value Energy (Calories) 210 Calories from Fat (g) 99 Total Fat (g) 11 Saturated Fat (g) 9 Unsaturated Fat (g) 2 Trans Fat (g) 0 Cholesterol (g) 5 Sodium (mg) 0.065 Total Carbohydrate (g) 27 Dietary Fibres (g) 1 Total Sugars (g) 24 Added Sugar (g) 19 Protein (g) 4 KD 0.500 100 g",
    "meta": {
      "dedup_key": "https://eshop.kddc.com/en/Ice-Cream/Chocolate-Ice-Cream-500-ML-7483",
      "name": "Chocolate Ice Cream 500 ML",
      "brand": null,
      "category": "ice cream",
      "flavor": "chocolate",
      "volume_ml": 500,
      "weight_g": 100,
      "pack_units": null,
      "product_url": "https://eshop.kddc.com/en/Ice-Cream/Chocolate-Ice-Cream-500-ML-7483",
      "product_code": "FICFMSHLCHRCUP",
      "sku": "FICFMSHLCHRCUP",
      "availability": "in_stock",
      "price_now_kwd": 0.5,
      "options_text": "Piece | 1 piece | KWD 0.5",
      "price_notes": null,
      "reviews_count": 0,
      "rating_stars": null,
      "desc": "Classic chocolate ice cream. Always a pleasure Nutrition Facts Per 100 g Nutrition Value Energy (Calories) 210 Calories from Fat (g) 99 Total Fat (g) 11 Saturated Fat (g) 9 Unsaturated Fat (g) 2 Trans Fat (g) 0 Cholesterol (g) 5 Sodium (mg) 0.065 Total Carbohydrate (g) 27 Dietary Fibres (g) 1 Total Sugars (g) 24 Added Sugar (g) 19 Protein (g) 4  KD 0.500 100 g"
    }
  },
  {
    "type": "product",
    "title": "Chocolate Ice Cream Cups (No Added Sugar)",
    "url": "https://eshop.kddc.com/en/Ice-Cream/Chocolate-Ice-Cream-Cups-(No-Added-Sugar)-9498",
    "category": "ice cream",
    "text": "Chocolate Ice Cream Cups (No Added Sugar) | ice cream | 2.4 KWD | None | chocolate | | | | Carton - 6 Pieces | 6 pieces | KWD 2.4 | Delicious chocolate ice cream with no added sugar. Clinically tested and endorsed by Dasman Diabetes Institute. Go ahead and indulge yourself guilt-free! KD 2.400",
    "meta": {
      "dedup_key": "https://eshop.kddc.com/en/Ice-Cream/Chocolate-Ice-Cream-Cups-(No-Added-Sugar)-9498",
      "name": "Chocolate Ice Cream Cups (No Added Sugar)",
      "brand": null,
      "category": "ice cream",
      "flavor": "chocolate",
      "volume_ml": null,
      "weight_g": null,
      "pack_units": null,
      "product_url": "https://eshop.kddc.com/en/Ice-Cream/Chocolate-Ice-Cream-Cups-(No-Added-Sugar)-9498",
      "product_code": "FICNSAC167CH6GM",
      "sku": "FICNSAC167CH6GM",
      "availability": "in_stock",
      "price_now_kwd": 2.4,
      "options_text": "Carton - 6 Pieces | 6 pieces | KWD 2.4",
      "price_notes": "carton_per_piece≈0.400 KWD",
      "reviews_count": 0,
      "rating_stars": null,
      "desc": "Delicious chocolate ice cream with no added sugar. Clinically tested and endorsed by Dasman Diabetes Institute. Go ahead and indulge yourself guilt-free!  KD 2.400 "
    }
  },
  {
    "type": "product",
    "title": "Chocolate Lulu Cone",
    "url": "https://eshop.kddc.com/en/Ice-Cream/Chocolate-Lulu-Cone-7453",
    "category": "ice cream",
    "text": "Chocolate Lulu Cone | ice cream | 4.44 KWD | None | chocolate | | 89 g | | Carton - 24 Pieces | 24 pieces | KWD 4.44 | Enjoy Chocolate ice cream mixed with nougat sauce, sprinkled with crunchy almonds Nutrition Facts Per 89 g Nutrition Value Energy (Calories) 310 Calories from Fat (g) 171 Total Fat (g) 19 Saturated Fat (g) 10 Unsaturated Fat (g) 9 Trans Fat (g) 0 Cholesterol (g) 5 Sodium (mg) 0.05 Total Carbohydrate (g) 31 Dietary Fibres (g) 2 Total Sugars (g) 24 Added Sugar (g) 20.97 Protein (g) 4 KD 4.440 89 g",
    "meta": {
      "dedup_key": "https://eshop.kddc.com/en/Ice-Cream/Chocolate-Lulu-Cone-7453",
      "name": "Chocolate Lulu Cone",
      "brand": null,
      "category": "ice cream",
      "flavor": "chocolate",
      "volume_ml": null,
      "weight_g": 89,
      "pack_units": null,
      "product_url": "https://eshop.kddc.com/en/Ice-Cream/Chocolate-Lulu-Cone-7453",
      "product_code": "FICCCB100LUCH",
      "sku": "FICCCB100LUCH",
      "availability": "in_stock",
      "price_now_kwd": 4.44,
      "options_text": "Carton - 24 Pieces | 24 pieces | KWD 4.44",
      "price_notes": "carton_per_piece≈0.185 KWD",
      "reviews_count": 0,
      "rating_stars": null,
      "desc": "Enjoy Chocolate ice cream mixed with nougat sauce, sprinkled with crunchy almonds Nutrition Facts Per 89 g Nutrition Value Energy (Calories) 310 Calories from Fat (g) 171 Total Fat (g) 19 Saturated Fat (g) 10 Unsaturated Fat (g) 9 Trans Fat (g) 0 Cholesterol (g) 5 Sodium (mg) 0.05 Total Carbohydrate (g) 31 Dietary Fibres (g) 2 Total Sugars (g) 24 Added Sugar (g) 20.97 Protein (g) 4  KD 4.440 89 g"
    }
  },
  {
    "type": "product",
    "title": "Chocolate Lulu Cone (Pack of 6)",
    "url": "https://eshop.kddc.com/en/Ice-Cream/Chocolate-Lulu-Cone-(Pack-of-6)-7454",
    "category": "ice cream",
    "text": "Chocolate Lulu Cone (Pack of 6) | ice cream | 1.11 KWD | None | chocolate | | 89 g | | Carton - 6 Pieces | 6 pieces | KWD 1.11 | Enjoy Chocolate ice cream mixed with nougat sauce, sprinkled with crunchy almonds Nutrition Facts Per 89 g Nutrition Value Energy (Calories) 310 Calories from Fat (g) 171 Total Fat (g) 19 Saturated Fat (g) 10 Unsaturated Fat (g) 9 Trans Fat (g) 0 Cholesterol (g) 5 Sodium (mg) 0.05 Total Carbohydrate (g) 31 Dietary Fibres (g) 2 Total Sugars (g) 24 Added Sugar (g) 20.97 Protein (g) 4 KD 1.110 89 g",
    "meta": {
      "dedup_key": "https://eshop.kddc.com/en/Ice-Cream/Chocolate-Lulu-Cone-(Pack-of-6)-7454",
      "name": "Chocolate Lulu Cone (Pack of 6)",
      "brand": null,
      "category": "ice cream",
      "flavor": "chocolate",
      "volume_ml": null,
      "weight_g": 89,
      "pack_units": null,
      "product_url": "https://eshop.kddc.com/en/Ice-Cream/Chocolate-Lulu-Cone-(Pack-of-6)-7454",
      "product_code": "FICCCB100LUCH6",
      "sku": "FICCCB100LUCH6",
      "availability": "in_stock",
      "price_now_kwd": 1.11,
      "options_text": "Carton - 6 Pieces | 6 pieces | KWD 1.11",
      "price_notes": "carton_per_piece≈0.185 KWD",
      "reviews_count": 0,
      "rating_stars": null,
      "desc": "Enjoy Chocolate ice cream mixed with nougat sauce, sprinkled with crunchy almonds Nutrition Facts Per 89 g Nutrition Value Energy (Calories) 310 Calories from Fat (g) 171 Total Fat (g) 19 Saturated Fat (g) 10 Unsaturated Fat (g) 9 Trans Fat (g) 0 Cholesterol (g) 5 Sodium (mg) 0.05 Total Carbohydrate (g) 31 Dietary Fibres (g) 2 Total Sugars (g) 24 Added Sugar (g) 20.97 Protein (g) 4  KD 1.110 89 g"
    }
  },
  {
    "type": "product",
    "title": "Chocolate Lulu Stick",
    "url": "https://eshop.kddc.com/en/Ice-Cream/Chocolate-Lulu-Stick-7522",
    "category": "ice cream",
    "text": "Chocolate Lulu Stick | ice cream | 2.4 KWD | None | chocolate | | | | Carton - 24 Pieces | 24 pieces | KWD 2.4 | Creamy chocolate ice cream with nougat in the centre, coated with chocolate & crunchy almonds Nutrition Facts Per 1 Piece Nutrition Value Energy (Calories) 230 Calories from Fat (g) 153 Total Fat (g) 17 Saturated Fat (g) 10 Unsaturated Fat (g) 7 Trans Fat (g) 0 Cholesterol (g) 0 Sodium (mg) 0.025 Total Carbohydrate (g) 18 Dietary Fibres (g) 1 Total Sugars (g) 16 Added Sugar (g) 14 Protein (g) 2 KD 2.400",
    "meta": {
      "dedup_key": "https://eshop.kddc.com/en/Ice-Cream/Chocolate-Lulu-Stick-7522",
      "name": "Chocolate Lulu Stick",
      "brand": null,
      "category": "ice cream",
      "flavor": "chocolate",
      "volume_ml": null,
      "weight_g": null,
      "pack_units": null,
      "product_url": "https://eshop.kddc.com/en/Ice-Cream/Chocolate-Lulu-Stick-7522",
      "product_code": "FICSTL24LUCH",
      "sku": "FICSTL24LUCH",
      "availability": "in_stock",
      "price_now_kwd": 2.4,
      "options_text": "Carton - 24 Pieces | 24 pieces | KWD 2.4",
      "price_notes": "carton_per_piece≈0.100 KWD",
      "reviews_count": 1,
      "rating_stars": 10,
      "desc": "Creamy chocolate ice cream with nougat in the centre, coated with chocolate & crunchy almonds Nutrition Facts Per 1 Piece Nutrition Value Energy (Calories) 230 Calories from Fat (g) 153 Total Fat (g) 17 Saturated Fat (g) 10 Unsaturated Fat (g) 7 Trans Fat (g) 0 Cholesterol (g) 0 Sodium (mg) 0.025 Total Carbohydrate (g) 18 Dietary Fibres (g) 1 Total Sugars (g) 16 Added Sugar (g) 14 Protein (g) 2  KD 2.400 "
    }
  },
  {
    "type": "product",
    "title": "Chocolate Sandwich (48 Pieces)",
    "url": "https://eshop.kddc.com/en/Ice-Cream/Chocolate-Sandwich-(48-Pieces)-9539",
    "category": "ice cream",
    "text": "Chocolate Sandwich (48 Pieces) | ice cream | 4.8 KWD | None | chocolate | | | 48 pcs | Carton - 48 Pieces | 48 pieces | KWD 4.8 | Chocolate ice cream sandwich, perfect snack anytime of the day. KD 4.800",
    "meta": {
      "dedup_key": "https://eshop.kddc.com/en/Ice-Cream/Chocolate-Sandwich-(48-Pieces)-9539",
      "name": "Chocolate Sandwich (48 Pieces)",
      "brand": null,
      "category": "ice cream",
      "flavor": "chocolate",
      "volume_ml": null,
      "weight_g": null,
      "pack_units": 48,
      "product_url": "https://eshop.kddc.com/en/Ice-Cream/Chocolate-Sandwich-(48-Pieces)-9539",
      "product_code": "FICSBONDCH48",
      "sku": "FICSBONDCH48",
      "availability": "in_stock",
      "price_now_kwd": 4.8,
      "options_text": "Carton - 48 Pieces | 48 pieces | KWD 4.8",
      "price_notes": "carton_per_piece≈0.100 KWD",
      "reviews_count": 0,
      "rating_stars": null,
      "desc": "Chocolate ice cream sandwich, perfect snack anytime of the day.  KD 4.800 "
    }
  },
  {
    "type": "product",
    "title": "Chocolate Soft Ice Cream 1 LTR",
    "url": "https://eshop.kddc.com/en/Ice-Cream/Chocolate-Soft-Ice-Cream-1-LTR-7468",
    "category": "ice cream",
    "text": "Chocolate Soft Ice Cream 1 LTR | ice cream | 8.28 KWD | None | chocolate | 1000 ml | | | Carton - 12 Pieces | 12 pieces | KWD 8.28 || Piece | 1 piece | KWD 0.69 | Great tasting chocolate soft ice cream now made in the comfort of your home Nutrition Facts Per 100 ml. Nutrition Value Energy (Calories) 170 Calories from Fat (g) 40.5 Total Fat (g) 4.5 Saturated Fat (g) 3 Unsaturated Fat (g) 1.5 Trans Fat (g) 0 Cholesterol (g) 10 Sodium (mg) 0.055 Total Carbohydrate (g) 28 Dietary Fibres (g) 1 Total Sugars (g) 26 Added Sugar (g) 19 Protein (g) 4 Calcium (mg) 130 KD 8.280 100 ml",
    "meta": {
      "dedup_key": "https://eshop.kddc.com/en/Ice-Cream/Chocolate-Soft-Ice-Cream-1-LTR-7468",
      "name": "Chocolate Soft Ice Cream 1 LTR",
      "brand": null,
      "category": "ice cream",
      "flavor": "chocolate",
      "volume_ml": 1000,
      "weight_g": null,
      "pack_units": null,
      "product_url": "https://eshop.kddc.com/en/Ice-Cream/Chocolate-Soft-Ice-Cream-1-LTR-7468",
      "product_code": "FICFMS1LCHSFTG",
      "sku": "FICFMS1LCHSFTG",
      "availability": "in_stock",
      "price_now_kwd": 8.28,
      "options_text": "Carton - 12 Pieces | 12 pieces | KWD 8.28 || Piece | 1 piece | KWD 0.69",
      "price_notes": "carton_per_piece≈0.690 KWD",
      "reviews_count": 0,
      "rating_stars": null,
      "desc": "Great tasting chocolate soft ice cream now made in the comfort of your home Nutrition Facts Per 100 ml. Nutrition Value Energy (Calories) 170 Calories from Fat (g) 40.5 Total Fat (g) 4.5 Saturated Fat (g) 3 Unsaturated Fat (g) 1.5 Trans Fat (g) 0 Cholesterol (g) 10 Sodium (mg) 0.055 Total Carbohydrate (g) 28 Dietary Fibres (g) 1 Total Sugars (g) 26 Added Sugar (g) 19 Protein (g) 4 Calcium (mg) 130  KD 8.280 100 ml"
    }
  },
  {
    "type": "product",
    "title": "Choconuts Ice Cream 1 LTR",
    "url": "https://eshop.kddc.com/en/Ice-Cream/Choconuts-Ice-Cream-1-LTR-7469",
    "category": "ice cream",
    "text": "Choconuts Ice Cream 1 LTR | ice cream | 1.0 KWD | None | chocolate | 1000 ml | 100 g | | Piece | 1 piece | KWD 1.0 | The crunch of nuts in delicious rich chocolate ice cream Nutrition Facts Per 100 g Nutrition Value Energy (Calories) 260 Calories from Fat (g) 117 Total Fat (g) 13 Saturated Fat (g) 8 Unsaturated Fat (g) 5 Trans Fat (g) 0 Cholesterol (g) 5 Sodium (mg) 0.075 Total Carbohydrate (g) 31 Dietary Fibres (g) 2 Total Sugars (g) 28 Added Sugar (g) 23 Protein (g) 5 KD 1.000 100 g",
    "meta": {
      "dedup_key": "https://eshop.kddc.com/en/Ice-Cream/Choconuts-Ice-Cream-1-LTR-7469",
      "name": "Choconuts Ice Cream 1 LTR",
      "brand": null,
      "category": "ice cream",
      "flavor": "chocolate",
      "volume_ml": 1000,
      "weight_g": 100,
      "pack_units": null,
      "product_url": "https://eshop.kddc.com/en/Ice-Cream/Choconuts-Ice-Cream-1-LTR-7469",
      "product_code": "FICFMS1LCNRCUP",
      "sku": "FICFMS1LCNRCUP",
      "availability": "in_stock",
      "price_now_kwd": 1.0,
      "options_text": "Piece | 1 piece | KWD 1.0",
      "price_notes": null,
      "reviews_count": 0,
      "rating_stars": null,
      "desc": "The crunch of nuts in delicious rich chocolate ice cream Nutrition Facts Per 100 g Nutrition Value Energy (Calories) 260 Calories from Fat (g) 117 Total Fat (g) 13 Saturated Fat (g) 8 Unsaturated Fat (g) 5 Trans Fat (g) 0 Cholesterol (g) 5 Sodium (mg) 0.075 Total Carbohydrate (g) 31 Dietary Fibres (g) 2 Total Sugars (g) 28 Added Sugar (g) 23 Protein (g) 5  KD 1.000 100 g"
    }
  },
  {
    "type": "product",
    "title": "Columbia Sticks",
    "url": "https://eshop.kddc.com/en/Ice-Cream/Columbia-Sticks-8726",
    "category": "ice cream",
    "text": "Columbia Sticks | ice cream | 0.595 KWD | None | vanilla | | 55 g | | Carton - 6 Pieces | 6 pieces | KWD 0.595 | A blend of delicious Vanilla Ice Cream coated with fruity boysenberry. Nutrition Facts Per 55 g Nutrition Value Energy (Calories) 80 Calories from Fat (g) 27 Total Fat (g) 3 Saturated Fat (g) 2.5 Unsaturated Fat (g) 0.5 Trans Fat (g) 0 Cholesterol (g) 0 Sodium (mg) 0.015 Total Carbohydrate (g) 12 Dietary Fibres (g) 0 Total Sugars (g) 12 Added Sugar (g) 9 Protein (g) 1 KD 0.595 55 g",
    "meta": {
      "dedup_key": "https://eshop.kddc.com/en/Ice-Cream/Columbia-Sticks-8726",
      "name": "Columbia Sticks",
      "brand": null,
      "category": "ice cream",
      "flavor": "vanilla",
      "volume_ml": null,
      "weight_g": 55,
      "pack_units": null,
      "product_url": "https://eshop.kddc.com/en/Ice-Cream/Columbia-Sticks-8726",
      "product_code": "FICSTL6COLUMBIA",
      "sku": "FICSTL6COLUMBIA",
      "availability": "in_stock",
      "price_now_kwd": 0.595,
      "options_text": "Carton - 6 Pieces | 6 pieces | KWD 0.595",
      "price_notes": "carton_per_piece≈0.099 KWD",
      "reviews_count": 0,
      "rating_stars": null,
      "desc": "A blend of delicious Vanilla Ice Cream coated with fruity boysenberry. Nutrition Facts Per 55 g Nutrition Value Energy (Calories) 80 Calories from Fat (g) 27 Total Fat (g) 3 Saturated Fat (g) 2.5 Unsaturated Fat (g) 0.5 Trans Fat (g) 0 Cholesterol (g) 0 Sodium (mg) 0.015 Total Carbohydrate (g) 12 Dietary Fibres (g) 0 Total Sugars (g) 12 Added Sugar (g) 9 Protein (g) 1  KD 0.595 55 g"
    }
  },
  {
    "type": "product",
    "title": "Cream Caramel Ice Cream 1 LTR",
    "url": "https://eshop.kddc.com/en/Ice-Cream/Cream-Caramel-Ice-Cream-1-LTR-7466",
    "category": "ice cream",
    "text": "Cream Caramel Ice Cream 1 LTR | ice cream | 1.0 KWD | None | caramel | 1000 ml | 100 g | | Piece | 1 piece | KWD 1.0 | Inspired by the original cr?me caramel, adapted for ice cream Nutrition Facts Per 100 g Nutrition Value Energy (Calories) 250 Calories from Fat (g) 117 Total Fat (g) 13 Saturated Fat (g) 8 Unsaturated Fat (g) 5 Trans Fat (g) 0 Cholesterol (g) 5 Sodium (mg) 0.06 Total Carbohydrate (g) 29 Dietary Fibres (g) 1 Total Sugars (g) 27 Added Sugar (g) 22 Protein (g) 4 KD 1.000 100 g",
    "meta": {
      "dedup_key": "https://eshop.kddc.com/en/Ice-Cream/Cream-Caramel-Ice-Cream-1-LTR-7466",
      "name": "Cream Caramel Ice Cream 1 LTR",
      "brand": null,
      "category": "ice cream",
      "flavor": "caramel",
      "volume_ml": 1000,
      "weight_g": 100,
      "pack_units": null,
      "product_url": "https://eshop.kddc.com/en/Ice-Cream/Cream-Caramel-Ice-Cream-1-LTR-7466",
      "product_code": "FICFMS1LCCRCUP",
      "sku": "FICFMS1LCCRCUP",
      "availability": "in_stock",
      "price_now_kwd": 1.0,
      "options_text": "Piece | 1 piece | KWD 1.0",
      "price_notes": null,
      "reviews_count": 0,
      "rating_stars": null,
      "desc": "Inspired by the original cr?me caramel, adapted for ice cream Nutrition Facts Per 100 g Nutrition Value Energy (Calories) 250 Calories from Fat (g) 117 Total Fat (g) 13 Saturated Fat (g) 8 Unsaturated Fat (g) 5 Trans Fat (g) 0 Cholesterol (g) 5 Sodium (mg) 0.06 Total Carbohydrate (g) 29 Dietary Fibres (g) 1 Total Sugars (g) 27 Added Sugar (g) 22 Protein (g) 4  KD 1.000 100 g"
    }
  },
  {
    "type": "product",
    "title": "Failaka Sticks",
    "url": "https://eshop.kddc.com/en/Ice-Cream/Failaka-Sticks-8725",
    "category": "ice cream",
    "text": "Failaka Sticks | ice cream | 0.595 KWD | None | vanilla | | 55 g | | Carton - 6 Pieces | 6 pieces | KWD 0.595 | A blend of delicious Vanilla Ice Cream coated with the tangy Raspberry Nutrition Facts Per 55 g Nutrition Value Energy (Calories) 70 Calories from Fat (g) 27 Total Fat (g) 3 Saturated Fat (g) 2.5 Unsaturated Fat (g) 0.5 Trans Fat (g) 0 Cholesterol (g) 0 Sodium (mg) 0.015 Total Carbohydrate (g) 11 Dietary Fibres (g) 0 Total Sugars (g) 11 Added Sugar (g) 9 Protein (g) 1 KD 0.595 55 g",
    "meta": {
      "dedup_key": "https://eshop.kddc.com/en/Ice-Cream/Failaka-Sticks-8725",
      "name": "Failaka Sticks",
      "brand": null,
      "category": "ice cream",
      "flavor": "vanilla",
      "volume_ml": null,
      "weight_g": 55,
      "pack_units": null,
      "product_url": "https://eshop.kddc.com/en/Ice-Cream/Failaka-Sticks-8725",
      "product_code": "FICSTL6FAILAKA",
      "sku": "FICSTL6FAILAKA",
      "availability": "in_stock",
      "price_now_kwd": 0.595,
      "options_text": "Carton - 6 Pieces | 6 pieces | KWD 0.595",
      "price_notes": "carton_per_piece≈0.099 KWD",
      "reviews_count": 0,
      "rating_stars": null,
      "desc": "A blend of delicious Vanilla Ice Cream coated with the tangy Raspberry Nutrition Facts Per 55 g Nutrition Value Energy (Calories) 70 Calories from Fat (g) 27 Total Fat (g) 3 Saturated Fat (g) 2.5 Unsaturated Fat (g) 0.5 Trans Fat (g) 0 Cholesterol (g) 0 Sodium (mg) 0.015 Total Carbohydrate (g) 11 Dietary Fibres (g) 0 Total Sugars (g) 11 Added Sugar (g) 9 Protein (g) 1  KD 0.595 55 g"
    }
  },
  {
    "type": "product",
    "title": "Gold Cone",
    "url": "https://eshop.kddc.com/en/Ice-Cream/Gold-Cone-7452",
    "category": "ice cream",
    "text": "Gold Cone | ice cream | 3.6 KWD | None | vanilla | | | | Carton - 24 Pieces | 24 pieces | KWD 3.6 | Enjoy the delicious combination of rich and creamy vanilla ice cream sprinkled with quality almond nuts. Nutrition Facts Per 1 Piece Nutrition Value Energy (Calories) 190 Calories from Fat (g) 90 Total Fat (g) 10 Saturated Fat (g) 8 Unsaturated Fat (g) 2 Trans Fat (g) 0 Cholesterol (g) 5 Sodium (mg) 0.035 Total Carbohydrate (g) 22 Dietary Fibres (g) 1 Total Sugars (g) 16 Added Sugar (g) 13 Protein (g) 3 KD 3.600",
    "meta": {
      "dedup_key": "https://eshop.kddc.com/en/Ice-Cream/Gold-Cone-7452",
      "name": "Gold Cone",
      "brand": null,
      "category": "ice cream",
      "flavor": "vanilla",
      "volume_ml": null,
      "weight_g": null,
      "pack_units": null,
      "product_url": "https://eshop.kddc.com/en/Ice-Cream/Gold-Cone-7452",
      "product_code": "FICCCB100G",
      "sku": "FICCCB100G",
      "availability": "in_stock",
      "price_now_kwd": 3.6,
      "options_text": "Carton - 24 Pieces | 24 pieces | KWD 3.6",
      "price_notes": "carton_per_piece≈0.150 KWD",
      "reviews_count": 0,
      "rating_stars": null,
      "desc": "Enjoy the delicious combination of rich and creamy vanilla ice cream sprinkled with quality almond nuts. Nutrition Facts Per 1 Piece Nutrition Value Energy (Calories) 190 Calories from Fat (g) 90 Total Fat (g) 10 Saturated Fat (g) 8 Unsaturated Fat (g) 2 Trans Fat (g) 0 Cholesterol (g) 5 Sodium (mg) 0.035 Total Carbohydrate (g) 22 Dietary Fibres (g) 1 Total Sugars (g) 16 Added Sugar (g) 13 Protein (g) 3  KD 3.600 "
    }
  },
  {
    "type": "product",
    "title": "Gold Cone (Pack of 6)",
    "url": "https://eshop.kddc.com/en/Ice-Cream/Gold-Cone-(Pack-of-6)-7463",
    "category": "ice cream",
    "text": "Gold Cone (Pack of 6) | ice cream | 0.9 KWD | None | vanilla | | | | Piece | 1 piece | KWD 0.9 | Enjoy the delicious combination of rich and creamy vanilla ice cream sprinkled with quality almond nuts. Nutrition Facts Per 1 Piece Nutrition Value Energy (Calories) 190 Calories from Fat (g) 90 Total Fat (g) 10 Saturated Fat (g) 8 Unsaturated Fat (g) 2 Trans Fat (g) 0 Cholesterol (g) 5 Sodium (mg) 0.035 Total Carbohydrate (g) 22 Dietary Fibres (g) 1 Total Sugars (g) 16 Added Sugar (g) 13 Protein (g) 3 KD 0.900",
    "meta": {
      "dedup_key": "https://eshop.kddc.com/en/Ice-Cream/Gold-Cone-(Pack-of-6)-7463",
      "name": "Gold Cone (Pack of 6)",
      "brand": null,
      "category": "ice cream",
      "flavor": "vanilla",
      "volume_ml": null,
      "weight_g": null,
      "pack_units": null,
      "product_url": "https://eshop.kddc.com/en/Ice-Cream/Gold-Cone-(Pack-of-6)-7463",
      "product_code": "FICCCBGOLD6",
      "sku": "FICCCBGOLD6",
      "availability": "in_stock",
      "price_now_kwd": 0.9,
      "options_text": "Piece | 1 piece | KWD 0.9",
      "price_notes": null,
      "reviews_count": 0,
      "rating_stars": null,
      "desc": "Enjoy the delicious combination of rich and creamy vanilla ice cream sprinkled with quality almond nuts. Nutrition Facts Per 1 Piece Nutrition Value Energy (Calories) 190 Calories from Fat (g) 90 Total Fat (g) 10 Saturated Fat (g) 8 Unsaturated Fat (g) 2 Trans Fat (g) 0 Cholesterol (g) 5 Sodium (mg) 0.035 Total Carbohydrate (g) 22 Dietary Fibres (g) 1 Total Sugars (g) 16 Added Sugar (g) 13 Protein (g) 3  KD 0.900 "
    }
  },
  {
    "type": "product",
    "title": "Hamba Sticks",
    "url": "https://eshop.kddc.com/en/Ice-Cream/Hamba-Sticks-8716",
    "category": "ice cream",
    "text": "Hamba Sticks | ice cream | 0.595 KWD | None | vanilla | | | | Carton - 6 Pieces | 6 pieces | KWD 0.595 | A blend of creamy vanilla ice cream with the real taste of mango. Nutrition Facts Per 1 Piece Nutrition Value Energy (Calories) 70 Calories from Fat (g) 27 Total Fat (g) 3 Saturated Fat (g) 2.5 Unsaturated Fat (g) 0.5 Trans Fat (g) 0 Cholesterol (g) 0 Sodium (mg) 0.015 Total Carbohydrate (g) 12 Dietary Fibres (g) 0 Total Sugars (g) 11 Added Sugar (g) 9 Protein (g) 1 KD 0.595",
    "meta": {
      "dedup_key": "https://eshop.kddc.com/en/Ice-Cream/Hamba-Sticks-8716",
      "name": "Hamba Sticks",
      "brand": null,
      "category": "ice cream",
      "flavor": "vanilla",
      "volume_ml": null,
      "weight_g": null,
      "pack_units": null,
      "product_url": "https://eshop.kddc.com/en/Ice-Cream/Hamba-Sticks-8716",
      "product_code": "FICSTL6HAMBA",
      "sku": "FICSTL6HAMBA",
      "availability": "in_stock",
      "price_now_kwd": 0.595,
      "options_text": "Carton - 6 Pieces | 6 pieces | KWD 0.595",
      "price_notes": "carton_per_piece≈0.099 KWD",
      "reviews_count": 0,
      "rating_stars": null,
      "desc": "A blend of creamy vanilla ice cream with the real taste of mango. Nutrition Facts Per 1 Piece Nutrition Value Energy (Calories) 70 Calories from Fat (g) 27 Total Fat (g) 3 Saturated Fat (g) 2.5 Unsaturated Fat (g) 0.5 Trans Fat (g) 0 Cholesterol (g) 0 Sodium (mg) 0.015 Total Carbohydrate (g) 12 Dietary Fibres (g) 0 Total Sugars (g) 11 Added Sugar (g) 9 Protein (g) 1  KD 0.595 "
    }
  },
  {
    "type": "product",
    "title": "Ice Cream Biscuits",
    "url": "https://eshop.kddc.com/en/Ice-Cream/Ice-Cream-Biscuits-8698",
    "category": "ice cream",
    "text": "Ice Cream Biscuits | ice cream | 3.0 KWD | None | None | | 100 g | | Carton - 144 Pieces | 144 pieces | KWD 3.0 || Pack of 24 Pieces | 24 pieces | KWD 0.5 | Enjoy crunchy biscuits with tea, ice cream, dessert or on its own. Great mid day snack Nutrition Facts Per 100 g Nutrition Value Energy (Calories) 413 Calories from Fat (g) 54.9 Total Fat (g) 6.1 Saturated Fat (g) 2.99 Unsaturated Fat (g) 3.11 Trans Fat (g) 0.04 Cholesterol (g) 0 Sodium (mg) 0.55 Total Carbohydrate (g) 83.8 Dietary Fibres (g) 2.05 Total Sugars (g) 29.7 Added Sugar (g) 28.4 Protein (g) 5.7 KD 3.000 100 g",
    "meta": {
      "dedup_key": "https://eshop.kddc.com/en/Ice-Cream/Ice-Cream-Biscuits-8698",
      "name": "Ice Cream Biscuits",
      "brand": null,
      "category": "ice cream",
      "flavor": null,
      "volume_ml": null,
      "weight_g": 100,
      "pack_units": null,
      "product_url": "https://eshop.kddc.com/en/Ice-Cream/Ice-Cream-Biscuits-8698",
      "product_code": "FICSNDBSCSAL",
      "sku": "FICSNDBSCSAL",
      "availability": "in_stock",
      "price_now_kwd": 3.0,
      "options_text": "Carton - 144 Pieces | 144 pieces | KWD 3.0 || Pack of 24 Pieces | 24 pieces | KWD 0.5",
      "price_notes": "carton_per_piece≈0.021 KWD",
      "reviews_count": 0,
      "rating_stars": null,
      "desc": "Enjoy crunchy biscuits with tea, ice cream, dessert or on its own. Great mid day snack Nutrition Facts Per 100 g Nutrition Value Energy (Calories) 413 Calories from Fat (g) 54.9 Total Fat (g) 6.1 Saturated Fat (g) 2.99 Unsaturated Fat (g) 3.11 Trans Fat (g) 0.04 Cholesterol (g) 0 Sodium (mg) 0.55 Total Carbohydrate (g) 83.8 Dietary Fibres (g) 2.05 Total Sugars (g) 29.7 Added Sugar (g) 28.4 Protein (g) 5.7  KD 3.000 100 g"
    }
  },
  {
    "type": "product",
    "title": "Ice Cream Crunchy Cup Cones (B)",
    "url": "https://eshop.kddc.com/en/Ice-Cream/Ice-Cream-Crunchy-Cup-Cones-(B)-8596",
    "category": "ice cream",
    "text": "Ice Cream Crunchy Cup Cones (B) | ice cream | 0.745 KWD | None | None | | 4 g | | Carton - 24 Pieces | 24 pieces | KWD 0.745 | Enjoy the crunch with a scoop of your favourite KDD ice cream and your choice of toppings Nutrition Facts Per 4.5 g Nutrition Value Energy (Calories) 0 Calories from Fat (g) 15 Total Fat (g) 0 Saturated Fat (g) 0 Unsaturated Fat (g) 0 Trans Fat (g) 0 Cholesterol (g) 0 Sodium (mg) 0 Total Carbohydrate (g) 0.01 Dietary Fibres (g) 3 Total Sugars (g) 0 Added Sugar (g) 0 Protein (g) 0 KD 0.745 4.5 g",
    "meta": {
      "dedup_key": "https://eshop.kddc.com/en/Ice-Cream/Ice-Cream-Crunchy-Cup-Cones-(B)-8596",
      "name": "Ice Cream Crunchy Cup Cones (B)",
      "brand": null,
      "category": "ice cream",
      "flavor": null,
      "volume_ml": null,
      "weight_g": 4,
      "pack_units": null,
      "product_url": "https://eshop.kddc.com/en/Ice-Cream/Ice-Cream-Crunchy-Cup-Cones-(B)-8596",
      "product_code": "FICWCOCOMM24",
      "sku": "FICWCOCOMM24",
      "availability": "in_stock",
      "price_now_kwd": 0.745,
      "options_text": "Carton - 24 Pieces | 24 pieces | KWD 0.745",
      "price_notes": "carton_per_piece≈0.031 KWD",
      "reviews_count": 0,
      "rating_stars": null,
      "desc": "Enjoy the crunch with a scoop of your favourite KDD ice cream and your choice of toppings Nutrition Facts Per 4.5 g Nutrition Value Energy (Calories) 0 Calories from Fat (g) 15 Total Fat (g) 0 Saturated Fat (g) 0 Unsaturated Fat (g) 0 Trans Fat (g) 0 Cholesterol (g) 0 Sodium (mg) 0 Total Carbohydrate (g) 0.01 Dietary Fibres (g) 3 Total Sugars (g) 0 Added Sugar (g) 0 Protein (g) 0  KD 0.745 4.5 g"
    }
  },
  {
    "type": "product",
    "title": "Ice Cream Crunchy Sugar Cones (R)",
    "url": "https://eshop.kddc.com/en/Ice-Cream/Ice-Cream-Crunchy-Sugar-Cones-(R)-8595",
    "category": "ice cream",
    "text": "Ice Cream Crunchy Sugar Cones (R) | ice cream | 0.775 KWD | None | None | | 11 g | | Carton - 24 Pieces | 24 pieces | KWD 0.775 | Enjoy the crunch with a scoop of your favourite KDD ice cream and your choice of toppings Nutrition Facts Per 11 g Nutrition Value Energy (Calories) 45 Calories from Fat (g) 4.5 Total Fat (g) 0.5 Saturated Fat (g) 0 Unsaturated Fat (g) 0.5 Trans Fat (g) 0 Cholesterol (g) 0 Sodium (mg) 0.01 Total Carbohydrate (g) 9 Dietary Fibres (g) 0 Total Sugars (g) 3 Added Sugar (g) 3 Protein (g) 1 KD 0.775 11 g",
    "meta": {
      "dedup_key": "https://eshop.kddc.com/en/Ice-Cream/Ice-Cream-Crunchy-Sugar-Cones-(R)-8595",
      "name": "Ice Cream Crunchy Sugar Cones (R)",
      "brand": null,
      "category": "ice cream",
      "flavor": null,
      "volume_ml": null,
      "weight_g": 11,
      "pack_units": null,
      "product_url": "https://eshop.kddc.com/en/Ice-Cream/Ice-Cream-Crunchy-Sugar-Cones-(R)-8595",
      "product_code": "FICSUGCOCO24",
      "sku": "FICSUGCOCO24",
      "availability": "in_stock",
      "price_now_kwd": 0.775,
      "options_text": "Carton - 24 Pieces | 24 pieces | KWD 0.775",
      "price_notes": "carton_per_piece≈0.032 KWD",
      "reviews_count": 0,
      "rating_stars": null,
      "desc": "Enjoy the crunch with a scoop of your favourite KDD ice cream and your choice of toppings Nutrition Facts Per 11 g Nutrition Value Energy (Calories) 45 Calories from Fat (g) 4.5 Total Fat (g) 0.5 Saturated Fat (g) 0 Unsaturated Fat (g) 0.5 Trans Fat (g) 0 Cholesterol (g) 0 Sodium (mg) 0.01 Total Carbohydrate (g) 9 Dietary Fibres (g) 0 Total Sugars (g) 3 Added Sugar (g) 3 Protein (g) 1  KD 0.775 11 g"
    }
  },
  {
    "type": "product",
    "title": "KDD VANILLA SOFT ICE MIX 1 LTR TGA",
    "url": "https://eshop.kddc.com/en/Ice-Cream/Vanilla-Soft-Ice-Cream-1-LTR-7478",
    "category": "ice cream",
    "text": "KDD VANILLA SOFT ICE MIX 1 LTR TGA | ice cream | 8.28 KWD | None | vanilla | 1000 ml | | | Carton - 12 Pieces | 12 pieces | KWD 8.28 || Piece | 1 piece | KWD 0.69 | Great tasting vanilla soft ice cream now made in the comfort of your home Nutrition Facts Per 100 ml. Nutrition Value Energy (Calories) 160 Calories from Fat (g) 40.5 Total Fat (g) 4.5 Saturated Fat (g) 3.5 Unsaturated Fat (g) 1 Trans Fat (g) 0 Cholesterol (g) 10 Sodium (mg) 0.055 Total Carbohydrate (g) 27 Dietary Fibres (g) 0 Total Sugars (g) 25 Added Sugar (g) 17 Protein (g) 3 Calcium (mg) 130 KD 8.280 100 ml",
    "meta": {
      "dedup_key": "https://eshop.kddc.com/en/Ice-Cream/Vanilla-Soft-Ice-Cream-1-LTR-7478",
      "name": "KDD VANILLA SOFT ICE MIX 1 LTR TGA",
      "brand": null,
      "category": "ice cream",
      "flavor": "vanilla",
      "volume_ml": 1000,
      "weight_g": null,
      "pack_units": null,
      "product_url": "https://eshop.kddc.com/en/Ice-Cream/Vanilla-Soft-Ice-Cream-1-LTR-7478",
      "product_code": "FICFMS1LVNSFTG",
      "sku": "FICFMS1LVNSFTG",
      "availability": "in_stock",
      "price_now_kwd": 8.28,
      "options_text": "Carton - 12 Pieces | 12 pieces | KWD 8.28 || Piece | 1 piece | KWD 0.69",
      "price_notes": "carton_per_piece≈0.690 KWD",
      "reviews_count": 0,
      "rating_stars": null,
      "desc": "Great tasting vanilla soft ice cream now made in the comfort of your home Nutrition Facts Per 100 ml. Nutrition Value Energy (Calories) 160 Calories from Fat (g) 40.5 Total Fat (g) 4.5 Saturated Fat (g) 3.5 Unsaturated Fat (g) 1 Trans Fat (g) 0 Cholesterol (g) 10 Sodium (mg) 0.055 Total Carbohydrate (g) 27 Dietary Fibres (g) 0 Total Sugars (g) 25 Added Sugar (g) 17 Protein (g) 3 Calcium (mg) 130  KD 8.280 100 ml"
    }
  },
  {
    "type": "product",
    "title": "Mango Ice Cream 1 LTR",
    "url": "https://eshop.kddc.com/en/Ice-Cream/Mango-Ice-Cream-1-LTR-7470",
    "category": "ice cream",
    "text": "Mango Ice Cream 1 LTR | ice cream | 1.0 KWD | None | mango | 1000 ml | 100 g | | Piece | 1 piece | KWD 1.0 | Classic mango ice cream. Always a pleasure Nutrition Facts Per 100 g Nutrition Value Energy (Calories) 200 Calories from Fat (g) 90 Total Fat (g) 10 Saturated Fat (g) 9 Unsaturated Fat (g) 1 Trans Fat (g) 0 Cholesterol (g) 5 Sodium (mg) 0.045 Total Carbohydrate (g) 24 Dietary Fibres (g) 0 Total Sugars (g) 24 Added Sugar (g) 17 Protein (g) 3 KD 1.000 100 g",
    "meta": {
      "dedup_key": "https://eshop.kddc.com/en/Ice-Cream/Mango-Ice-Cream-1-LTR-7470",
      "name": "Mango Ice Cream 1 LTR",
      "brand": null,
      "category": "ice cream",
      "flavor": "mango",
      "volume_ml": 1000,
      "weight_g": 100,
      "pack_units": null,
      "product_url": "https://eshop.kddc.com/en/Ice-Cream/Mango-Ice-Cream-1-LTR-7470",
      "product_code": "FICFMS1LMGRCUP",
      "sku": "FICFMS1LMGRCUP",
      "availability": "in_stock",
      "price_now_kwd": 1.0,
      "options_text": "Piece | 1 piece | KWD 1.0",
      "price_notes": null,
      "reviews_count": 0,
      "rating_stars": null,
      "desc": "Classic mango ice cream. Always a pleasure Nutrition Facts Per 100 g Nutrition Value Energy (Calories) 200 Calories from Fat (g) 90 Total Fat (g) 10 Saturated Fat (g) 9 Unsaturated Fat (g) 1 Trans Fat (g) 0 Cholesterol (g) 5 Sodium (mg) 0.045 Total Carbohydrate (g) 24 Dietary Fibres (g) 0 Total Sugars (g) 24 Added Sugar (g) 17 Protein (g) 3  KD 1.000 100 g"
    }
  },
  {
    "type": "product",
    "title": "Mango Ice Cream 5 LTR",
    "url": "https://eshop.kddc.com/en/Ice-Cream/Mango-Ice-Cream-5-LTR-7480",
    "category": "ice cream",
    "text": "Mango Ice Cream 5 LTR | ice cream | 4.4 KWD | None | mango | 5000 ml | 100 g | | Piece | 1 piece | KWD 4.4 | Classic mango ice cream. Always a pleasure Nutrition Facts Per 100 g Nutrition Value Energy (Calories) 200 Calories from Fat (g) 90 Total Fat (g) 10 Saturated Fat (g) 9 Unsaturated Fat (g) 1 Trans Fat (g) 0 Cholesterol (g) 5 Sodium (mg) 0.045 Total Carbohydrate (g) 24 Dietary Fibres (g) 0 Total Sugars (g) 24 Added Sugar (g) 17 Protein (g) 3 KD 4.400 100 g",
    "meta": {
      "dedup_key": "https://eshop.kddc.com/en/Ice-Cream/Mango-Ice-Cream-5-LTR-7480",
      "name": "Mango Ice Cream 5 LTR",
      "brand": null,
      "category": "ice cream",
      "flavor": "mango",
      "volume_ml": 5000,
      "weight_g": 100,
      "pack_units": null,
      "product_url": "https://eshop.kddc.com/en/Ice-Cream/Mango-Ice-Cream-5-LTR-7480",
      "product_code": "FICFMS5LMG",
      "sku": "FICFMS5LMG",
      "availability": "in_stock",
      "price_now_kwd": 4.4,
      "options_text": "Piece | 1 piece | KWD 4.4",
      "price_notes": null,
      "reviews_count": 0,
      "rating_stars": null,
      "desc": "Classic mango ice cream. Always a pleasure Nutrition Facts Per 100 g Nutrition Value Energy (Calories) 200 Calories from Fat (g) 90 Total Fat (g) 10 Saturated Fat (g) 9 Unsaturated Fat (g) 1 Trans Fat (g) 0 Cholesterol (g) 5 Sodium (mg) 0.045 Total Carbohydrate (g) 24 Dietary Fibres (g) 0 Total Sugars (g) 24 Added Sugar (g) 17 Protein (g) 3  KD 4.400 100 g"
    }
  },
  {
    "type": "product",
    "title": "Mango Ice Cream 500 ML",
    "url": "https://eshop.kddc.com/en/Ice-Cream/Mango-Ice-Cream-500-ML-7485",
    "category": "ice cream",
    "text": "Mango Ice Cream 500 ML | ice cream | 0.5 KWD | None | mango | 500 ml | 100 g | | Piece | 1 piece | KWD 0.5 | Classic mango ice cream. Always a pleasure Nutrition Facts Per 100 g Nutrition Value Energy (Calories) 200 Calories from Fat (g) 90 Total Fat (g) 10 Saturated Fat (g) 9 Unsaturated Fat (g) 1 Trans Fat (g) 0 Cholesterol (g) 5 Sodium (mg) 0.045 Total Carbohydrate (g) 24 Dietary Fibres (g) 0 Total Sugars (g) 24 Added Sugar (g) 17 Protein (g) 3 KD 0.500 100 g",
    "meta": {
      "dedup_key": "https://eshop.kddc.com/en/Ice-Cream/Mango-Ice-Cream-500-ML-7485",
      "name": "Mango Ice Cream 500 ML",
      "brand": null,
      "category": "ice cream",
      "flavor": "mango",
      "volume_ml": 500,
      "weight_g": 100,
      "pack_units": null,
      "product_url": "https://eshop.kddc.com/en/Ice-Cream/Mango-Ice-Cream-500-ML-7485",
      "product_code": "FICFMSHLMGRCUP",
      "sku": "FICFMSHLMGRCUP",
      "availability": "in_stock",
      "price_now_kwd": 0.5,
      "options_text": "Piece | 1 piece | KWD 0.5",
      "price_notes": null,
      "reviews_count": 0,
      "rating_stars": null,
      "desc": "Classic mango ice cream. Always a pleasure Nutrition Facts Per 100 g Nutrition Value Energy (Calories) 200 Calories from Fat (g) 90 Total Fat (g) 10 Saturated Fat (g) 9 Unsaturated Fat (g) 1 Trans Fat (g) 0 Cholesterol (g) 5 Sodium (mg) 0.045 Total Carbohydrate (g) 24 Dietary Fibres (g) 0 Total Sugars (g) 24 Added Sugar (g) 17 Protein (g) 3  KD 0.500 100 g"
    }
  },
  {
    "type": "product",
    "title": "Orange Lolly Sticks 48 Pcs",
    "url": "https://eshop.kddc.com/en/Ice-Cream/Orange-Lolly-Sticks-48-Pcs-8700",
    "category": "ice cream",
    "text": "Orange Lolly Sticks 48 Pcs | ice cream | 2.16 KWD | None | orange | | | 48 pcs | Carton - 48 Pieces | 48 pieces | KWD 2.16 | Exciting orange flavored ice lolly, a favourite among kids. No artificial colours Nutrition Facts Per 1 Piece Nutrition Value Energy (Calories) 50 Calories from Fat (g) 0 Total Fat (g) 0 Saturated Fat (g) 0 Unsaturated Fat (g) 0 Trans Fat (g) 0 Cholesterol (g) 0 Sodium (mg) 0 Total Carbohydrate (g) 13 Dietary Fibres (g) 0 Total Sugars (g) 13 Added Sugar (g) 13 Protein (g) 0 KD 2.160",
    "meta": {
      "dedup_key": "https://eshop.kddc.com/en/Ice-Cream/Orange-Lolly-Sticks-48-Pcs-8700",
      "name": "Orange Lolly Sticks 48 Pcs",
      "brand": null,
      "category": "ice cream",
      "flavor": "orange",
      "volume_ml": null,
      "weight_g": null,
      "pack_units": 48,
      "product_url": "https://eshop.kddc.com/en/Ice-Cream/Orange-Lolly-Sticks-48-Pcs-8700",
      "product_code": "FICSTL48ORGSTK",
      "sku": "FICSTL48ORGSTK",
      "availability": "in_stock",
      "price_now_kwd": 2.16,
      "options_text": "Carton - 48 Pieces | 48 pieces | KWD 2.16",
      "price_notes": "carton_per_piece≈0.045 KWD",
      "reviews_count": 0,
      "rating_stars": null,
      "desc": "Exciting orange flavored ice lolly, a favourite among kids. No artificial colours Nutrition Facts Per 1 Piece Nutrition Value Energy (Calories) 50 Calories from Fat (g) 0 Total Fat (g) 0 Saturated Fat (g) 0 Unsaturated Fat (g) 0 Trans Fat (g) 0 Cholesterol (g) 0 Sodium (mg) 0 Total Carbohydrate (g) 13 Dietary Fibres (g) 0 Total Sugars (g) 13 Added Sugar (g) 13 Protein (g) 0  KD 2.160 "
    }
  },
  {
    "type": "product",
    "title": "Primo Cones (Vanilla & Chocolate with Almonds) (24 Pcs)",
    "url": "https://eshop.kddc.com/en/Ice-Cream/Primo-Cones-(Vanilla--and--Chocolate-with-Almonds)-(24-Pcs)-8691",
    "category": "ice cream",
    "text": "Primo Cones (Vanilla & Chocolate with Almonds) (24 Pcs) | ice cream | 3.6 KWD | None | vanilla | | | 24 pcs | Carton - 24 Pieces | 24 pieces | KWD 3.6 | Enjoy the combination of rich and creamy vanilla & chocolate Ice cream Nutrition Facts Per 1 Piece Nutrition Value Energy (Calories) 190 Calories from Fat (g) 90 Total Fat (g) 10 Saturated Fat (g) 7 Unsaturated Fat (g) 3 Trans Fat (g) 0 Cholesterol (g) 5 Sodium (mg) 0.035 Total Carbohydrate (g) 23 Dietary Fibres (g) 1 Total Sugars (g) 16 Added Sugar (g) 13 Protein (g) 3 KD 3.600",
    "meta": {
      "dedup_key": "https://eshop.kddc.com/en/Ice-Cream/Primo-Cones-(Vanilla--and--Chocolate-with-Almonds)-(24-Pcs)-8691",
      "name": "Primo Cones (Vanilla & Chocolate with Almonds) (24 Pcs)",
      "brand": null,
      "category": "ice cream",
      "flavor": "vanilla",
      "volume_ml": null,
      "weight_g": null,
      "pack_units": 24,
      "product_url": "https://eshop.kddc.com/en/Ice-Cream/Primo-Cones-(Vanilla--and--Chocolate-with-Almonds)-(24-Pcs)-8691",
      "product_code": "FICCCB100CVCTP",
      "sku": "FICCCB100CVCTP",
      "availability": "in_stock",
      "price_now_kwd": 3.6,
      "options_text": "Carton - 24 Pieces | 24 pieces | KWD 3.6",
      "price_notes": "carton_per_piece≈0.150 KWD",
      "reviews_count": 0,
      "rating_stars": null,
      "desc": "Enjoy the combination of rich and creamy vanilla & chocolate Ice cream Nutrition Facts Per 1 Piece Nutrition Value Energy (Calories) 190 Calories from Fat (g) 90 Total Fat (g) 10 Saturated Fat (g) 7 Unsaturated Fat (g) 3 Trans Fat (g) 0 Cholesterol (g) 5 Sodium (mg) 0.035 Total Carbohydrate (g) 23 Dietary Fibres (g) 1 Total Sugars (g) 16 Added Sugar (g) 13 Protein (g) 3  KD 3.600 "
    }
  },
  {
    "type": "product",
    "title": "Primo Cones (Vanilla & Chocolate with Almonds) (6 Pcs)",
    "url": "https://eshop.kddc.com/en/Ice-Cream/Primo-Cones-(Vanilla--and--Chocolate-with-Almonds)-(6-Pcs)-8692",
    "category": "ice cream",
    "text": "Primo Cones (Vanilla & Chocolate with Almonds) (6 Pcs) | ice cream | 0.9 KWD | None | vanilla | | | 6 pcs | Carton - 6 Pieces | 6 pieces | KWD 0.9 | Enjoy the combination of rich and creamy vanilla & chocolate Ice cream Nutrition Facts Per 1 Piece Nutrition Value Energy (Calories) 190 Calories from Fat (g) 90 Total Fat (g) 10 Saturated Fat (g) 7 Unsaturated Fat (g) 3 Trans Fat (g) 0 Cholesterol (g) 5 Sodium (mg) 0.035 Total Carbohydrate (g) 23 Dietary Fibres (g) 1 Total Sugars (g) 16 Added Sugar (g) 13 Protein (g) 3 KD 0.900",
    "meta": {
      "dedup_key": "https://eshop.kddc.com/en/Ice-Cream/Primo-Cones-(Vanilla--and--Chocolate-with-Almonds)-(6-Pcs)-8692",
      "name": "Primo Cones (Vanilla & Chocolate with Almonds) (6 Pcs)",
      "brand": null,
      "category": "ice cream",
      "flavor": "vanilla",
      "volume_ml": null,
      "weight_g": null,
      "pack_units": 6,
      "product_url": "https://eshop.kddc.com/en/Ice-Cream/Primo-Cones-(Vanilla--and--Chocolate-with-Almonds)-(6-Pcs)-8692",
      "product_code": "FICCCB100CVCTP6",
      "sku": "FICCCB100CVCTP6",
      "availability": "in_stock",
      "price_now_kwd": 0.9,
      "options_text": "Carton - 6 Pieces | 6 pieces | KWD 0.9",
      "price_notes": "carton_per_piece≈0.150 KWD",
      "reviews_count": 0,
      "rating_stars": null,
      "desc": "Enjoy the combination of rich and creamy vanilla & chocolate Ice cream Nutrition Facts Per 1 Piece Nutrition Value Energy (Calories) 190 Calories from Fat (g) 90 Total Fat (g) 10 Saturated Fat (g) 7 Unsaturated Fat (g) 3 Trans Fat (g) 0 Cholesterol (g) 5 Sodium (mg) 0.035 Total Carbohydrate (g) 23 Dietary Fibres (g) 1 Total Sugars (g) 16 Added Sugar (g) 13 Protein (g) 3  KD 0.900 "
    }
  },
  {
    "type": "product",
    "title": "Primo Vanilla & Chocolate with Almonds Cups (24 Pcs)",
    "url": "https://eshop.kddc.com/en/Ice-Cream/Primo-Vanilla--and--Chocolate-with-Almonds-Cups-(24-Pcs)-8690",
    "category": "ice cream",
    "text": "Primo Vanilla & Chocolate with Almonds Cups (24 Pcs) | ice cream | 2.4 KWD | None | vanilla | | | 24 pcs | Carton - 24 Pieces | 24 pieces | KWD 2.4 | Enjoy the combination of rich and creamy vanilla & chocolate Ice cream KD 2.400",
    "meta": {
      "dedup_key": "https://eshop.kddc.com/en/Ice-Cream/Primo-Vanilla--and--Chocolate-with-Almonds-Cups-(24-Pcs)-8690",
      "name": "Primo Vanilla & Chocolate with Almonds Cups (24 Pcs)",
      "brand": null,
      "category": "ice cream",
      "flavor": "vanilla",
      "volume_ml": null,
      "weight_g": null,
      "pack_units": 24,
      "product_url": "https://eshop.kddc.com/en/Ice-Cream/Primo-Vanilla--and--Chocolate-with-Almonds-Cups-(24-Pcs)-8690",
      "product_code": "FICCCB100CHVNTP",
      "sku": "FICCCB100CHVNTP",
      "availability": "in_stock",
      "price_now_kwd": 2.4,
      "options_text": "Carton - 24 Pieces | 24 pieces | KWD 2.4",
      "price_notes": "carton_per_piece≈0.100 KWD",
      "reviews_count": 0,
      "rating_stars": null,
      "desc": "Enjoy the combination of rich and creamy vanilla & chocolate Ice cream  KD 2.400 "
    }
  },
  {
    "type": "product",
    "title": "Raspberry Lolly Sticks 48 Pcs",
    "url": "https://eshop.kddc.com/en/Ice-Cream/Raspberry-Lolly-Sticks-48-Pcs-8701",
    "category": "ice cream",
    "text": "Raspberry Lolly Sticks 48 Pcs | ice cream | 2.16 KWD | None | None | | | 48 pcs | Carton - 48 Pieces | 48 pieces | KWD 2.16 | Exciting rasberry flavored ice lolly, a favourite among kids. No artificial colours Nutrition Facts Per 1 Piece Nutrition Value Energy (Calories) 50 Calories from Fat (g) 0 Total Fat (g) 0 Saturated Fat (g) 0 Unsaturated Fat (g) 0 Trans Fat (g) 0 Cholesterol (g) 0 Sodium (mg) 0 Total Carbohydrate (g) 13 Dietary Fibres (g) 0 Total Sugars (g) 13 Added Sugar (g) 13 Protein (g) 0 KD 2.160",
    "meta": {
      "dedup_key": "https://eshop.kddc.com/en/Ice-Cream/Raspberry-Lolly-Sticks-48-Pcs-8701",
      "name": "Raspberry Lolly Sticks 48 Pcs",
      "brand": null,
      "category": "ice cream",
      "flavor": null,
      "volume_ml": null,
      "weight_g": null,
      "pack_units": 48,
      "product_url": "https://eshop.kddc.com/en/Ice-Cream/Raspberry-Lolly-Sticks-48-Pcs-8701",
      "product_code": "FICSTL48RSBSTK",
      "sku": "FICSTL48RSBSTK",
      "availability": "out_of_stock",
      "price_now_kwd": 2.16,
      "options_text": "Carton - 48 Pieces | 48 pieces | KWD 2.16",
      "price_notes": "carton_per_piece≈0.045 KWD",
      "reviews_count": 0,
      "rating_stars": null,
      "desc": "Exciting rasberry flavored ice lolly, a favourite among kids. No artificial colours Nutrition Facts Per 1 Piece Nutrition Value Energy (Calories) 50 Calories from Fat (g) 0 Total Fat (g) 0 Saturated Fat (g) 0 Unsaturated Fat (g) 0 Trans Fat (g) 0 Cholesterol (g) 0 Sodium (mg) 0 Total Carbohydrate (g) 13 Dietary Fibres (g) 0 Total Sugars (g) 13 Added Sugar (g) 13 Protein (g) 0  KD 2.160 "
    }
  },
  {
    "type": "product",
    "title": "Rocket Lolly",
    "url": "https://eshop.kddc.com/en/Ice-Cream/Rocket--Lolly-7534",
    "category": "ice cream",
    "text": "Rocket Lolly | ice cream | 2.16 KWD | None | None | | | | Carton - 48 Pieces | 48 pieces | KWD 2.16 | Exciting multi- flavored ice lolly in the shape of a rocket. No artificial colours Nutrition Facts Per 1 Piece Nutrition Value Energy (Calories) 0 Calories from Fat (g) 50 Total Fat (g) 0 Saturated Fat (g) 0 Unsaturated Fat (g) 0 Trans Fat (g) 0 Cholesterol (g) 0 Sodium (mg) 0 Total Carbohydrate (g) 0 Dietary Fibres (g) 13 Total Sugars (g) 0 Added Sugar (g) 13 Protein (g) 13 KD 2.160",
    "meta": {
      "dedup_key": "https://eshop.kddc.com/en/Ice-Cream/Rocket--Lolly-7534",
      "name": "Rocket Lolly",
      "brand": null,
      "category": "ice cream",
      "flavor": null,
      "volume_ml": null,
      "weight_g": null,
      "pack_units": null,
      "product_url": "https://eshop.kddc.com/en/Ice-Cream/Rocket--Lolly-7534",
      "product_code": "FICSTLLOSRK",
      "sku": "FICSTLLOSRK",
      "availability": "in_stock",
      "price_now_kwd": 2.16,
      "options_text": "Carton - 48 Pieces | 48 pieces | KWD 2.16",
      "price_notes": "carton_per_piece≈0.045 KWD",
      "reviews_count": 1,
      "rating_stars": 10,
      "desc": "Exciting multi- flavored ice lolly in the shape of a rocket. No artificial colours Nutrition Facts Per 1 Piece Nutrition Value Energy (Calories) 0 Calories from Fat (g) 50 Total Fat (g) 0 Saturated Fat (g) 0 Unsaturated Fat (g) 0 Trans Fat (g) 0 Cholesterol (g) 0 Sodium (mg) 0 Total Carbohydrate (g) 0 Dietary Fibres (g) 13 Total Sugars (g) 0 Added Sugar (g) 13 Protein (g) 13  KD 2.160 "
    }
  },
  {
    "type": "product",
    "title": "Silver Cone",
    "url": "https://eshop.kddc.com/en/Ice-Cream/Silver-Cone-7457",
    "category": "ice cream",
    "text": "Silver Cone | ice cream | 3.6 KWD | None | chocolate | | | | Carton - 24 Pieces | 24 pieces | KWD 3.6 | Enjoy Creamy chocolate ice cream sprinkled with quality chocolate pieces. Nutrition Facts Per 1 Piece Nutrition Value Energy (Calories) 220 Calories from Fat (g) 90 Total Fat (g) 10 Saturated Fat (g) 8 Unsaturated Fat (g) 2 Trans Fat (g) 0 Cholesterol (g) 5 Sodium (mg) 0.055 Total Carbohydrate (g) 29 Dietary Fibres (g) 0 Total Sugars (g) 22 Added Sugar (g) 19 Protein (g) 3 KD 3.600",
    "meta": {
      "dedup_key": "https://eshop.kddc.com/en/Ice-Cream/Silver-Cone-7457",
      "name": "Silver Cone",
      "brand": null,
      "category": "ice cream",
      "flavor": "chocolate",
      "volume_ml": null,
      "weight_g": null,
      "pack_units": null,
      "product_url": "https://eshop.kddc.com/en/Ice-Cream/Silver-Cone-7457",
      "product_code": "FICCCB100S",
      "sku": "FICCCB100S",
      "availability": "in_stock",
      "price_now_kwd": 3.6,
      "options_text": "Carton - 24 Pieces | 24 pieces | KWD 3.6",
      "price_notes": "carton_per_piece≈0.150 KWD",
      "reviews_count": 0,
      "rating_stars": null,
      "desc": "Enjoy Creamy chocolate ice cream sprinkled with quality chocolate pieces. Nutrition Facts Per 1 Piece Nutrition Value Energy (Calories) 220 Calories from Fat (g) 90 Total Fat (g) 10 Saturated Fat (g) 8 Unsaturated Fat (g) 2 Trans Fat (g) 0 Cholesterol (g) 5 Sodium (mg) 0.055 Total Carbohydrate (g) 29 Dietary Fibres (g) 0 Total Sugars (g) 22 Added Sugar (g) 19 Protein (g) 3  KD 3.600 "
    }
  },
  {
    "type": "product",
    "title": "Silver Cone (Pack of 6)",
    "url": "https://eshop.kddc.com/en/Ice-Cream/Silver-Cone-(Pack-of-6)-7464",
    "category": "ice cream",
    "text": "Silver Cone (Pack of 6) | ice cream | 0.9 KWD | None | chocolate | | | | Piece | 1 piece | KWD 0.9 | Enjoy Creamy chocolate ice cream sprinkled with quality chocolate pieces. Nutrition Facts Per 1 Piece Nutrition Value Energy (Calories) 220 Calories from Fat (g) 90 Total Fat (g) 10 Saturated Fat (g) 8 Unsaturated Fat (g) 2 Trans Fat (g) 0 Cholesterol (g) 5 Sodium (mg) 0.055 Total Carbohydrate (g) 29 Dietary Fibres (g) 0 Total Sugars (g) 22 Added Sugar (g) 19 Protein (g) 3 KD 0.900",
    "meta": {
      "dedup_key": "https://eshop.kddc.com/en/Ice-Cream/Silver-Cone-(Pack-of-6)-7464",
      "name": "Silver Cone (Pack of 6)",
      "brand": null,
      "category": "ice cream",
      "flavor": "chocolate",
      "volume_ml": null,
      "weight_g": null,
      "pack_units": null,
      "product_url": "https://eshop.kddc.com/en/Ice-Cream/Silver-Cone-(Pack-of-6)-7464",
      "product_code": "FICCCBSLVR6",
      "sku": "FICCCBSLVR6",
      "availability": "in_stock",
      "price_now_kwd": 0.9,
      "options_text": "Piece | 1 piece | KWD 0.9",
      "price_notes": null,
      "reviews_count": 0,
      "rating_stars": null,
      "desc": "Enjoy Creamy chocolate ice cream sprinkled with quality chocolate pieces. Nutrition Facts Per 1 Piece Nutrition Value Energy (Calories) 220 Calories from Fat (g) 90 Total Fat (g) 10 Saturated Fat (g) 8 Unsaturated Fat (g) 2 Trans Fat (g) 0 Cholesterol (g) 5 Sodium (mg) 0.055 Total Carbohydrate (g) 29 Dietary Fibres (g) 0 Total Sugars (g) 22 Added Sugar (g) 19 Protein (g) 3  KD 0.900 "
    }
  },
  {
    "type": "product",
    "title": "Strawberry Cheesecake Ice Cream 500ML",
    "url": "https://eshop.kddc.com/en/Ice-Cream/Strawberry-Cheesecake-Ice-Cream-500ML-8693",
    "category": "ice cream",
    "text": "Strawberry Cheesecake Ice Cream 500ML | ice cream | 0.88 KWD | None | strawberry | 500 ml | | | Piece | 1 piece | KWD 0.88 | Delicious Strawberry swirls in authentic cheesecake ice cream KD 0.880",
    "meta": {
      "dedup_key": "https://eshop.kddc.com/en/Ice-Cream/Strawberry-Cheesecake-Ice-Cream-500ML-8693",
      "name": "Strawberry Cheesecake Ice Cream 500ML",
      "brand": null,
      "category": "ice cream",
      "flavor": "strawberry",
      "volume_ml": 500,
      "weight_g": null,
      "pack_units": null,
      "product_url": "https://eshop.kddc.com/en/Ice-Cream/Strawberry-Cheesecake-Ice-Cream-500ML-8693",
      "product_code": "FICFMSHLSBCHSCK",
      "sku": "FICFMSHLSBCHSCK",
      "availability": "in_stock",
      "price_now_kwd": 0.88,
      "options_text": "Piece | 1 piece | KWD 0.88",
      "price_notes": null,
      "reviews_count": 0,
      "rating_stars": null,
      "desc": "Delicious Strawberry swirls in authentic cheesecake ice cream  KD 0.880 "
    }
  },
  {
    "type": "product",
    "title": "Strawberry Cup",
    "url": "https://eshop.kddc.com/en/Ice-Cream/Strawberry-Cup-7461",
    "category": "ice cream",
    "text": "Strawberry Cup | ice cream | 2.4 KWD | None | strawberry | | 55 g | | Carton - 24 Pieces | 24 pieces | KWD 2.4 | Classic strawberry ice cream. Always a pleasure Nutrition Facts Per 55 g Nutrition Value Energy (Calories) 100 Calories from Fat (g) 54 Total Fat (g) 6 Saturated Fat (g) 5 Unsaturated Fat (g) 1 Trans Fat (g) 0 Cholesterol (g) 5 Sodium (mg) 0.035 Total Carbohydrate (g) 12 Dietary Fibres (g) 0 Total Sugars (g) 12 Added Sugar (g) 9 Protein (g) 2 KD 2.400 55 g",
    "meta": {
      "dedup_key": "https://eshop.kddc.com/en/Ice-Cream/Strawberry-Cup-7461",
      "name": "Strawberry Cup",
      "brand": null,
      "category": "ice cream",
      "flavor": "strawberry",
      "volume_ml": null,
      "weight_g": 55,
      "pack_units": null,
      "product_url": "https://eshop.kddc.com/en/Ice-Cream/Strawberry-Cup-7461",
      "product_code": "FICCCB1SB",
      "sku": "FICCCB1SB",
      "availability": "in_stock",
      "price_now_kwd": 2.4,
      "options_text": "Carton - 24 Pieces | 24 pieces | KWD 2.4",
      "price_notes": "carton_per_piece≈0.100 KWD",
      "reviews_count": 0,
      "rating_stars": null,
      "desc": "Classic strawberry ice cream. Always a pleasure Nutrition Facts Per 55 g Nutrition Value Energy (Calories) 100 Calories from Fat (g) 54 Total Fat (g) 6 Saturated Fat (g) 5 Unsaturated Fat (g) 1 Trans Fat (g) 0 Cholesterol (g) 5 Sodium (mg) 0.035 Total Carbohydrate (g) 12 Dietary Fibres (g) 0 Total Sugars (g) 12 Added Sugar (g) 9 Protein (g) 2  KD 2.400 55 g"
    }
  },
  {
    "type": "product",
    "title": "Strawberry Ice Cream 1 LTR",
    "url": "https://eshop.kddc.com/en/Ice-Cream/Strawberry-Ice-Cream-1-LTR-7474",
    "category": "ice cream",
    "text": "Strawberry Ice Cream 1 LTR | ice cream | 1.0 KWD | None | strawberry | 1000 ml | 100 g | | Piece | 1 piece | KWD 1.0 | Classic strawberry ice cream. Always a pleasure Nutrition Facts Per 100 g Nutrition Value Energy (Calories) 200 Calories from Fat (g) 90 Total Fat (g) 10 Saturated Fat (g) 9 Unsaturated Fat (g) 1 Trans Fat (g) 0 Cholesterol (g) 5 Sodium (mg) 0.065 Total Carbohydrate (g) 24 Dietary Fibres (g) 0 Total Sugars (g) 23 Added Sugar (g) 17 Protein (g) 3 KD 1.000 100 g",
    "meta": {
      "dedup_key": "https://eshop.kddc.com/en/Ice-Cream/Strawberry-Ice-Cream-1-LTR-7474",
      "name": "Strawberry Ice Cream 1 LTR",
      "brand": null,
      "category": "ice cream",
      "flavor": "strawberry",
      "volume_ml": 1000,
      "weight_g": 100,
      "pack_units": null,
      "product_url": "https://eshop.kddc.com/en/Ice-Cream/Strawberry-Ice-Cream-1-LTR-7474",
      "product_code": "FICFMS1LSBRCUP",
      "sku": "FICFMS1LSBRCUP",
      "availability": "in_stock",
      "price_now_kwd": 1.0,
      "options_text": "Piece | 1 piece | KWD 1.0",
      "price_notes": null,
      "reviews_count": 0,
      "rating_stars": null,
      "desc": "Classic strawberry ice cream. Always a pleasure Nutrition Facts Per 100 g Nutrition Value Energy (Calories) 200 Calories from Fat (g) 90 Total Fat (g) 10 Saturated Fat (g) 9 Unsaturated Fat (g) 1 Trans Fat (g) 0 Cholesterol (g) 5 Sodium (mg) 0.065 Total Carbohydrate (g) 24 Dietary Fibres (g) 0 Total Sugars (g) 23 Added Sugar (g) 17 Protein (g) 3  KD 1.000 100 g"
    }
  },
  {
    "type": "product",
    "title": "Strawberry Ice Cream 5 LTR",
    "url": "https://eshop.kddc.com/en/Ice-Cream/Strawberry-Ice-Cream-5-LTR-7481",
    "category": "ice cream",
    "text": "Strawberry Ice Cream 5 LTR | ice cream | 4.4 KWD | None | strawberry | 5000 ml | 100 g | | Piece | 1 piece | KWD 4.4 | Classic strawberry ice cream. Always a pleasure Nutrition Facts Per 100 g Nutrition Value Energy (Calories) 200 Calories from Fat (g) 90 Total Fat (g) 10 Saturated Fat (g) 9 Unsaturated Fat (g) 1 Trans Fat (g) 0 Cholesterol (g) 5 Sodium (mg) 0.065 Total Carbohydrate (g) 24 Dietary Fibres (g) 0 Total Sugars (g) 23 Added Sugar (g) 17 Protein (g) 3 KD 4.400 100 g",
    "meta": {
      "dedup_key": "https://eshop.kddc.com/en/Ice-Cream/Strawberry-Ice-Cream-5-LTR-7481",
      "name": "Strawberry Ice Cream 5 LTR",
      "brand": null,
      "category": "ice cream",
      "flavor": "strawberry",
      "volume_ml": 5000,
      "weight_g": 100,
      "pack_units": null,
      "product_url": "https://eshop.kddc.com/en/Ice-Cream/Strawberry-Ice-Cream-5-LTR-7481",
      "product_code": "FICFMS5LSB",
      "sku": "FICFMS5LSB",
      "availability": "in_stock",
      "price_now_kwd": 4.4,
      "options_text": "Piece | 1 piece | KWD 4.4",
      "price_notes": null,
      "reviews_count": 0,
      "rating_stars": null,
      "desc": "Classic strawberry ice cream. Always a pleasure Nutrition Facts Per 100 g Nutrition Value Energy (Calories) 200 Calories from Fat (g) 90 Total Fat (g) 10 Saturated Fat (g) 9 Unsaturated Fat (g) 1 Trans Fat (g) 0 Cholesterol (g) 5 Sodium (mg) 0.065 Total Carbohydrate (g) 24 Dietary Fibres (g) 0 Total Sugars (g) 23 Added Sugar (g) 17 Protein (g) 3  KD 4.400 100 g"
    }
  },
  {
    "type": "product",
    "title": "Strawberry Ice Cream Cups (No Added Sugar)",
    "url": "https://eshop.kddc.com/en/Ice-Cream/Strawberry-Ice-Cream-Cups-(No-Added-Sugar)-9499",
    "category": "ice cream",
    "text": "Strawberry Ice Cream Cups (No Added Sugar) | ice cream | 2.4 KWD | None | strawberry | | | | Carton - 6 Pieces | 6 pieces | KWD 2.4 | Delicious strawberry ice cream with no added sugar. Go ahead and indulge yourself guilt-free! KD 2.400",
    "meta": {
      "dedup_key": "https://eshop.kddc.com/en/Ice-Cream/Strawberry-Ice-Cream-Cups-(No-Added-Sugar)-9499",
      "name": "Strawberry Ice Cream Cups (No Added Sugar)",
      "brand": null,
      "category": "ice cream",
      "flavor": "strawberry",
      "volume_ml": null,
      "weight_g": null,
      "pack_units": null,
      "product_url": "https://eshop.kddc.com/en/Ice-Cream/Strawberry-Ice-Cream-Cups-(No-Added-Sugar)-9499",
      "product_code": "FICNSAC167SB6GM",
      "sku": "FICNSAC167SB6GM",
      "availability": "in_stock",
      "price_now_kwd": 2.4,
      "options_text": "Carton - 6 Pieces | 6 pieces | KWD 2.4",
      "price_notes": "carton_per_piece≈0.400 KWD",
      "reviews_count": 0,
      "rating_stars": null,
      "desc": "Delicious strawberry ice cream with no added sugar. Go ahead and indulge yourself guilt-free!  KD 2.400 "
    }
  },
  {
    "type": "product",
    "title": "Vanilla Almond Cup Ice Cream",
    "url": "https://eshop.kddc.com/en/Ice-Cream/Vanilla-Almond-Cup-Ice-Cream-7459",
    "category": "ice cream",
    "text": "Vanilla Almond Cup Ice Cream | ice cream | 3.6 KWD | None | vanilla | | | | Carton - 18 Pieces | 18 pieces | KWD 3.6 | Vanilla & almond. A fine combination for an ice cream Nutrition Facts Per 1 Piece Nutrition Value Energy (Calories) 230 Calories from Fat (g) 135 Total Fat (g) 15 Saturated Fat (g) 9 Unsaturated Fat (g) 6 Trans Fat (g) 0 Cholesterol (g) 5 Sodium (mg) 0.04 Total Carbohydrate (g) 22 Dietary Fibres (g) 1 Total Sugars (g) 20 Added Sugar (g) 14 Protein (g) 5 KD 3.600",
    "meta": {
      "dedup_key": "https://eshop.kddc.com/en/Ice-Cream/Vanilla-Almond-Cup-Ice-Cream-7459",
      "name": "Vanilla Almond Cup Ice Cream",
      "brand": null,
      "category": "ice cream",
      "flavor": "vanilla",
      "volume_ml": null,
      "weight_g": null,
      "pack_units": null,
      "product_url": "https://eshop.kddc.com/en/Ice-Cream/Vanilla-Almond-Cup-Ice-Cream-7459",
      "product_code": "FICCCB17VA",
      "sku": "FICCCB17VA",
      "availability": "in_stock",
      "price_now_kwd": 3.6,
      "options_text": "Carton - 18 Pieces | 18 pieces | KWD 3.6",
      "price_notes": "carton_per_piece≈0.200 KWD",
      "reviews_count": 0,
      "rating_stars": null,
      "desc": "Vanilla & almond. A fine combination for an ice cream Nutrition Facts Per 1 Piece Nutrition Value Energy (Calories) 230 Calories from Fat (g) 135 Total Fat (g) 15 Saturated Fat (g) 9 Unsaturated Fat (g) 6 Trans Fat (g) 0 Cholesterol (g) 5 Sodium (mg) 0.04 Total Carbohydrate (g) 22 Dietary Fibres (g) 1 Total Sugars (g) 20 Added Sugar (g) 14 Protein (g) 5  KD 3.600 "
    }
  },
  {
    "type": "product",
    "title": "Vanilla Almond Ice Cream 1 LTR",
    "url": "https://eshop.kddc.com/en/Ice-Cream/Vanilla-Almond-Ice-Cream-1-LTR-7475",
    "category": "ice cream",
    "text": "Vanilla Almond Ice Cream 1 LTR | ice cream | 1.0 KWD | None | vanilla | 1000 ml | 100 g | | Piece | 1 piece | KWD 1.0 | Vanilla & almond. A fine combination for an ice cream Nutrition Facts Per 100 g Nutrition Value Energy (Calories) 240 Calories from Fat (g) 126 Total Fat (g) 14 Saturated Fat (g) 9 Unsaturated Fat (g) 6 Trans Fat (g) 0 Cholesterol (g) 5 Sodium (mg) 0.04 Total Carbohydrate (g) 23 Dietary Fibres (g) 1 Total Sugars (g) 21 Added Sugar (g) 16 Protein (g) 5 KD 1.000 100 g",
    "meta": {
      "dedup_key": "https://eshop.kddc.com/en/Ice-Cream/Vanilla-Almond-Ice-Cream-1-LTR-7475",
      "name": "Vanilla Almond Ice Cream 1 LTR",
      "brand": null,
      "category": "ice cream",
      "flavor": "vanilla",
      "volume_ml": 1000,
      "weight_g": 100,
      "pack_units": null,
      "product_url": "https://eshop.kddc.com/en/Ice-Cream/Vanilla-Almond-Ice-Cream-1-LTR-7475",
      "product_code": "FICFMS1LVARCUP",
      "sku": "FICFMS1LVARCUP",
      "availability": "in_stock",
      "price_now_kwd": 1.0,
      "options_text": "Piece | 1 piece | KWD 1.0",
      "price_notes": null,
      "reviews_count": 0,
      "rating_stars": null,
      "desc": "Vanilla & almond. A fine combination for an ice cream Nutrition Facts Per 100 g Nutrition Value Energy (Calories) 240 Calories from Fat (g) 126 Total Fat (g) 14 Saturated Fat (g) 9 Unsaturated Fat (g) 6 Trans Fat (g) 0 Cholesterol (g) 5 Sodium (mg) 0.04 Total Carbohydrate (g) 23 Dietary Fibres (g) 1 Total Sugars (g) 21 Added Sugar (g) 16 Protein (g) 5  KD 1.000 100 g"
    }
  },
  {
    "type": "product",
    "title": "Vanilla Chocolate Ice Cream 1 LTR",
    "url": "https://eshop.kddc.com/en/Ice-Cream/Vanilla-Chocolate-Ice-Cream-1-LTR-7476",
    "category": "ice cream",
    "text": "Vanilla Chocolate Ice Cream 1 LTR | ice cream | 1.0 KWD | None | vanilla | 1000 ml | | | Piece | 1 piece | KWD 1.0 | Vanilla & Chocolate ice cream. Best of both worlds KD 1.000",
    "meta": {
      "dedup_key": "https://eshop.kddc.com/en/Ice-Cream/Vanilla-Chocolate-Ice-Cream-1-LTR-7476",
      "name": "Vanilla Chocolate Ice Cream 1 LTR",
      "brand": null,
      "category": "ice cream",
      "flavor": "vanilla",
      "volume_ml": 1000,
      "weight_g": null,
      "pack_units": null,
      "product_url": "https://eshop.kddc.com/en/Ice-Cream/Vanilla-Chocolate-Ice-Cream-1-LTR-7476",
      "product_code": "FICFMS1LVCRCUP",
      "sku": "FICFMS1LVCRCUP",
      "availability": "in_stock",
      "price_now_kwd": 1.0,
      "options_text": "Piece | 1 piece | KWD 1.0",
      "price_notes": null,
      "reviews_count": 0,
      "rating_stars": null,
      "desc": "Vanilla & Chocolate ice cream. Best of both worlds  KD 1.000 "
    }
  },
  {
    "type": "product",
    "title": "Vanilla Cup Ice Cream",
    "url": "https://eshop.kddc.com/en/Ice-Cream/Vanilla-Cup-Ice-Cream-7462",
    "category": "ice cream",
    "text": "Vanilla Cup Ice Cream | ice cream | 2.4 KWD | None | vanilla | | 55 g | | Carton - 24 Pieces | 24 pieces | KWD 2.4 | Classic vanilla ice cream. Always a pleasure Nutrition Facts Per 55 g Nutrition Value Energy (Calories) 100 Calories from Fat (g) 54 Total Fat (g) 6 Saturated Fat (g) 5 Unsaturated Fat (g) 1 Trans Fat (g) 0 Cholesterol (g) 5 Sodium (mg) 0.025 Total Carbohydrate (g) 12 Dietary Fibres (g) 0 Total Sugars (g) 12 Added Sugar (g) 9 Protein (g) 2 KD 2.400 55 g",
    "meta": {
      "dedup_key": "https://eshop.kddc.com/en/Ice-Cream/Vanilla-Cup-Ice-Cream-7462",
      "name": "Vanilla Cup Ice Cream",
      "brand": null,
      "category": "ice cream",
      "flavor": "vanilla",
      "volume_ml": null,
      "weight_g": 55,
      "pack_units": null,
      "product_url": "https://eshop.kddc.com/en/Ice-Cream/Vanilla-Cup-Ice-Cream-7462",
      "product_code": "FICCCB1VN",
      "sku": "FICCCB1VN",
      "availability": "in_stock",
      "price_now_kwd": 2.4,
      "options_text": "Carton - 24 Pieces | 24 pieces | KWD 2.4",
      "price_notes": "carton_per_piece≈0.100 KWD",
      "reviews_count": 0,
      "rating_stars": null,
      "desc": "Classic vanilla ice cream. Always a pleasure Nutrition Facts Per 55 g Nutrition Value Energy (Calories) 100 Calories from Fat (g) 54 Total Fat (g) 6 Saturated Fat (g) 5 Unsaturated Fat (g) 1 Trans Fat (g) 0 Cholesterol (g) 5 Sodium (mg) 0.025 Total Carbohydrate (g) 12 Dietary Fibres (g) 0 Total Sugars (g) 12 Added Sugar (g) 9 Protein (g) 2  KD 2.400 55 g"
    }
  },
  {
    "type": "product",
    "title": "Vanilla Ice Cream 1 LTR",
    "url": "https://eshop.kddc.com/en/Ice-Cream/Vanilla-Ice-Cream-1-LTR-7477",
    "category": "ice cream",
    "text": "Vanilla Ice Cream 1 LTR | ice cream | 1.0 KWD | None | vanilla | 1000 ml | 100 g | | Piece | 1 piece | KWD 1.0 | Classic vanilla ice cream. Always a pleasure Nutrition Facts Per 100 g Nutrition Value Energy (Calories) 200 Calories from Fat (g) 90 Total Fat (g) 10 Saturated Fat (g) 10 Unsaturated Fat (g) 0 Trans Fat (g) 0 Cholesterol (g) 5 Sodium (mg) 0.045 Total Carbohydrate (g) 24 Dietary Fibres (g) 0 Total Sugars (g) 23 Added Sugar (g) 17 Protein (g) 3 KD 1.000 100 g",
    "meta": {
      "dedup_key": "https://eshop.kddc.com/en/Ice-Cream/Vanilla-Ice-Cream-1-LTR-7477",
      "name": "Vanilla Ice Cream 1 LTR",
      "brand": null,
      "category": "ice cream",
      "flavor": "vanilla",
      "volume_ml": 1000,
      "weight_g": 100,
      "pack_units": null,
      "product_url": "https://eshop.kddc.com/en/Ice-Cream/Vanilla-Ice-Cream-1-LTR-7477",
      "product_code": "FICFMS1LVNRCUP",
      "sku": "FICFMS1LVNRCUP",
      "availability": "in_stock",
      "price_now_kwd": 1.0,
      "options_text": "Piece | 1 piece | KWD 1.0",
      "price_notes": null,
      "reviews_count": 0,
      "rating_stars": null,
      "desc": "Classic vanilla ice cream. Always a pleasure Nutrition Facts Per 100 g Nutrition Value Energy (Calories) 200 Calories from Fat (g) 90 Total Fat (g) 10 Saturated Fat (g) 10 Unsaturated Fat (g) 0 Trans Fat (g) 0 Cholesterol (g) 5 Sodium (mg) 0.045 Total Carbohydrate (g) 24 Dietary Fibres (g) 0 Total Sugars (g) 23 Added Sugar (g) 17 Protein (g) 3  KD 1.000 100 g"
    }
  },
  {
    "type": "product",
    "title": "Vanilla Ice Cream 500 ML",
    "url": "https://eshop.kddc.com/en/Ice-Cream/Vanilla-Ice-Cream-500-ML-7488",
    "category": "ice cream",
    "text": "Vanilla Ice Cream 500 ML | ice cream | 0.5 KWD | None | vanilla | 500 ml | 100 g | | Piece | 1 piece | KWD 0.5 | Classic vanilla ice cream. Always a pleasure Nutrition Facts Per 100 g Nutrition Value Energy (Calories) 200 Calories from Fat (g) 90 Total Fat (g) 10 Saturated Fat (g) 10 Unsaturated Fat (g) 0 Trans Fat (g) 0 Cholesterol (g) 5 Sodium (mg) 0.045 Total Carbohydrate (g) 24 Dietary Fibres (g) 0 Total Sugars (g) 23 Added Sugar (g) 17 Protein (g) 3 KD 0.500 100 g",
    "meta": {
      "dedup_key": "https://eshop.kddc.com/en/Ice-Cream/Vanilla-Ice-Cream-500-ML-7488",
      "name": "Vanilla Ice Cream 500 ML",
      "brand": null,
      "category": "ice cream",
      "flavor": "vanilla",
      "volume_ml": 500,
      "weight_g": 100,
      "pack_units": null,
      "product_url": "https://eshop.kddc.com/en/Ice-Cream/Vanilla-Ice-Cream-500-ML-7488",
      "product_code": "FICFMSHLVNRCUP",
      "sku": "FICFMSHLVNRCUP",
      "availability": "in_stock",
      "price_now_kwd": 0.5,
      "options_text": "Piece | 1 piece | KWD 0.5",
      "price_notes": null,
      "reviews_count": 0,
      "rating_stars": null,
      "desc": "Classic vanilla ice cream. Always a pleasure Nutrition Facts Per 100 g Nutrition Value Energy (Calories) 200 Calories from Fat (g) 90 Total Fat (g) 10 Saturated Fat (g) 10 Unsaturated Fat (g) 0 Trans Fat (g) 0 Cholesterol (g) 5 Sodium (mg) 0.045 Total Carbohydrate (g) 24 Dietary Fibres (g) 0 Total Sugars (g) 23 Added Sugar (g) 17 Protein (g) 3  KD 0.500 100 g"
    }
  },
  {
    "type": "product",
    "title": "Vanilla Ice Cream Cups (No Added Sugar)",
    "url": "https://eshop.kddc.com/en/Ice-Cream/Vanilla-Ice-Cream-Cups-(No-Added-Sugar)-9500",
    "category": "ice cream",
    "text": "Vanilla Ice Cream Cups (No Added Sugar) | ice cream | 2.4 KWD | None | vanilla | | | | Carton - 6 Pieces | 6 pieces | KWD 2.4 | Delicious vanilla ice cream with no added sugar. Go ahead and indulge yourself guilt-free! KD 2.400",
    "meta": {
      "dedup_key": "https://eshop.kddc.com/en/Ice-Cream/Vanilla-Ice-Cream-Cups-(No-Added-Sugar)-9500",
      "name": "Vanilla Ice Cream Cups (No Added Sugar)",
      "brand": null,
      "category": "ice cream",
      "flavor": "vanilla",
      "volume_ml": null,
      "weight_g": null,
      "pack_units": null,
      "product_url": "https://eshop.kddc.com/en/Ice-Cream/Vanilla-Ice-Cream-Cups-(No-Added-Sugar)-9500",
      "product_code": "FICNSAC167VN6GM",
      "sku": "FICNSAC167VN6GM",
      "availability": "in_stock",
      "price_now_kwd": 2.4,
      "options_text": "Carton - 6 Pieces | 6 pieces | KWD 2.4",
      "price_notes": "carton_per_piece≈0.400 KWD",
      "reviews_count": 0,
      "rating_stars": null,
      "desc": "Delicious vanilla ice cream with no added sugar. Go ahead and indulge yourself guilt-free!  KD 2.400 "
    }
  },
  {
    "type": "product",
    "title": "Vanilla Lulu Cone",
    "url": "https://eshop.kddc.com/en/Ice-Cream/Vanilla-Lulu-Cone-7455",
    "category": "ice cream",
    "text": "Vanilla Lulu Cone | ice cream | 4.44 KWD | None | vanilla | | | | Carton - 24 Pieces | 24 pieces | KWD 4.44 | Enjoy tasty vanilla Ice Cream mixed with nougat sauce, sprinkled with crunchy almonds Nutrition Facts Per 1 Piece Nutrition Value Energy (Calories) 310 Calories from Fat (g) 180 Total Fat (g) 20 Saturated Fat (g) 11 Unsaturated Fat (g) 9 Trans Fat (g) 0 Cholesterol (g) 5 Sodium (mg) 0.045 Total Carbohydrate (g) 29 Dietary Fibres (g) 1 Total Sugars (g) 23 Added Sugar (g) 20 Protein (g) 4 KD 4.440",
    "meta": {
      "dedup_key": "https://eshop.kddc.com/en/Ice-Cream/Vanilla-Lulu-Cone-7455",
      "name": "Vanilla Lulu Cone",
      "brand": null,
      "category": "ice cream",
      "flavor": "vanilla",
      "volume_ml": null,
      "weight_g": null,
      "pack_units": null,
      "product_url": "https://eshop.kddc.com/en/Ice-Cream/Vanilla-Lulu-Cone-7455",
      "product_code": "FICCCB100LUVN",
      "sku": "FICCCB100LUVN",
      "availability": "in_stock",
      "price_now_kwd": 4.44,
      "options_text": "Carton - 24 Pieces | 24 pieces | KWD 4.44",
      "price_notes": "carton_per_piece≈0.185 KWD",
      "reviews_count": 0,
      "rating_stars": null,
      "desc": "Enjoy tasty vanilla Ice Cream mixed with nougat sauce, sprinkled with crunchy almonds Nutrition Facts Per 1 Piece Nutrition Value Energy (Calories) 310 Calories from Fat (g) 180 Total Fat (g) 20 Saturated Fat (g) 11 Unsaturated Fat (g) 9 Trans Fat (g) 0 Cholesterol (g) 5 Sodium (mg) 0.045 Total Carbohydrate (g) 29 Dietary Fibres (g) 1 Total Sugars (g) 23 Added Sugar (g) 20 Protein (g) 4  KD 4.440 "
    }
  },
  {
    "type": "product",
    "title": "Vanilla Lulu Cone (Pack of 6)",
    "url": "https://eshop.kddc.com/en/Ice-Cream/Vanilla-Lulu-Cone-(Pack-of-6)-7456",
    "category": "ice cream",
    "text": "Vanilla Lulu Cone (Pack of 6) | ice cream | 1.11 KWD | None | vanilla | | | | Carton - 6 Pieces | 6 pieces | KWD 1.11 | Enjoy tasty vanilla Ice Cream mixed with nougat sauce, sprinkled with crunchy almonds Nutrition Facts Per 1 Piece Nutrition Value Energy (Calories) 310 Calories from Fat (g) 180 Total Fat (g) 20 Saturated Fat (g) 11 Unsaturated Fat (g) 9 Trans Fat (g) 0 Cholesterol (g) 5 Sodium (mg) 0.045 Total Carbohydrate (g) 29 Dietary Fibres (g) 1 Total Sugars (g) 23 Added Sugar (g) 20 Protein (g) 4 KD 1.110",
    "meta": {
      "dedup_key": "https://eshop.kddc.com/en/Ice-Cream/Vanilla-Lulu-Cone-(Pack-of-6)-7456",
      "name": "Vanilla Lulu Cone (Pack of 6)",
      "brand": null,
      "category": "ice cream",
      "flavor": "vanilla",
      "volume_ml": null,
      "weight_g": null,
      "pack_units": null,
      "product_url": "https://eshop.kddc.com/en/Ice-Cream/Vanilla-Lulu-Cone-(Pack-of-6)-7456",
      "product_code": "FICCCB100LUVN6",
      "sku": "FICCCB100LUVN6",
      "availability": "in_stock",
      "price_now_kwd": 1.11,
      "options_text": "Carton - 6 Pieces | 6 pieces | KWD 1.11",
      "price_notes": "carton_per_piece≈0.185 KWD",
      "reviews_count": 0,
      "rating_stars": null,
      "desc": "Enjoy tasty vanilla Ice Cream mixed with nougat sauce, sprinkled with crunchy almonds Nutrition Facts Per 1 Piece Nutrition Value Energy (Calories) 310 Calories from Fat (g) 180 Total Fat (g) 20 Saturated Fat (g) 11 Unsaturated Fat (g) 9 Trans Fat (g) 0 Cholesterol (g) 5 Sodium (mg) 0.045 Total Carbohydrate (g) 29 Dietary Fibres (g) 1 Total Sugars (g) 23 Added Sugar (g) 20 Protein (g) 4  KD 1.110 "
    }
  },
  {
    "type": "product",
    "title": "Vanilla Lulu Stick",
    "url": "https://eshop.kddc.com/en/Ice-Cream/Vanilla-Lulu-Stick-7521",
    "category": "ice cream",
    "text": "Vanilla Lulu Stick | ice cream | 2.4 KWD | None | vanilla | | | | Carton - 24 Pieces | 24 pieces | KWD 2.4 | Creamy vanilla ice cream with nougat in the centre, coated with chocolate & crunchy almonds. Nutrition Facts Per 1 Piece Nutrition Value Energy (Calories) 230 Calories from Fat (g) 153 Total Fat (g) 17 Saturated Fat (g) 10 Unsaturated Fat (g) 7 Trans Fat (g) 0 Cholesterol (g) 0 Sodium (mg) 0.025 Total Carbohydrate (g) 17 Dietary Fibres (g) 0 Total Sugars (g) 16 Added Sugar (g) 14 Protein (g) 2 KD 2.400",
    "meta": {
      "dedup_key": "https://eshop.kddc.com/en/Ice-Cream/Vanilla-Lulu-Stick-7521",
      "name": "Vanilla Lulu Stick",
      "brand": null,
      "category": "ice cream",
      "flavor": "vanilla",
      "volume_ml": null,
      "weight_g": null,
      "pack_units": null,
      "product_url": "https://eshop.kddc.com/en/Ice-Cream/Vanilla-Lulu-Stick-7521",
      "product_code": "FICSTL24LU",
      "sku": "FICSTL24LU",
      "availability": "in_stock",
      "price_now_kwd": 2.4,
      "options_text": "Carton - 24 Pieces | 24 pieces | KWD 2.4",
      "price_notes": "carton_per_piece≈0.100 KWD",
      "reviews_count": 0,
      "rating_stars": null,
      "desc": "Creamy vanilla ice cream with nougat in the centre, coated with chocolate & crunchy almonds. Nutrition Facts Per 1 Piece Nutrition Value Energy (Calories) 230 Calories from Fat (g) 153 Total Fat (g) 17 Saturated Fat (g) 10 Unsaturated Fat (g) 7 Trans Fat (g) 0 Cholesterol (g) 0 Sodium (mg) 0.025 Total Carbohydrate (g) 17 Dietary Fibres (g) 0 Total Sugars (g) 16 Added Sugar (g) 14 Protein (g) 2  KD 2.400 "
    }
  },
  {
    "type": "product",
    "title": "Vanilla Lulu Stick (Pack of 6)",
    "url": "https://eshop.kddc.com/en/Ice-Cream/Vanilla-Lulu-Stick-(Pack-of-6)-7535",
    "category": "ice cream",
    "text": "Vanilla Lulu Stick (Pack of 6) | ice cream | 0.595 KWD | None | vanilla | | | | Piece | 1 piece | KWD 0.595 | Creamy vanilla ice cream with nougat in the centre, coated with chocolate & crunchy almonds. Nutrition Facts Per 1 Piece Nutrition Value Energy (Calories) 230 Calories from Fat (g) 153 Total Fat (g) 17 Saturated Fat (g) 10 Unsaturated Fat (g) 7 Trans Fat (g) 0 Cholesterol (g) 0 Sodium (mg) 0.025 Total Carbohydrate (g) 17 Dietary Fibres (g) 0 Total Sugars (g) 16 Added Sugar (g) 14 Protein (g) 2 KD 0.595",
    "meta": {
      "dedup_key": "https://eshop.kddc.com/en/Ice-Cream/Vanilla-Lulu-Stick-(Pack-of-6)-7535",
      "name": "Vanilla Lulu Stick (Pack of 6)",
      "brand": null,
      "category": "ice cream",
      "flavor": "vanilla",
      "volume_ml": null,
      "weight_g": null,
      "pack_units": null,
      "product_url": "https://eshop.kddc.com/en/Ice-Cream/Vanilla-Lulu-Stick-(Pack-of-6)-7535",
      "product_code": "FICSTLLULU6",
      "sku": "FICSTLLULU6",
      "availability": "in_stock",
      "price_now_kwd": 0.595,
      "options_text": "Piece | 1 piece | KWD 0.595",
      "price_notes": null,
      "reviews_count": 0,
      "rating_stars": null,
      "desc": "Creamy vanilla ice cream with nougat in the centre, coated with chocolate & crunchy almonds. Nutrition Facts Per 1 Piece Nutrition Value Energy (Calories) 230 Calories from Fat (g) 153 Total Fat (g) 17 Saturated Fat (g) 10 Unsaturated Fat (g) 7 Trans Fat (g) 0 Cholesterol (g) 0 Sodium (mg) 0.025 Total Carbohydrate (g) 17 Dietary Fibres (g) 0 Total Sugars (g) 16 Added Sugar (g) 14 Protein (g) 2  KD 0.595 "
    }
  },
  {
    "type": "product",
    "title": "Vanilla Sandwich (48 Pieces)",
    "url": "https://eshop.kddc.com/en/Ice-Cream/Vanilla-Sandwich-(48-Pieces)-9527",
    "category": "ice cream",
    "text": "Vanilla Sandwich (48 Pieces) | ice cream | 4.8 KWD | None | vanilla | | | 48 pcs | Carton - 48 Pieces | 48 pieces | KWD 4.8 | Vanilla ice cream sandwich, perfect snack anytime of the day. KD 4.800",
    "meta": {
      "dedup_key": "https://eshop.kddc.com/en/Ice-Cream/Vanilla-Sandwich-(48-Pieces)-9527",
      "name": "Vanilla Sandwich (48 Pieces)",
      "brand": null,
      "category": "ice cream",
      "flavor": "vanilla",
      "volume_ml": null,
      "weight_g": null,
      "pack_units": 48,
      "product_url": "https://eshop.kddc.com/en/Ice-Cream/Vanilla-Sandwich-(48-Pieces)-9527",
      "product_code": "FICSBONDVL48",
      "sku": "FICSBONDVL48",
      "availability": "in_stock",
      "price_now_kwd": 4.8,
      "options_text": "Carton - 48 Pieces | 48 pieces | KWD 4.8",
      "price_notes": "carton_per_piece≈0.100 KWD",
      "reviews_count": 0,
      "rating_stars": null,
      "desc": "Vanilla ice cream sandwich, perfect snack anytime of the day.  KD 4.800 "
    }
  },
  {
    "type": "product",
    "title": "Vanilla Sandwich (Pack of 10)",
    "url": "https://eshop.kddc.com/en/Ice-Cream/Vanilla-Sandwich-(Pack-of-10)-7514",
    "category": "ice cream",
    "text": "Vanilla Sandwich (Pack of 10) | ice cream | 0.99 KWD | None | vanilla | | | | Piece | 1 piece | KWD 0.99 | Vanilla ice cream sandwich, perfect snack anytime of the day. Nutrition Facts Per 1 Piece Nutrition Value Energy (Calories) 90 Calories from Fat (g) 27 Total Fat (g) 3 Saturated Fat (g) 2.5 Unsaturated Fat (g) 0.5 Trans Fat (g) 0 Cholesterol (g) 0 Sodium (mg) 0.075 Total Carbohydrate (g) 15 Dietary Fibres (g) 0 Total Sugars (g) 8 Added Sugar (g) 7 Protein (g) 1 KD 0.990",
    "meta": {
      "dedup_key": "https://eshop.kddc.com/en/Ice-Cream/Vanilla-Sandwich-(Pack-of-10)-7514",
      "name": "Vanilla Sandwich (Pack of 10)",
      "brand": null,
      "category": "ice cream",
      "flavor": "vanilla",
      "volume_ml": null,
      "weight_g": null,
      "pack_units": null,
      "product_url": "https://eshop.kddc.com/en/Ice-Cream/Vanilla-Sandwich-(Pack-of-10)-7514",
      "product_code": "FICSBONDVL10",
      "sku": "FICSBONDVL10",
      "availability": "in_stock",
      "price_now_kwd": 0.99,
      "options_text": "Piece | 1 piece | KWD 0.99",
      "price_notes": null,
      "reviews_count": 0,
      "rating_stars": null,
      "desc": "Vanilla ice cream sandwich, perfect snack anytime of the day. Nutrition Facts Per 1 Piece Nutrition Value Energy (Calories) 90 Calories from Fat (g) 27 Total Fat (g) 3 Saturated Fat (g) 2.5 Unsaturated Fat (g) 0.5 Trans Fat (g) 0 Cholesterol (g) 0 Sodium (mg) 0.075 Total Carbohydrate (g) 15 Dietary Fibres (g) 0 Total Sugars (g) 8 Added Sugar (g) 7 Protein (g) 1  KD 0.990 "
    }
  },
  {
    "type": "product",
    "title": "1.2.3 Apple Juice (Kids) 125ml",
    "url": "https://eshop.kddc.com/en/Juices/1.2.3-Apple-Juice-(Kids)-125ml-8586",
    "category": "ice cream",
    "text": "1.2.3 Apple Juice (Kids) 125ml | ice cream | 3.4 KWD | None | apple | 125 ml | | | Carton - 40 Pieces | 40 pieces | KWD 3.4 || Piece | 1 piece | KWD 0.085 || Pack Of Eight | 8 pieces | KWD 0.68 | 100% apple juice with no added sugar, colours, flavours or preservatives. Refreshing taste that can be enjoyed any time of the day. KD 3.400",
    "meta": {
      "dedup_key": "https://eshop.kddc.com/en/Juices/1.2.3-Apple-Juice-(Kids)-125ml-8586",
      "name": "1.2.3 Apple Juice (Kids) 125ml",
      "brand": null,
      "category": "juices",
      "flavor": "apple",
      "volume_ml": 125,
      "weight_g": null,
      "pack_units": null,
      "product_url": "https://eshop.kddc.com/en/Juices/1.2.3-Apple-Juice-(Kids)-125ml-8586",
      "product_code": "FJU125APPL8",
      "sku": "FJU125APPL8",
      "availability": "in_stock",
      "price_now_kwd": 3.4,
      "options_text": "Carton - 40 Pieces | 40 pieces | KWD 3.4 || Piece | 1 piece | KWD 0.085 || Pack Of Eight | 8 pieces | KWD 0.68",
      "price_notes": "carton_per_piece≈0.085 KWD",
      "reviews_count": 0,
      "rating_stars": null,
      "desc": "100% apple juice with no added sugar, colours, flavours or preservatives. Refreshing taste that can be enjoyed any time of the day.  KD 3.400 "
    }
  },
  {
    "type": "product",
    "title": "1.2.3 Cocktail Drink (Kids) 125ml",
    "url": "https://eshop.kddc.com/en/Juices/1.2.3-Cocktail-Drink-(Kids)-125ml-7550",
    "category": "ice cream",
    "text": "1.2.3 Cocktail Drink (Kids) 125ml | ice cream | 3.4 KWD | None | None | 125 ml | | | Carton - 40 Pieces | 40 pieces | KWD 3.4 | Great tasting and refreshing cocktail nectar. A delicious mix of fruits that is a family favorite for any occasion. No preservatives added. Nutrition Facts Per 100 ml. Nutrition Value Energy (Calories) 45 Calories from Fat (g) 0 Total Fat (g) 0 Saturated Fat (g) 0 Unsaturated Fat (g) 0 Trans Fat (g) 0 Cholesterol (g) 0 Sodium (mg) 0 Total Carbohydrate (g) 12 Dietary Fibres (g) 0 Total Sugars (g) 11 Added Sugar (g) 8 Protein (g) 0 KD 3.400 100 ml",
    "meta": {
      "dedup_key": "https://eshop.kddc.com/en/Juices/1.2.3-Cocktail-Drink-(Kids)-125ml-7550",
      "name": "1.2.3 Cocktail Drink (Kids) 125ml",
      "brand": null,
      "category": "juices",
      "flavor": null,
      "volume_ml": 125,
      "weight_g": null,
      "pack_units": null,
      "product_url": "https://eshop.kddc.com/en/Juices/1.2.3-Cocktail-Drink-(Kids)-125ml-7550",
      "product_code": "FJU125COCK8",
      "sku": "FJU125COCK8",
      "availability": "in_stock",
      "price_now_kwd": 3.4,
      "options_text": "Carton - 40 Pieces | 40 pieces | KWD 3.4",
      "price_notes": "carton_per_piece≈0.085 KWD",
      "reviews_count": 0,
      "rating_stars": null,
      "desc": "Great tasting and refreshing cocktail nectar. A delicious mix of fruits that is a family favorite for any occasion. No preservatives added. Nutrition Facts Per 100 ml. Nutrition Value Energy (Calories) 45 Calories from Fat (g) 0 Total Fat (g) 0 Saturated Fat (g) 0 Unsaturated Fat (g) 0 Trans Fat (g) 0 Cholesterol (g) 0 Sodium (mg) 0 Total Carbohydrate (g) 12 Dietary Fibres (g) 0 Total Sugars (g) 11 Added Sugar (g) 8 Protein (g) 0  KD 3.400 100 ml"
    }
  },
  {
    "type": "product",
    "title": "1.2.3 Mango Nectar (Kids) 125ml",
    "url": "https://eshop.kddc.com/en/Juices/1.2.3-Mango-Nectar-(Kids)-125ml-7552",
    "category": "ice cream",
    "text": "1.2.3 Mango Nectar (Kids) 125ml | ice cream | 3.4 KWD | None | mango | 125 ml | | | Carton - 40 Pieces | 40 pieces | KWD 3.4 | Great tasting and refreshing mango nectar. An all time favorite that's enjoyed by whole family. No preservatives. Nutrition Facts Per 100 ml. Nutrition Value Energy (Calories) 60 Calories from Fat (g) 0 Total Fat (g) 0 Saturated Fat (g) 0 Unsaturated Fat (g) 0 Trans Fat (g) 0 Cholesterol (g) 0 Sodium (mg) 0 Total Carbohydrate (g) 15 Dietary Fibres (g) 0 Total Sugars (g) 13 Added Sugar (g) 9 Protein (g) 0 KD 3.400 100 ml",
    "meta": {
      "dedup_key": "https://eshop.kddc.com/en/Juices/1.2.3-Mango-Nectar-(Kids)-125ml-7552",
      "name": "1.2.3 Mango Nectar (Kids) 125ml",
      "brand": null,
      "category": "juices",
      "flavor": "mango",
      "volume_ml": 125,
      "weight_g": null,
      "pack_units": null,
      "product_url": "https://eshop.kddc.com/en/Juices/1.2.3-Mango-Nectar-(Kids)-125ml-7552",
      "product_code": "FJU125MNGO8",
      "sku": "FJU125MNGO8",
      "availability": "in_stock",
      "price_now_kwd": 3.4,
      "options_text": "Carton - 40 Pieces | 40 pieces | KWD 3.4",
      "price_notes": "carton_per_piece≈0.085 KWD",
      "reviews_count": 0,
      "rating_stars": null,
      "desc": "Great tasting and refreshing mango nectar. An all time favorite that's enjoyed by whole family. No preservatives. Nutrition Facts Per 100 ml. Nutrition Value Energy (Calories) 60 Calories from Fat (g) 0 Total Fat (g) 0 Saturated Fat (g) 0 Unsaturated Fat (g) 0 Trans Fat (g) 0 Cholesterol (g) 0 Sodium (mg) 0 Total Carbohydrate (g) 15 Dietary Fibres (g) 0 Total Sugars (g) 13 Added Sugar (g) 9 Protein (g) 0  KD 3.400 100 ml"
    }
  },
  {
    "type": "product",
    "title": "1.2.3 Orange with White Grape Juice 125ml",
    "url": "https://eshop.kddc.com/en/Juices",
    "category": "ice cream",
    "text": "1.2.3 Orange with White Grape Juice 125ml | ice cream | 1.62 KWD | None | orange | 125 ml | | | Carton - 18 Pieces | 18 pieces | KWD 1.62 || Piece | 1 piece | KWD 0.09 || Pack of Six | 6 pieces | KWD 0.54 | 100% fruit content. No added sugar, colour or preservatives. Great tasting orange juice for kids to replenish and hydrate on the go. KD 1.620",
    "meta": {
      "dedup_key": "https://eshop.kddc.com/en/Juices",
      "name": "1.2.3 Orange with White Grape Juice 125ml",
      "brand": null,
      "category": "juices",
      "flavor": "orange",
      "volume_ml": 125,
      "weight_g": null,
      "pack_units": null,
      "product_url": "https://eshop.kddc.com/en/Juices",
      "product_code": "FJUNS6125ORGN18",
      "sku": "FJUNS6125ORGN18",
      "availability": "in_stock",
      "price_now_kwd": 1.62,
      "options_text": "Carton - 18 Pieces | 18 pieces | KWD 1.62 || Piece | 1 piece | KWD 0.09 || Pack of Six | 6 pieces | KWD 0.54",
      "price_notes": "carton_per_piece≈0.090 KWD",
      "reviews_count": 0,
      "rating_stars": null,
      "desc": "100% fruit content. No added sugar, colour or preservatives. Great tasting orange juice for kids to replenish and hydrate on the go.  KD 1.620 "
    }
  },
  {
    "type": "product",
    "title": "Apple Juice 1 LTR",
    "url": "https://eshop.kddc.com/en/Juices/Apple-Juice-1-LTR-7563",
    "category": "ice cream",
    "text": "Apple Juice 1 LTR | ice cream | 5.4 KWD | None | apple | 1000 ml | | | Carton - 12 Pieces | 12 pieces | KWD 5.4 || Pack Of Four | 4 pieces | KWD 1.8 | 100% apple juice with no added sugar, colours, flavours or preservatives. Refreshing taste that can be enjoyed any time of the day. Nutrition Facts Per 100 ml. Nutrition Value Energy (Calories) 50 Calories from Fat (g) 0 Total Fat (g) 0 Saturated Fat (g) 0 Unsaturated Fat (g) 0 Trans Fat (g) 0 Cholesterol (g) 0 Sodium (mg) 0.005 Total Carbohydrate (g) 12 Dietary Fibres (g) 0 Total Sugars (g) 12 Added Sugar (g) 0 Protein (g) 0 KD 5.400 100 ml",
    "meta": {
      "dedup_key": "https://eshop.kddc.com/en/Juices/Apple-Juice-1-LTR-7563",
      "name": "Apple Juice 1 LTR",
      "brand": null,
      "category": "juices",
      "flavor": "apple",
      "volume_ml": 1000,
      "weight_g": null,
      "pack_units": null,
      "product_url": "https://eshop.kddc.com/en/Juices/Apple-Juice-1-LTR-7563",
      "product_code": "FJU1L4APPLTG",
      "sku": "FJU1L4APPLTG",
      "availability": "in_stock",
      "price_now_kwd": 5.4,
      "options_text": "Carton - 12 Pieces | 12 pieces | KWD 5.4 || Pack Of Four | 4 pieces | KWD 1.8",
      "price_notes": "carton_per_piece≈0.450 KWD",
      "reviews_count": 0,
      "rating_stars": null,
      "desc": "100% apple juice with no added sugar, colours, flavours or preservatives. Refreshing taste that can be enjoyed any time of the day. Nutrition Facts Per 100 ml. Nutrition Value Energy (Calories) 50 Calories from Fat (g) 0 Total Fat (g) 0 Saturated Fat (g) 0 Unsaturated Fat (g) 0 Trans Fat (g) 0 Cholesterol (g) 0 Sodium (mg) 0.005 Total Carbohydrate (g) 12 Dietary Fibres (g) 0 Total Sugars (g) 12 Added Sugar (g) 0 Protein (g) 0  KD 5.400 100 ml"
    }
  },
  {
    "type": "product",
    "title": "Apple Juice 250ml",
    "url": "https://eshop.kddc.com/en/Juices/Apple-Juice-250ml-7606",
    "category": "ice cream",
    "text": "Apple Juice 250ml | ice cream | 3.6 KWD | None | apple | 250 ml | | | Carton - 24 Pieces | 24 pieces | KWD 3.6 | 100% apple juice with no added sugar, colours, flavours or preservatives. Refreshing taste that can be enjoyed any time of the day. Nutrition Facts Per 100 ml. Nutrition Value Energy (Calories) 50 Calories from Fat (g) 0 Total Fat (g) 0 Saturated Fat (g) 0 Unsaturated Fat (g) 0 Trans Fat (g) 0 Cholesterol (g) 0 Sodium (mg) 0.005 Total Carbohydrate (g) 12 Dietary Fibres (g) 0 Total Sugars (g) 12 Added Sugar (g) 0 Protein (g) 0 KD 3.600 100 ml",
    "meta": {
      "dedup_key": "https://eshop.kddc.com/en/Juices/Apple-Juice-250ml-7606",
      "name": "Apple Juice 250ml",
      "brand": null,
      "category": "juices",
      "flavor": "apple",
      "volume_ml": 250,
      "weight_g": null,
      "pack_units": null,
      "product_url": "https://eshop.kddc.com/en/Juices/Apple-Juice-250ml-7606",
      "product_code": "FJUQL6APPL",
      "sku": "FJUQL6APPL",
      "availability": "in_stock",
      "price_now_kwd": 3.6,
      "options_text": "Carton - 24 Pieces | 24 pieces | KWD 3.6",
      "price_notes": "carton_per_piece≈0.150 KWD",
      "reviews_count": 0,
      "rating_stars": null,
      "desc": "100% apple juice with no added sugar, colours, flavours or preservatives. Refreshing taste that can be enjoyed any time of the day. Nutrition Facts Per 100 ml. Nutrition Value Energy (Calories) 50 Calories from Fat (g) 0 Total Fat (g) 0 Saturated Fat (g) 0 Unsaturated Fat (g) 0 Trans Fat (g) 0 Cholesterol (g) 0 Sodium (mg) 0.005 Total Carbohydrate (g) 12 Dietary Fibres (g) 0 Total Sugars (g) 12 Added Sugar (g) 0 Protein (g) 0  KD 3.600 100 ml"
    }
  },
  {
    "type": "product",
    "title": "Apple Raspberry Beverage (0% Sugar) 250ml",
    "url": "https://eshop.kddc.com/en/Juices/Apple-Raspberry-Beverage-(0-per--Sugar)-250ml-9566",
    "category": "ice cream",
    "text": "Apple Raspberry Beverage (0% Sugar) 250ml | ice cream | 1.98 KWD | None | apple | 250 ml | | | Carton - 18 Pieces | 18 pieces | KWD 1.98 || Pack of Six | 6 pieces | KWD 0.66 | A great tasting, water-based beverage with refreshing apple & raspberry flavor, containing zero sugar and rich in vitamins A, B6, C and D making it a great alternative to sugary drinks. Enjoy it chilled! KD 1.980",
    "meta": {
      "dedup_key": "https://eshop.kddc.com/en/Juices/Apple-Raspberry-Beverage-(0-per--Sugar)-250ml-9566",
      "name": "Apple Raspberry Beverage (0% Sugar) 250ml",
      "brand": null,
      "category": "juices",
      "flavor": "apple",
      "volume_ml": 250,
      "weight_g": null,
      "pack_units": null,
      "product_url": "https://eshop.kddc.com/en/Juices/Apple-Raspberry-Beverage-(0-per--Sugar)-250ml-9566",
      "product_code": "FJUBVGQPS6APRGM",
      "sku": "FJUBVGQPS6APRGM",
      "availability": "in_stock",
      "price_now_kwd": 1.98,
      "options_text": "Carton - 18 Pieces | 18 pieces | KWD 1.98 || Pack of Six | 6 pieces | KWD 0.66",
      "price_notes": "carton_per_piece≈0.110 KWD",
      "reviews_count": 0,
      "rating_stars": null,
      "desc": "A great tasting, water-based beverage with refreshing apple & raspberry flavor, containing zero sugar and rich in vitamins A, B6, C and D making it a great alternative to sugary drinks. Enjoy it chilled!  KD 1.980 "
    }
  },
  {
    "type": "product",
    "title": "Apricot Nectar 250ml",
    "url": "https://eshop.kddc.com/en/Juices/Apricot-Nectar-250ml-7604",
    "category": "ice cream",
    "text": "Apricot Nectar 250ml | ice cream | 3.6 KWD | None | None | 250 ml | | | Carton - 24 Pieces | 24 pieces | KWD 3.6 | Great tasting apricot nectar to replenish and hydrate on the go. No preservatives. Perfect for a sweet indulgent recharge. Nutrition Facts Per 100 ml. Nutrition Value Energy (Calories) 60 Calories from Fat (g) 0 Total Fat (g) 0 Saturated Fat (g) 0 Unsaturated Fat (g) 0 Trans Fat (g) 0 Cholesterol (g) 0 Sodium (mg) 0 Total Carbohydrate (g) 14 Dietary Fibres (g) 0 Total Sugars (g) 13 Added Sugar (g) 11 Protein (g) 0 KD 3.600 100 ml",
    "meta": {
      "dedup_key": "https://eshop.kddc.com/en/Juices/Apricot-Nectar-250ml-7604",
      "name": "Apricot Nectar 250ml",
      "brand": null,
      "category": "juices",
      "flavor": null,
      "volume_ml": 250,
      "weight_g": null,
      "pack_units": null,
      "product_url": "https://eshop.kddc.com/en/Juices/Apricot-Nectar-250ml-7604",
      "product_code": "FJUQL6APCT",
      "sku": "FJUQL6APCT",
      "availability": "in_stock",
      "price_now_kwd": 3.6,
      "options_text": "Carton - 24 Pieces | 24 pieces | KWD 3.6",
      "price_notes": "carton_per_piece≈0.150 KWD",
      "reviews_count": 0,
      "rating_stars": null,
      "desc": "Great tasting apricot nectar to replenish and hydrate on the go. No preservatives. Perfect for a sweet indulgent recharge. Nutrition Facts Per 100 ml. Nutrition Value Energy (Calories) 60 Calories from Fat (g) 0 Total Fat (g) 0 Saturated Fat (g) 0 Unsaturated Fat (g) 0 Trans Fat (g) 0 Cholesterol (g) 0 Sodium (mg) 0 Total Carbohydrate (g) 14 Dietary Fibres (g) 0 Total Sugars (g) 13 Added Sugar (g) 11 Protein (g) 0  KD 3.600 100 ml"
    }
  },
  {
    "type": "product",
    "title": "Cherry Drink 250ml",
    "url": "https://eshop.kddc.com/en/Juices/Cherry-Drink-250ml-7607",
    "category": "ice cream",
    "text": "Cherry Drink 250ml | ice cream | 3.6 KWD | None | None | 250 ml | | | Carton - 24 Pieces | 24 pieces | KWD 3.6 || Pack of Six | 6 pieces | KWD 0.9 | A light and refreshing drink full of cherry flavor that can be enjoyed any time of the day. No preservatives added. Nutrition Facts Per 100 ml. Nutrition Value Energy (Calories) 60 Calories from Fat (g) 0 Total Fat (g) 0 Saturated Fat (g) 0 Unsaturated Fat (g) 0 Trans Fat (g) 0 Cholesterol (g) 0 Sodium (mg) 0 Total Carbohydrate (g) 15 Dietary Fibres (g) 0 Total Sugars (g) 15 Added Sugar (g) 14 Protein (g) 0 KD 3.600 100 ml",
    "meta": {
      "dedup_key": "https://eshop.kddc.com/en/Juices/Cherry-Drink-250ml-7607",
      "name": "Cherry Drink 250ml",
      "brand": null,
      "category": "juices",
      "flavor": null,
      "volume_ml": 250,
      "weight_g": null,
      "pack_units": null,
      "product_url": "https://eshop.kddc.com/en/Juices/Cherry-Drink-250ml-7607",
      "product_code": "FJUQL6CHRY24",
      "sku": "FJUQL6CHRY24",
      "availability": "in_stock",
      "price_now_kwd": 3.6,
      "options_text": "Carton - 24 Pieces | 24 pieces | KWD 3.6 || Pack of Six | 6 pieces | KWD 0.9",
      "price_notes": "carton_per_piece≈0.150 KWD",
      "reviews_count": 0,
      "rating_stars": null,
      "desc": "A light and refreshing drink full of cherry flavor that can be enjoyed any time of the day. No preservatives added. Nutrition Facts Per 100 ml. Nutrition Value Energy (Calories) 60 Calories from Fat (g) 0 Total Fat (g) 0 Saturated Fat (g) 0 Unsaturated Fat (g) 0 Trans Fat (g) 0 Cholesterol (g) 0 Sodium (mg) 0 Total Carbohydrate (g) 15 Dietary Fibres (g) 0 Total Sugars (g) 15 Added Sugar (g) 14 Protein (g) 0  KD 3.600 100 ml"
    }
  },
  {
    "type": "product",
    "title": "Cocktail Drink 1 LTR",
    "url": "https://eshop.kddc.com/en/Juices/Cocktail-Drink-1-LTR-7567",
    "category": "ice cream",
    "text": "Cocktail Drink 1 LTR | ice cream | 5.4 KWD | None | None | 1000 ml | | | Carton - 12 Pieces | 12 pieces | KWD 5.4 || Pack Of Four | 4 pieces | KWD 1.8 | Great tasting and refreshing cocktail nectar. A delicious mix of fruits that is a family favorite for any occasion. No preservatives added. Nutrition Facts Per 100 ml. Nutrition Value Energy (Calories) 45 Calories from Fat (g) 0 Total Fat (g) 0 Saturated Fat (g) 0 Unsaturated Fat (g) 0 Trans Fat (g) 0 Cholesterol (g) 0 Sodium (mg) 0 Total Carbohydrate (g) 12 Dietary Fibres (g) 0 Total Sugars (g) 11 Added Sugar (g) 8 Protein (g) 0 KD 5.400 100 ml",
    "meta": {
      "dedup_key": "https://eshop.kddc.com/en/Juices/Cocktail-Drink-1-LTR-7567",
      "name": "Cocktail Drink 1 LTR",
      "brand": null,
      "category": "juices",
      "flavor": null,
      "volume_ml": 1000,
      "weight_g": null,
      "pack_units": null,
      "product_url": "https://eshop.kddc.com/en/Juices/Cocktail-Drink-1-LTR-7567",
      "product_code": "FJU1L4COCKTG",
      "sku": "FJU1L4COCKTG",
      "availability": "in_stock",
      "price_now_kwd": 5.4,
      "options_text": "Carton - 12 Pieces | 12 pieces | KWD 5.4 || Pack Of Four | 4 pieces | KWD 1.8",
      "price_notes": "carton_per_piece≈0.450 KWD",
      "reviews_count": 0,
      "rating_stars": null,
      "desc": "Great tasting and refreshing cocktail nectar. A delicious mix of fruits that is a family favorite for any occasion. No preservatives added. Nutrition Facts Per 100 ml. Nutrition Value Energy (Calories) 45 Calories from Fat (g) 0 Total Fat (g) 0 Saturated Fat (g) 0 Unsaturated Fat (g) 0 Trans Fat (g) 0 Cholesterol (g) 0 Sodium (mg) 0 Total Carbohydrate (g) 12 Dietary Fibres (g) 0 Total Sugars (g) 11 Added Sugar (g) 8 Protein (g) 0  KD 5.400 100 ml"
    }
  },
  {
    "type": "product",
    "title": "Cocktail Drink 250 ML",
    "url": "https://eshop.kddc.com/en/Juices/Cocktail-Drink-250-ML-7609",
    "category": "ice cream",
    "text": "Cocktail Drink 250 ML | ice cream | 3.6 KWD | None | None | 250 ml | | | Carton - 24 Pieces | 24 pieces | KWD 3.6 || Pack of Six | 6 pieces | KWD 0.9 | Great tasting and refreshing cocktail nectar. A delicious mix of fruits that is a family favorite for any occasion. No preservatives added. Nutrition Facts Per 100 ml. Nutrition Value Energy (Calories) 45 Calories from Fat (g) 0 Total Fat (g) 0 Saturated Fat (g) 0 Unsaturated Fat (g) 0 Trans Fat (g) 0 Cholesterol (g) 0 Sodium (mg) 0 Total Carbohydrate (g) 12 Dietary Fibres (g) 0 Total Sugars (g) 11 Added Sugar (g) 8 Protein (g) 0 KD 3.600 100 ml",
    "meta": {
      "dedup_key": "https://eshop.kddc.com/en/Juices/Cocktail-Drink-250-ML-7609",
      "name": "Cocktail Drink 250 ML",
      "brand": null,
      "category": "juices",
      "flavor": null,
      "volume_ml": 250,
      "weight_g": null,
      "pack_units": null,
      "product_url": "https://eshop.kddc.com/en/Juices/Cocktail-Drink-250-ML-7609",
      "product_code": "FJUQL6COCK",
      "sku": "FJUQL6COCK",
      "availability": "in_stock",
      "price_now_kwd": 3.6,
      "options_text": "Carton - 24 Pieces | 24 pieces | KWD 3.6 || Pack of Six | 6 pieces | KWD 0.9",
      "price_notes": "carton_per_piece≈0.150 KWD",
      "reviews_count": 0,
      "rating_stars": null,
      "desc": "Great tasting and refreshing cocktail nectar. A delicious mix of fruits that is a family favorite for any occasion. No preservatives added. Nutrition Facts Per 100 ml. Nutrition Value Energy (Calories) 45 Calories from Fat (g) 0 Total Fat (g) 0 Saturated Fat (g) 0 Unsaturated Fat (g) 0 Trans Fat (g) 0 Cholesterol (g) 0 Sodium (mg) 0 Total Carbohydrate (g) 12 Dietary Fibres (g) 0 Total Sugars (g) 11 Added Sugar (g) 8 Protein (g) 0  KD 3.600 100 ml"
    }
  },
  {
    "type": "product",
    "title": "Cocktail Drink 250ml (Prisma Pack)",
    "url": "https://eshop.kddc.com/en/Juices/Cocktail-Drink-250ml-(Prisma-Pack)-8193",
    "category": "ice cream",
    "text": "Cocktail Drink 250ml (Prisma Pack) | ice cream | 2.7 KWD | None | None | 250 ml | | | Carton - 18 Pieces | 18 pieces | KWD 2.7 | Great tasting and refreshing cocktail nectar. A delicious mix of fruits that is a family favorite for any occasion. No preservatives added. Nutrition Facts Per 100 ml. Nutrition Value Energy (Calories) 45 Calories from Fat (g) 0 Total Fat (g) 0 Saturated Fat (g) 0 Unsaturated Fat (g) 0 Trans Fat (g) 0 Cholesterol (g) 0 Sodium (mg) 0 Total Carbohydrate (g) 12 Dietary Fibres (g) 0 Total Sugars (g) 11 Added Sugar (g) 8 Protein (g) 0 KD 2.700 100 ml",
    "meta": {
      "dedup_key": "https://eshop.kddc.com/en/Juices/Cocktail-Drink-250ml-(Prisma-Pack)-8193",
      "name": "Cocktail Drink 250ml (Prisma Pack)",
      "brand": null,
      "category": "juices",
      "flavor": null,
      "volume_ml": 250,
      "weight_g": null,
      "pack_units": null,
      "product_url": "https://eshop.kddc.com/en/Juices/Cocktail-Drink-250ml-(Prisma-Pack)-8193",
      "product_code": "FJUQL6PSCOCK18",
      "sku": "FJUQL6PSCOCK18",
      "availability": "in_stock",
      "price_now_kwd": 2.7,
      "options_text": "Carton - 18 Pieces | 18 pieces | KWD 2.7",
      "price_notes": "carton_per_piece≈0.150 KWD",
      "reviews_count": 0,
      "rating_stars": null,
      "desc": "Great tasting and refreshing cocktail nectar. A delicious mix of fruits that is a family favorite for any occasion. No preservatives added. Nutrition Facts Per 100 ml. Nutrition Value Energy (Calories) 45 Calories from Fat (g) 0 Total Fat (g) 0 Saturated Fat (g) 0 Unsaturated Fat (g) 0 Trans Fat (g) 0 Cholesterol (g) 0 Sodium (mg) 0 Total Carbohydrate (g) 12 Dietary Fibres (g) 0 Total Sugars (g) 11 Added Sugar (g) 8 Protein (g) 0  KD 2.700 100 ml"
    }
  },
  {
    "type": "product",
    "title": "Cocktail Fruit Nectar (No Added Sugar) 125ml",
    "url": "https://eshop.kddc.com/en/Juices/Cocktail-Fruit-Nectar-(No-Added-Sugar)-125ml-8800",
    "category": "ice cream",
    "text": "Cocktail Fruit Nectar (No Added Sugar) 125ml | ice cream | 1.62 KWD | None | None | 125 ml | | | Carton - 18 Pieces | 18 pieces | KWD 1.62 || Piece | 1 piece | KWD 0.09 || Pack of Six | 6 pieces | KWD 0.54 | 100% fruit content. No added sugar, colour or preservatives. A delicious mix of fruits that is a family favorite for any occasion. Nutrition Facts Per 100 ml. Nutrition Value Energy (Calories) 50 Calories from Fat (g) 0 Total Fat (g) 0 Saturated Fat (g) 0 Unsaturated Fat (g) 0 Trans Fat (g) 0 Cholesterol (g) 0 Sodium (mg) 0.005 Total Carbohydrate (g) 12 Dietary Fibres (g) 0 Total Sugars (g) 12 Added Sugar (g) 0 Protein (g) 0 KD 1.620 100 ml",
    "meta": {
      "dedup_key": "https://eshop.kddc.com/en/Juices/Cocktail-Fruit-Nectar-(No-Added-Sugar)-125ml-8800",
      "name": "Cocktail Fruit Nectar (No Added Sugar) 125ml",
      "brand": null,
      "category": "juices",
      "flavor": null,
      "volume_ml": 125,
      "weight_g": null,
      "pack_units": null,
      "product_url": "https://eshop.kddc.com/en/Juices/Cocktail-Fruit-Nectar-(No-Added-Sugar)-125ml-8800",
      "product_code": "FJUNS6125COCK18",
      "sku": "FJUNS6125COCK18",
      "availability": "in_stock",
      "price_now_kwd": 1.62,
      "options_text": "Carton - 18 Pieces | 18 pieces | KWD 1.62 || Piece | 1 piece | KWD 0.09 || Pack of Six | 6 pieces | KWD 0.54",
      "price_notes": "carton_per_piece≈0.090 KWD",
      "reviews_count": 0,
      "rating_stars": null,
      "desc": "100% fruit content. No added sugar, colour or preservatives. A delicious mix of fruits that is a family favorite for any occasion. Nutrition Facts Per 100 ml. Nutrition Value Energy (Calories) 50 Calories from Fat (g) 0 Total Fat (g) 0 Saturated Fat (g) 0 Unsaturated Fat (g) 0 Trans Fat (g) 0 Cholesterol (g) 0 Sodium (mg) 0.005 Total Carbohydrate (g) 12 Dietary Fibres (g) 0 Total Sugars (g) 12 Added Sugar (g) 0 Protein (g) 0  KD 1.620 100 ml"
    }
  },
  {
    "type": "product",
    "title": "Cranberry Drink 250 ML (Prisma Pack)",
    "url": "https://eshop.kddc.com/en/Juices/Cranberry-Drink-250-ML-(Prisma-Pack)-8192",
    "category": "ice cream",
    "text": "Cranberry Drink 250 ML (Prisma Pack) | ice cream | 2.7 KWD | None | None | 250 ml | | | Carton - 18 Pieces | 18 pieces | KWD 2.7 | A light & refreshing drink full of cranberry flavor that can be enjoyed any time of the day. No preservatives added Nutrition Facts Per 100 ml. Nutrition Value Energy (Calories) 50 Calories from Fat (g) 0 Total Fat (g) 0 Saturated Fat (g) 0 Unsaturated Fat (g) 0 Trans Fat (g) 0 Cholesterol (g) 0 Sodium (mg) 0 Total Carbohydrate (g) 14 Dietary Fibres (g) 0 Total Sugars (g) 14 Added Sugar (g) 11 Protein (g) 0 KD 2.700 100 ml",
    "meta": {
      "dedup_key": "https://eshop.kddc.com/en/Juices/Cranberry-Drink-250-ML-(Prisma-Pack)-8192",
      "name": "Cranberry Drink 250 ML (Prisma Pack)",
      "brand": null,
      "category": "juices",
      "flavor": null,
      "volume_ml": 250,
      "weight_g": null,
      "pack_units": null,
      "product_url": "https://eshop.kddc.com/en/Juices/Cranberry-Drink-250-ML-(Prisma-Pack)-8192",
      "product_code": "FJUQL6PSCBRY18",
      "sku": "FJUQL6PSCBRY18",
      "availability": "in_stock",
      "price_now_kwd": 2.7,
      "options_text": "Carton - 18 Pieces | 18 pieces | KWD 2.7",
      "price_notes": "carton_per_piece≈0.150 KWD",
      "reviews_count": 0,
      "rating_stars": null,
      "desc": "A light & refreshing drink full of cranberry flavor that can be enjoyed any time of the day. No preservatives added Nutrition Facts Per 100 ml. Nutrition Value Energy (Calories) 50 Calories from Fat (g) 0 Total Fat (g) 0 Saturated Fat (g) 0 Unsaturated Fat (g) 0 Trans Fat (g) 0 Cholesterol (g) 0 Sodium (mg) 0 Total Carbohydrate (g) 14 Dietary Fibres (g) 0 Total Sugars (g) 14 Added Sugar (g) 11 Protein (g) 0  KD 2.700 100 ml"
    }
  },
  {
    "type": "product",
    "title": "Grape Juice 1 LTR",
    "url": "https://eshop.kddc.com/en/Juices/Grape-Juice-1-LTR-7573",
    "category": "ice cream",
    "text": "Grape Juice 1 LTR | ice cream | 6.0 KWD | None | None | 1000 ml | | | Carton - 12 Pieces | 12 pieces | KWD 6.0 || Pack Of Four | 4 pieces | KWD 2.0 | 100% red grape juice with no added sugar, colours, flavours or preservatives. Delicous refreshment that's perfect for any occasion. Nutrition Facts Per 100 ml. Nutrition Value Energy (Calories) 60 Calories from Fat (g) 0 Total Fat (g) 0 Saturated Fat (g) 0 Unsaturated Fat (g) 0 Trans Fat (g) 0 Cholesterol (g) 0 Sodium (mg) 0 Total Carbohydrate (g) 16 Dietary Fibres (g) 0 Total Sugars (g) 16 Added Sugar (g) 0 Protein (g) 0 KD 6.000 100 ml",
    "meta": {
      "dedup_key": "https://eshop.kddc.com/en/Juices/Grape-Juice-1-LTR-7573",
      "name": "Grape Juice 1 LTR",
      "brand": null,
      "category": "juices",
      "flavor": null,
      "volume_ml": 1000,
      "weight_g": null,
      "pack_units": null,
      "product_url": "https://eshop.kddc.com/en/Juices/Grape-Juice-1-LTR-7573",
      "product_code": "FJU1L4GRPETG",
      "sku": "FJU1L4GRPETG",
      "availability": "in_stock",
      "price_now_kwd": 6.0,
      "options_text": "Carton - 12 Pieces | 12 pieces | KWD 6.0 || Pack Of Four | 4 pieces | KWD 2.0",
      "price_notes": "carton_per_piece≈0.500 KWD",
      "reviews_count": 0,
      "rating_stars": null,
      "desc": "100% red grape juice with no added sugar, colours, flavours or preservatives. Delicous refreshment that's perfect for any occasion. Nutrition Facts Per 100 ml. Nutrition Value Energy (Calories) 60 Calories from Fat (g) 0 Total Fat (g) 0 Saturated Fat (g) 0 Unsaturated Fat (g) 0 Trans Fat (g) 0 Cholesterol (g) 0 Sodium (mg) 0 Total Carbohydrate (g) 16 Dietary Fibres (g) 0 Total Sugars (g) 16 Added Sugar (g) 0 Protein (g) 0  KD 6.000 100 ml"
    }
  },
  {
    "type": "product",
    "title": "Grape Juice 250ml",
    "url": "https://eshop.kddc.com/en/Juices/Grape-Juice-250ml-7615",
    "category": "ice cream",
    "text": "Grape Juice 250ml | ice cream | 3.6 KWD | None | None | 250 ml | | | Carton - 24 Pieces | 24 pieces | KWD 3.6 | 100% red grape juice with no added sugar, colours, flavours or preservatives. Delicous refreshment that's perfect for any occasion. Nutrition Facts Per 100 ml. Nutrition Value Energy (Calories) 60 Calories from Fat (g) 0 Total Fat (g) 0 Saturated Fat (g) 0 Unsaturated Fat (g) 0 Trans Fat (g) 0 Cholesterol (g) 0 Sodium (mg) 0 Total Carbohydrate (g) 16 Dietary Fibres (g) 0 Total Sugars (g) 16 Added Sugar (g) 0 Protein (g) 0 KD 3.600 100 ml",
    "meta": {
      "dedup_key": "https://eshop.kddc.com/en/Juices/Grape-Juice-250ml-7615",
      "name": "Grape Juice 250ml",
      "brand": null,
      "category": "juices",
      "flavor": null,
      "volume_ml": 250,
      "weight_g": null,
      "pack_units": null,
      "product_url": "https://eshop.kddc.com/en/Juices/Grape-Juice-250ml-7615",
      "product_code": "FJUQL6GRPE",
      "sku": "FJUQL6GRPE",
      "availability": "in_stock",
      "price_now_kwd": 3.6,
      "options_text": "Carton - 24 Pieces | 24 pieces | KWD 3.6",
      "price_notes": "carton_per_piece≈0.150 KWD",
      "reviews_count": 0,
      "rating_stars": null,
      "desc": "100% red grape juice with no added sugar, colours, flavours or preservatives. Delicous refreshment that's perfect for any occasion. Nutrition Facts Per 100 ml. Nutrition Value Energy (Calories) 60 Calories from Fat (g) 0 Total Fat (g) 0 Saturated Fat (g) 0 Unsaturated Fat (g) 0 Trans Fat (g) 0 Cholesterol (g) 0 Sodium (mg) 0 Total Carbohydrate (g) 16 Dietary Fibres (g) 0 Total Sugars (g) 16 Added Sugar (g) 0 Protein (g) 0  KD 3.600 100 ml"
    }
  },
  {
    "type": "product",
    "title": "Grapefruit Juice 1 LTR",
    "url": "https://eshop.kddc.com/en/Juices/Grapefruit-Juice-1-LTR-7572",
    "category": "ice cream",
    "text": "Grapefruit Juice 1 LTR | ice cream | 6.0 KWD | None | None | 1000 ml | | | Carton - 12 Pieces | 12 pieces | KWD 6.0 || Pack Of Four | 4 pieces | KWD 2.0 | 100% grapefruit juice with no added sugar, colours, flavours or preservatives. Perfect for the weight watchers looking for a healthy option. Nutrition Facts Per 100 ml. Nutrition Value Energy (Calories) 40 Calories from Fat (g) 0 Total Fat (g) 0 Saturated Fat (g) 0 Unsaturated Fat (g) 0 Trans Fat (g) 0 Cholesterol (g) 0 Sodium (mg) 0 Total Carbohydrate (g) 10 Dietary Fibres (g) 0 Total Sugars (g) 10 Added Sugar (g) 0 Protein (g) 0 KD 6.000 100 ml",
    "meta": {
      "dedup_key": "https://eshop.kddc.com/en/Juices/Grapefruit-Juice-1-LTR-7572",
      "name": "Grapefruit Juice 1 LTR",
      "brand": null,
      "category": "juices",
      "flavor": null,
      "volume_ml": 1000,
      "weight_g": null,
      "pack_units": null,
      "product_url": "https://eshop.kddc.com/en/Juices/Grapefruit-Juice-1-LTR-7572",
      "product_code": "FJU1L4GRFTTG",
      "sku": "FJU1L4GRFTTG",
      "availability": "in_stock",
      "price_now_kwd": 6.0,
      "options_text": "Carton - 12 Pieces | 12 pieces | KWD 6.0 || Pack Of Four | 4 pieces | KWD 2.0",
      "price_notes": "carton_per_piece≈0.500 KWD",
      "reviews_count": 0,
      "rating_stars": null,
      "desc": "100% grapefruit juice with no added sugar, colours, flavours or preservatives. Perfect for the weight watchers looking for a healthy option. Nutrition Facts Per 100 ml. Nutrition Value Energy (Calories) 40 Calories from Fat (g) 0 Total Fat (g) 0 Saturated Fat (g) 0 Unsaturated Fat (g) 0 Trans Fat (g) 0 Cholesterol (g) 0 Sodium (mg) 0 Total Carbohydrate (g) 10 Dietary Fibres (g) 0 Total Sugars (g) 10 Added Sugar (g) 0 Protein (g) 0  KD 6.000 100 ml"
    }
  },
  {
    "type": "product",
    "title": "Grapefruit Juice 250ml",
    "url": "https://eshop.kddc.com/en/Juices/Grapefruit-Juice-250ml-7613",
    "category": "ice cream",
    "text": "Grapefruit Juice 250ml | ice cream | 3.6 KWD | None | None | 250 ml | | | Carton - 24 Pieces | 24 pieces | KWD 3.6 | 100% grapefruit juice with no added sugar, colours, flavours or preservatives. Perfect for the weight watchers looking for a healthy option. Nutrition Facts Per 100 ml. Nutrition Value Energy (Calories) 40 Calories from Fat (g) 0 Total Fat (g) 0 Saturated Fat (g) 0 Unsaturated Fat (g) 0 Trans Fat (g) 0 Cholesterol (g) 0 Sodium (mg) 0 Total Carbohydrate (g) 10 Dietary Fibres (g) 0 Total Sugars (g) 10 Added Sugar (g) 0 Protein (g) 0 KD 3.600 100 ml",
    "meta": {
      "dedup_key": "https://eshop.kddc.com/en/Juices/Grapefruit-Juice-250ml-7613",
      "name": "Grapefruit Juice 250ml",
      "brand": null,
      "category": "juices",
      "flavor": null,
      "volume_ml": 250,
      "weight_g": null,
      "pack_units": null,
      "product_url": "https://eshop.kddc.com/en/Juices/Grapefruit-Juice-250ml-7613",
      "product_code": "FJUQL6GRFT",
      "sku": "FJUQL6GRFT",
      "availability": "in_stock",
      "price_now_kwd": 3.6,
      "options_text": "Carton - 24 Pieces | 24 pieces | KWD 3.6",
      "price_notes": "carton_per_piece≈0.150 KWD",
      "reviews_count": 0,
      "rating_stars": null,
      "desc": "100% grapefruit juice with no added sugar, colours, flavours or preservatives. Perfect for the weight watchers looking for a healthy option. Nutrition Facts Per 100 ml. Nutrition Value Energy (Calories) 40 Calories from Fat (g) 0 Total Fat (g) 0 Saturated Fat (g) 0 Unsaturated Fat (g) 0 Trans Fat (g) 0 Cholesterol (g) 0 Sodium (mg) 0 Total Carbohydrate (g) 10 Dietary Fibres (g) 0 Total Sugars (g) 10 Added Sugar (g) 0 Protein (g) 0  KD 3.600 100 ml"
    }
  },
  {
    "type": "product",
    "title": "Guava Nectar 1 LTR",
    "url": "https://eshop.kddc.com/en/Juices/Guava-Nectar-1-LTR-7575",
    "category": "ice cream",
    "text": "Guava Nectar 1 LTR | ice cream | 5.7 KWD | None | None | 1000 ml | | | Carton - 12 Pieces | 12 pieces | KWD 5.7 || Pack Of Four | 4 pieces | KWD 1.9 | Great tasting and refreshing guava nectar. A classic tropical juice that everyone in the family can enjoy any time of the day. No preservatives. Nutrition Facts Per 100 ml. Nutrition Value Energy (Calories) 60 Calories from Fat (g) 0 Total Fat (g) 0 Saturated Fat (g) 0 Unsaturated Fat (g) 0 Trans Fat (g) 0 Cholesterol (g) 0 Sodium (mg) 0.005 Total Carbohydrate (g) 14 Dietary Fibres (g) 0 Total Sugars (g) 12 Added Sugar (g) 10 Protein (g) 0 KD 5.700 100 ml",
    "meta": {
      "dedup_key": "https://eshop.kddc.com/en/Juices/Guava-Nectar-1-LTR-7575",
      "name": "Guava Nectar 1 LTR",
      "brand": null,
      "category": "juices",
      "flavor": null,
      "volume_ml": 1000,
      "weight_g": null,
      "pack_units": null,
      "product_url": "https://eshop.kddc.com/en/Juices/Guava-Nectar-1-LTR-7575",
      "product_code": "FJU1L4GUVATG",
      "sku": "FJU1L4GUVATG",
      "availability": "in_stock",
      "price_now_kwd": 5.7,
      "options_text": "Carton - 12 Pieces | 12 pieces | KWD 5.7 || Pack Of Four | 4 pieces | KWD 1.9",
      "price_notes": "carton_per_piece≈0.475 KWD",
      "reviews_count": 0,
      "rating_stars": null,
      "desc": "Great tasting and refreshing guava nectar. A classic tropical juice that everyone in the family can enjoy any time of the day. No preservatives. Nutrition Facts Per 100 ml. Nutrition Value Energy (Calories) 60 Calories from Fat (g) 0 Total Fat (g) 0 Saturated Fat (g) 0 Unsaturated Fat (g) 0 Trans Fat (g) 0 Cholesterol (g) 0 Sodium (mg) 0.005 Total Carbohydrate (g) 14 Dietary Fibres (g) 0 Total Sugars (g) 12 Added Sugar (g) 10 Protein (g) 0  KD 5.700 100 ml"
    }
  },
  {
    "type": "product",
    "title": "Guava Nectar 250ml",
    "url": "https://eshop.kddc.com/en/Juices/Guava-Nectar-250ml-7617",
    "category": "ice cream",
    "text": "Guava Nectar 250ml | ice cream | 3.6 KWD | None | None | 250 ml | | | Carton - 24 Pieces | 24 pieces | KWD 3.6 | Great tasting and refreshing guava nectar. A classic tropical juice that everyone in the family can enjoy any time of the day. No preservatives. Nutrition Facts Per 100 ml. Nutrition Value Energy (Calories) 60 Calories from Fat (g) 0 Total Fat (g) 0 Saturated Fat (g) 0 Unsaturated Fat (g) 0 Trans Fat (g) 0 Cholesterol (g) 0 Sodium (mg) 0.005 Total Carbohydrate (g) 14 Dietary Fibres (g) 0 Total Sugars (g) 12 Added Sugar (g) 10 Protein (g) 0 KD 3.600 100 ml",
    "meta": {
      "dedup_key": "https://eshop.kddc.com/en/Juices/Guava-Nectar-250ml-7617",
      "name": "Guava Nectar 250ml",
      "brand": null,
      "category": "juices",
      "flavor": null,
      "volume_ml": 250,
      "weight_g": null,
      "pack_units": null,
      "product_url": "https://eshop.kddc.com/en/Juices/Guava-Nectar-250ml-7617",
      "product_code": "FJUQL6GUVA",
      "sku": "FJUQL6GUVA",
      "availability": "in_stock",
      "price_now_kwd": 3.6,
      "options_text": "Carton - 24 Pieces | 24 pieces | KWD 3.6",
      "price_notes": "carton_per_piece≈0.150 KWD",
      "reviews_count": 0,
      "rating_stars": null,
      "desc": "Great tasting and refreshing guava nectar. A classic tropical juice that everyone in the family can enjoy any time of the day. No preservatives. Nutrition Facts Per 100 ml. Nutrition Value Energy (Calories) 60 Calories from Fat (g) 0 Total Fat (g) 0 Saturated Fat (g) 0 Unsaturated Fat (g) 0 Trans Fat (g) 0 Cholesterol (g) 0 Sodium (mg) 0.005 Total Carbohydrate (g) 14 Dietary Fibres (g) 0 Total Sugars (g) 12 Added Sugar (g) 10 Protein (g) 0  KD 3.600 100 ml"
    }
  },
  {
    "type": "product",
    "title": "Guava with Orange , Apricot & Cranberry - 100% Natural Juice 250 ML - 100% Natural Juice 250ml",
    "url": "https://eshop.kddc.com/en/Juices/Guava-with-Orange-,-Apricot--and--Cranberry---100-per--Natural-Juice-250-ML---100-per--Natural-Juice-250ml-8198",
    "category": "ice cream",
    "text": "Guava with Orange , Apricot & Cranberry - 100% Natural Juice 250 ML - 100% Natural Juice 250ml | ice cream | 3.51 KWD | None | orange | 250 ml | | | Carton - 18 Pieces | 18 pieces | KWD 3.51 | A delicious 100% juice blend of super fruits Guavas, Oranges, Apricots and Cranberries with no added sugar or preservatives. Rich in Vitamins A, B6 and Iron. Nutrition Facts Per 100 ml. Nutrition Value Energy (Calories) 60 Calories from Fat (g) 0 Total Fat (g) 0 Saturated Fat (g) 0 Unsaturated Fat (g) 0 Trans Fat (g) 0 Cholesterol (g) 0 Sodium (mg) 0 Total Carbohydrate (g) 15 Dietary Fibres (g) 0 Total Sugars (g) 14 Added Sugar (g) 0 Protein (g) 0 Vitamin A (IU) 167 Vitamin B6 (mg) 0.58 Vitamin C (mg) 55 Potassium (mg) 130 Iron (mg) 1.9 Zinc (mg) 1.2 KD 3.510 100 ml",
    "meta": {
      "dedup_key": "https://eshop.kddc.com/en/Juices/Guava-with-Orange-,-Apricot--and--Cranberry---100-per--Natural-Juice-250-ML---100-per--Natural-Juice-250ml-8198",
      "name": "Guava with Orange , Apricot & Cranberry - 100% Natural Juice 250 ML - 100% Natural Juice 250ml",
      "brand": null,
      "category": "juices",
      "flavor": "orange",
      "volume_ml": 250,
      "weight_g": null,
      "pack_units": null,
      "product_url": "https://eshop.kddc.com/en/Juices/Guava-with-Orange-,-Apricot--and--Cranberry---100-per--Natural-Juice-250-ML---100-per--Natural-Juice-250ml-8198",
      "product_code": "FPFQL3PSAOG18",
      "sku": "FPFQL3PSAOG18",
      "availability": "in_stock",
      "price_now_kwd": 3.51,
      "options_text": "Carton - 18 Pieces | 18 pieces | KWD 3.51",
      "price_notes": "carton_per_piece≈0.195 KWD",
      "reviews_count": 0,
      "rating_stars": null,
      "desc": "A delicious 100% juice blend of super fruits Guavas, Oranges, Apricots and Cranberries with no added sugar or preservatives. Rich in Vitamins A, B6 and Iron. Nutrition Facts Per 100 ml. Nutrition Value Energy (Calories) 60 Calories from Fat (g) 0 Total Fat (g) 0 Saturated Fat (g) 0 Unsaturated Fat (g) 0 Trans Fat (g) 0 Cholesterol (g) 0 Sodium (mg) 0 Total Carbohydrate (g) 15 Dietary Fibres (g) 0 Total Sugars (g) 14 Added Sugar (g) 0 Protein (g) 0 Vitamin A (IU) 167 Vitamin B6 (mg) 0.58 Vitamin C (mg) 55 Potassium (mg) 130 Iron (mg) 1.9 Zinc (mg) 1.2  KD 3.510 100 ml"
    }
  },
  {
    "type": "product",
    "title": "Mango Nectar (No Added Sugar) 125ml",
    "url": "https://eshop.kddc.com/en/Juices/Mango-Nectar-(No-Added-Sugar)-125ml-8801",
    "category": "ice cream",
    "text": "Mango Nectar (No Added Sugar) 125ml | ice cream | 1.62 KWD | None | None | 125 ml | | | Carton - 18 Pieces | 18 pieces | KWD 1.62 || Piece | 1 piece | KWD 0.09 || Pack of Six | 6 pieces | KWD 0.54 | 100% fruit content. No added sugar, colour or preservatives. An all time favorite that's enjoyed by whole family. Nutrition Facts Per 100 ml. Nutrition Value Energy (Calories) 60 Calories from Fat (g) 0 Total Fat (g) 0 Saturated Fat (g) 0 Unsaturated Fat (g) 0 Trans Fat (g) 0 Cholesterol (g) 0 Sodium (mg) 0.005 Total Carbohydrate (g) 15 Dietary Fibres (g) 0 Total Sugars (g) 14 Added Sugar (g) 0 Protein (g) 0 KD 1.620 100 ml",
    "meta": {
      "dedup_key": "https://eshop.kddc.com/en/Juices/Mango-Nectar-(No-Added-Sugar)-125ml-8801",
      "name": "Mango Nectar (No Added Sugar) 125ml",
      "brand": null,
      "category": "juices",
      "flavor": null,
      "volume_ml": 125,
      "weight_g": null,
      "pack_units": null,
      "product_url": "https://eshop.kddc.com/en/Juices/Mango-Nectar-(No-Added-Sugar)-125ml-8801",
      "product_code": "FJUNS6125MNGO18",
      "sku": "FJUNS6125MNGO18",
      "availability": "in_stock",
      "price_now_kwd": 1.62,
      "options_text": "Carton - 18 Pieces | 18 pieces | KWD 1.62 || Piece | 1 piece | KWD 0.09 || Pack of Six | 6 pieces | KWD 0.54",
      "price_notes": "carton_per_piece≈0.090 KWD",
      "reviews_count": 0,
      "rating_stars": null,
      "desc": "100% fruit content. No added sugar, colour or preservatives. An all time favorite that's enjoyed by whole family. Nutrition Facts Per 100 ml. Nutrition Value Energy (Calories) 60 Calories from Fat (g) 0 Total Fat (g) 0 Saturated Fat (g) 0 Unsaturated Fat (g) 0 Trans Fat (g) 0 Cholesterol (g) 0 Sodium (mg) 0.005 Total Carbohydrate (g) 15 Dietary Fibres (g) 0 Total Sugars (g) 14 Added Sugar (g) 0 Protein (g) 0  KD 1.620 100 ml"
    }
  },
  {
    "type": "product",
    "title": "Mango Nectar 1 LTR",
    "url": "https://eshop.kddc.com/en/Juices/Mango-Nectar-1-LTR-7579",
    "category": "ice cream",
    "text": "Mango Nectar 1 LTR | ice cream | 6.0 KWD | None | mango | 1000 ml | | | Carton - 12 Pieces | 12 pieces | KWD 6.0 || Pack Of Four | 4 pieces | KWD 2.0 | Great tasting and refreshing mango nectar. An all time favorite that's enjoyed by whole family. No preservatives. Nutrition Facts Per 100 ml. Nutrition Value Energy (Calories) 60 Calories from Fat (g) 0 Total Fat (g) 0 Saturated Fat (g) 0 Unsaturated Fat (g) 0 Trans Fat (g) 0 Cholesterol (g) 0 Sodium (mg) 0 Total Carbohydrate (g) 15 Dietary Fibres (g) 0 Total Sugars (g) 13 Added Sugar (g) 9 Protein (g) 0 KD 6.000 100 ml",
    "meta": {
      "dedup_key": "https://eshop.kddc.com/en/Juices/Mango-Nectar-1-LTR-7579",
      "name": "Mango Nectar 1 LTR",
      "brand": null,
      "category": "juices",
      "flavor": "mango",
      "volume_ml": 1000,
      "weight_g": null,
      "pack_units": null,
      "product_url": "https://eshop.kddc.com/en/Juices/Mango-Nectar-1-LTR-7579",
      "product_code": "FJU1L4MNGOTG",
      "sku": "FJU1L4MNGOTG",
      "availability": "in_stock",
      "price_now_kwd": 6.0,
      "options_text": "Carton - 12 Pieces | 12 pieces | KWD 6.0 || Pack Of Four | 4 pieces | KWD 2.0",
      "price_notes": "carton_per_piece≈0.500 KWD",
      "reviews_count": 0,
      "rating_stars": null,
      "desc": "Great tasting and refreshing mango nectar. An all time favorite that's enjoyed by whole family. No preservatives. Nutrition Facts Per 100 ml. Nutrition Value Energy (Calories) 60 Calories from Fat (g) 0 Total Fat (g) 0 Saturated Fat (g) 0 Unsaturated Fat (g) 0 Trans Fat (g) 0 Cholesterol (g) 0 Sodium (mg) 0 Total Carbohydrate (g) 15 Dietary Fibres (g) 0 Total Sugars (g) 13 Added Sugar (g) 9 Protein (g) 0  KD 6.000 100 ml"
    }
  },
  {
    "type": "product",
    "title": "Mango Nectar 250ml",
    "url": "https://eshop.kddc.com/en/Juices/Mango-Nectar-250ml-7620",
    "category": "ice cream",
    "text": "Mango Nectar 250ml | ice cream | 3.6 KWD | None | mango | 250 ml | | | Carton - 24 Pieces | 24 pieces | KWD 3.6 || Pack of Six | 6 pieces | KWD 0.9 | Great tasting and refreshing mango nectar. An all time favorite that's enjoyed by whole family. No preservatives. Nutrition Facts Per 100 ml. Nutrition Value Energy (Calories) 60 Calories from Fat (g) 0 Total Fat (g) 0 Saturated Fat (g) 0 Unsaturated Fat (g) 0 Trans Fat (g) 0 Cholesterol (g) 0 Sodium (mg) 0 Total Carbohydrate (g) 15 Dietary Fibres (g) 0 Total Sugars (g) 13 Added Sugar (g) 9 Protein (g) 0 KD 3.600 100 ml",
    "meta": {
      "dedup_key": "https://eshop.kddc.com/en/Juices/Mango-Nectar-250ml-7620",
      "name": "Mango Nectar 250ml",
      "brand": null,
      "category": "juices",
      "flavor": "mango",
      "volume_ml": 250,
      "weight_g": null,
      "pack_units": null,
      "product_url": "https://eshop.kddc.com/en/Juices/Mango-Nectar-250ml-7620",
      "product_code": "FJUQL6MNGO",
      "sku": "FJUQL6MNGO",
      "availability": "in_stock",
      "price_now_kwd": 3.6,
      "options_text": "Carton - 24 Pieces | 24 pieces | KWD 3.6 || Pack of Six | 6 pieces | KWD 0.9",
      "price_notes": "carton_per_piece≈0.150 KWD",
      "reviews_count": 0,
      "rating_stars": null,
      "desc": "Great tasting and refreshing mango nectar. An all time favorite that's enjoyed by whole family. No preservatives. Nutrition Facts Per 100 ml. Nutrition Value Energy (Calories) 60 Calories from Fat (g) 0 Total Fat (g) 0 Saturated Fat (g) 0 Unsaturated Fat (g) 0 Trans Fat (g) 0 Cholesterol (g) 0 Sodium (mg) 0 Total Carbohydrate (g) 15 Dietary Fibres (g) 0 Total Sugars (g) 13 Added Sugar (g) 9 Protein (g) 0  KD 3.600 100 ml"
    }
  },
  {
    "type": "product",
    "title": "Mango Nectar 250ml (Prisma Pack)",
    "url": "https://eshop.kddc.com/en/Juices/Mango-Nectar-250ml-(Prisma-Pack)-8194",
    "category": "ice cream",
    "text": "Mango Nectar 250ml (Prisma Pack) | ice cream | 2.7 KWD | None | mango | 250 ml | | | Carton - 18 Pieces | 18 pieces | KWD 2.7 | Great tasting and refreshing mango nectar. An all time favorite that's enjoyed by whole family. No preservatives. Nutrition Facts Per 100 ml. Nutrition Value Energy (Calories) 60 Calories from Fat (g) 0 Total Fat (g) 0 Saturated Fat (g) 0 Unsaturated Fat (g) 0 Trans Fat (g) 0 Cholesterol (g) 0 Sodium (mg) 0 Total Carbohydrate (g) 15 Dietary Fibres (g) 0 Total Sugars (g) 13 Added Sugar (g) 9 Protein (g) 0 KD 2.700 100 ml",
    "meta": {
      "dedup_key": "https://eshop.kddc.com/en/Juices/Mango-Nectar-250ml-(Prisma-Pack)-8194",
      "name": "Mango Nectar 250ml (Prisma Pack)",
      "brand": null,
      "category": "juices",
      "flavor": "mango",
      "volume_ml": 250,
      "weight_g": null,
      "pack_units": null,
      "product_url": "https://eshop.kddc.com/en/Juices/Mango-Nectar-250ml-(Prisma-Pack)-8194",
      "product_code": "FJUQL6PSMNGO18",
      "sku": "FJUQL6PSMNGO18",
      "availability": "in_stock",
      "price_now_kwd": 2.7,
      "options_text": "Carton - 18 Pieces | 18 pieces | KWD 2.7",
      "price_notes": "carton_per_piece≈0.150 KWD",
      "reviews_count": 0,
      "rating_stars": null,
      "desc": "Great tasting and refreshing mango nectar. An all time favorite that's enjoyed by whole family. No preservatives. Nutrition Facts Per 100 ml. Nutrition Value Energy (Calories) 60 Calories from Fat (g) 0 Total Fat (g) 0 Saturated Fat (g) 0 Unsaturated Fat (g) 0 Trans Fat (g) 0 Cholesterol (g) 0 Sodium (mg) 0 Total Carbohydrate (g) 15 Dietary Fibres (g) 0 Total Sugars (g) 13 Added Sugar (g) 9 Protein (g) 0  KD 2.700 100 ml"
    }
  },
  {
    "type": "product",
    "title": "Mango Peach Beverage (0% Sugar) 250ml",
    "url": "https://eshop.kddc.com/en/Juices/Mango-Peach-Beverage-(0-per--Sugar)-250ml-9567",
    "category": "ice cream",
    "text": "Mango Peach Beverage (0% Sugar) 250ml | ice cream | 1.98 KWD | None | mango | 250 ml | | | Carton - 18 Pieces | 18 pieces | KWD 1.98 || Pack of Six | 6 pieces | KWD 0.66 | A great tasting, water-based beverage with tropical mango & peach flavor, containing zero sugar and rich in vitamins A, B6, C and D making it a great alternative to sugary drinks. Enjoy it chilled! KD 1.980",
    "meta": {
      "dedup_key": "https://eshop.kddc.com/en/Juices/Mango-Peach-Beverage-(0-per--Sugar)-250ml-9567",
      "name": "Mango Peach Beverage (0% Sugar) 250ml",
      "brand": null,
      "category": "juices",
      "flavor": "mango",
      "volume_ml": 250,
      "weight_g": null,
      "pack_units": null,
      "product_url": "https://eshop.kddc.com/en/Juices/Mango-Peach-Beverage-(0-per--Sugar)-250ml-9567",
      "product_code": "FJUBVGQPS6MNPGM",
      "sku": "FJUBVGQPS6MNPGM",
      "availability": "in_stock",
      "price_now_kwd": 1.98,
      "options_text": "Carton - 18 Pieces | 18 pieces | KWD 1.98 || Pack of Six | 6 pieces | KWD 0.66",
      "price_notes": "carton_per_piece≈0.110 KWD",
      "reviews_count": 0,
      "rating_stars": null,
      "desc": "A great tasting, water-based beverage with tropical mango & peach flavor, containing zero sugar and rich in vitamins A, B6, C and D making it a great alternative to sugary drinks. Enjoy it chilled!  KD 1.980 "
    }
  },
  {
    "type": "product",
    "title": "Mojito (lemon & mint) Beverage (0% Sugar) 250ml.",
    "url": "https://eshop.kddc.com/en/Juices/Mojito-(lemon--and--mint)-Beverage-(0-per--Sugar)-250ml-9568",
    "category": "ice cream",
    "text": "Mojito (lemon & mint) Beverage (0% Sugar) 250ml. | ice cream | 1.98 KWD | None | None | 250 ml | | | Carton - 18 Pieces | 18 pieces | KWD 1.98 || Pack of Six | 6 pieces | KWD 0.66 | A great tasting, water-based beverage with zesty lemon & mint flavor, containing zero sugar and rich in vitamins A, B6, C and D making it a great alternative to sugary drinks. Enjoy it chilled! KD 1.980",
    "meta": {
      "dedup_key": "https://eshop.kddc.com/en/Juices/Mojito-(lemon--and--mint)-Beverage-(0-per--Sugar)-250ml-9568",
      "name": "Mojito (lemon & mint) Beverage (0% Sugar) 250ml.",
      "brand": null,
      "category": "juices",
      "flavor": null,
      "volume_ml": 250,
      "weight_g": null,
      "pack_units": null,
      "product_url": "https://eshop.kddc.com/en/Juices/Mojito-(lemon--and--mint)-Beverage-(0-per--Sugar)-250ml-9568",
      "product_code": "FJUBVGQPS6MTOGM",
      "sku": "FJUBVGQPS6MTOGM",
      "availability": "in_stock",
      "price_now_kwd": 1.98,
      "options_text": "Carton - 18 Pieces | 18 pieces | KWD 1.98 || Pack of Six | 6 pieces | KWD 0.66",
      "price_notes": "carton_per_piece≈0.110 KWD",
      "reviews_count": 1,
      "rating_stars": 10,
      "desc": "A great tasting, water-based beverage with zesty lemon & mint flavor, containing zero sugar and rich in vitamins A, B6, C and D making it a great alternative to sugary drinks. Enjoy it chilled!  KD 1.980 "
    }
  },
  {
    "type": "product",
    "title": "Orange Juice 1 LTR",
    "url": "https://eshop.kddc.com/en/Juices/Orange-Juice-1-LTR-7583",
    "category": "ice cream",
    "text": "Orange Juice 1 LTR | ice cream | 5.7 KWD | None | orange | 1000 ml | | | Carton - 12 Pieces | 12 pieces | KWD 5.7 || Pack Of Four | 4 pieces | KWD 1.9 | 100% orange juice with no added sugar, colours, flavours or preservatives. A classical favorite at the breakfast table. Nutrition Facts Per 100 ml. Nutrition Value Energy (Calories) 50 Calories from Fat (g) 0 Total Fat (g) 0 Saturated Fat (g) 0 Unsaturated Fat (g) 0 Trans Fat (g) 0 Cholesterol (g) 0 Sodium (mg) 0 Total Carbohydrate (g) 12 Dietary Fibres (g) 0 Total Sugars (g) 12 Added Sugar (g) 0 Protein (g) 0 KD 5.700 100 ml",
    "meta": {
      "dedup_key": "https://eshop.kddc.com/en/Juices/Orange-Juice-1-LTR-7583",
      "name": "Orange Juice 1 LTR",
      "brand": null,
      "category": "juices",
      "flavor": "orange",
      "volume_ml": 1000,
      "weight_g": null,
      "pack_units": null,
      "product_url": "https://eshop.kddc.com/en/Juices/Orange-Juice-1-LTR-7583",
      "product_code": "FJU1L4ORNGTG",
      "sku": "FJU1L4ORNGTG",
      "availability": "in_stock",
      "price_now_kwd": 5.7,
      "options_text": "Carton - 12 Pieces | 12 pieces | KWD 5.7 || Pack Of Four | 4 pieces | KWD 1.9",
      "price_notes": "carton_per_piece≈0.475 KWD",
      "reviews_count": 0,
      "rating_stars": null,
      "desc": "100% orange juice with no added sugar, colours, flavours or preservatives. A classical favorite at the breakfast table. Nutrition Facts Per 100 ml. Nutrition Value Energy (Calories) 50 Calories from Fat (g) 0 Total Fat (g) 0 Saturated Fat (g) 0 Unsaturated Fat (g) 0 Trans Fat (g) 0 Cholesterol (g) 0 Sodium (mg) 0 Total Carbohydrate (g) 12 Dietary Fibres (g) 0 Total Sugars (g) 12 Added Sugar (g) 0 Protein (g) 0  KD 5.700 100 ml"
    }
  },
  {
    "type": "product",
    "title": "Orange Juice 250 ML",
    "url": "https://eshop.kddc.com/en/Juices/Orange-Juice-250-ML-7622",
    "category": "ice cream",
    "text": "Orange Juice 250 ML | ice cream | 3.6 KWD | None | orange | 250 ml | | | Carton - 24 Pieces | 24 pieces | KWD 3.6 | 100% orange juice with no added sugar, colours, flavours or preservatives. A classical favorite at the breakfast table. Nutrition Facts Per 100 ml. Nutrition Value Energy (Calories) 50 Calories from Fat (g) 0 Total Fat (g) 0 Saturated Fat (g) 0 Unsaturated Fat (g) 0 Trans Fat (g) 0 Cholesterol (g) 0 Sodium (mg) 0 Total Carbohydrate (g) 12 Dietary Fibres (g) 0 Total Sugars (g) 12 Added Sugar (g) 0 Protein (g) 0 KD 3.600 100 ml",
    "meta": {
      "dedup_key": "https://eshop.kddc.com/en/Juices/Orange-Juice-250-ML-7622",
      "name": "Orange Juice 250 ML",
      "brand": null,
      "category": "juices",
      "flavor": "orange",
      "volume_ml": 250,
      "weight_g": null,
      "pack_units": null,
      "product_url": "https://eshop.kddc.com/en/Juices/Orange-Juice-250-ML-7622",
      "product_code": "FJUQL6ORNG",
      "sku": "FJUQL6ORNG",
      "availability": "in_stock",
      "price_now_kwd": 3.6,
      "options_text": "Carton - 24 Pieces | 24 pieces | KWD 3.6",
      "price_notes": "carton_per_piece≈0.150 KWD",
      "reviews_count": 0,
      "rating_stars": null,
      "desc": "100% orange juice with no added sugar, colours, flavours or preservatives. A classical favorite at the breakfast table. Nutrition Facts Per 100 ml. Nutrition Value Energy (Calories) 50 Calories from Fat (g) 0 Total Fat (g) 0 Saturated Fat (g) 0 Unsaturated Fat (g) 0 Trans Fat (g) 0 Cholesterol (g) 0 Sodium (mg) 0 Total Carbohydrate (g) 12 Dietary Fibres (g) 0 Total Sugars (g) 12 Added Sugar (g) 0 Protein (g) 0  KD 3.600 100 ml"
    }
  },
  {
    "type": "product",
    "title": "Passion Fruit 250ml (Prisma Pack)",
    "url": "https://eshop.kddc.com/en/Juices/Passion-Fruit-250ml-(Prisma-Pack)-8196",
    "category": "ice cream",
    "text": "Passion Fruit 250ml (Prisma Pack) | ice cream | 2.7 KWD | None | None | 250 ml | | | Carton - 18 Pieces | 18 pieces | KWD 2.7 | Great tasting and refreshing passion fruit nectar. An exciting tropical taste experience that is a must try. No preservatives added. Nutrition Facts Per 100 ml. Nutrition Value Energy (Calories) 50 Calories from Fat (g) 0 Total Fat (g) 0 Saturated Fat (g) 0 Unsaturated Fat (g) 0 Trans Fat (g) 0 Cholesterol (g) 0 Sodium (mg) 0 Total Carbohydrate (g) 13 Dietary Fibres (g) 0 Total Sugars (g) 12 Added Sugar (g) 9 Protein (g) 0 KD 2.700 100 ml",
    "meta": {
      "dedup_key": "https://eshop.kddc.com/en/Juices/Passion-Fruit-250ml-(Prisma-Pack)-8196",
      "name": "Passion Fruit 250ml (Prisma Pack)",
      "brand": null,
      "category": "juices",
      "flavor": null,
      "volume_ml": 250,
      "weight_g": null,
      "pack_units": null,
      "product_url": "https://eshop.kddc.com/en/Juices/Passion-Fruit-250ml-(Prisma-Pack)-8196",
      "product_code": "FJUQL6PSPFRT18",
      "sku": "FJUQL6PSPFRT18",
      "availability": "in_stock",
      "price_now_kwd": 2.7,
      "options_text": "Carton - 18 Pieces | 18 pieces | KWD 2.7",
      "price_notes": "carton_per_piece≈0.150 KWD",
      "reviews_count": 0,
      "rating_stars": null,
      "desc": "Great tasting and refreshing passion fruit nectar. An exciting tropical taste experience that is a must try. No preservatives added. Nutrition Facts Per 100 ml. Nutrition Value Energy (Calories) 50 Calories from Fat (g) 0 Total Fat (g) 0 Saturated Fat (g) 0 Unsaturated Fat (g) 0 Trans Fat (g) 0 Cholesterol (g) 0 Sodium (mg) 0 Total Carbohydrate (g) 13 Dietary Fibres (g) 0 Total Sugars (g) 12 Added Sugar (g) 9 Protein (g) 0  KD 2.700 100 ml"
    }
  },
  {
    "type": "product",
    "title": "Peach Nectar 250ml",
    "url": "https://eshop.kddc.com/en/Juices/Peach-Nectar-250ml-7625",
    "category": "ice cream",
    "text": "Peach Nectar 250ml | ice cream | 3.6 KWD | None | None | 250 ml | | | Carton - 24 Pieces | 24 pieces | KWD 3.6 | Great tasting and refreshing peach nectar. Ideal for a sweet recharge any time of the day. No preservatives added. Nutrition Facts Per 100 ml. Nutrition Value Energy (Calories) 50 Calories from Fat (g) 0 Total Fat (g) 0 Saturated Fat (g) 0 Unsaturated Fat (g) 0 Trans Fat (g) 0 Cholesterol (g) 0 Sodium (mg) 0 Total Carbohydrate (g) 13 Dietary Fibres (g) 0 Total Sugars (g) 11 Added Sugar (g) 9 Protein (g) 0 KD 3.600 100 ml",
    "meta": {
      "dedup_key": "https://eshop.kddc.com/en/Juices/Peach-Nectar-250ml-7625",
      "name": "Peach Nectar 250ml",
      "brand": null,
      "category": "juices",
      "flavor": null,
      "volume_ml": 250,
      "weight_g": null,
      "pack_units": null,
      "product_url": "https://eshop.kddc.com/en/Juices/Peach-Nectar-250ml-7625",
      "product_code": "FJUQL6PEACH24",
      "sku": "FJUQL6PEACH24",
      "availability": "in_stock",
      "price_now_kwd": 3.6,
      "options_text": "Carton - 24 Pieces | 24 pieces | KWD 3.6",
      "price_notes": "carton_per_piece≈0.150 KWD",
      "reviews_count": 0,
      "rating_stars": null,
      "desc": "Great tasting and refreshing peach nectar. Ideal for a sweet recharge any time of the day. No preservatives added. Nutrition Facts Per 100 ml. Nutrition Value Energy (Calories) 50 Calories from Fat (g) 0 Total Fat (g) 0 Saturated Fat (g) 0 Unsaturated Fat (g) 0 Trans Fat (g) 0 Cholesterol (g) 0 Sodium (mg) 0 Total Carbohydrate (g) 13 Dietary Fibres (g) 0 Total Sugars (g) 11 Added Sugar (g) 9 Protein (g) 0  KD 3.600 100 ml"
    }
  },
  {
    "type": "product",
    "title": "Pineapple Juice 1 LTR",
    "url": "https://eshop.kddc.com/en/Juices/Pineapple-Juice-1-LTR-7587",
    "category": "ice cream",
    "text": "Pineapple Juice 1 LTR | ice cream | 6.0 KWD | None | apple | 1000 ml | | | Carton - 12 Pieces | 12 pieces | KWD 6.0 || Pack Of Four | 4 pieces | KWD 2.0 | 100% pineapple juice with no added sugar, colours, flavours or preservatives. Delicious tropical refresher for any time of the day. Nutrition Facts Per 100 ml. Nutrition Value Energy (Calories) 50 Calories from Fat (g) 0 Total Fat (g) 0 Saturated Fat (g) 0 Unsaturated Fat (g) 0 Trans Fat (g) 0 Cholesterol (g) 0 Sodium (mg) 0 Total Carbohydrate (g) 13 Dietary Fibres (g) 0 Total Sugars (g) 13 Added Sugar (g) 0 Protein (g) 0 KD 6.000 100 ml",
    "meta": {
      "dedup_key": "https://eshop.kddc.com/en/Juices/Pineapple-Juice-1-LTR-7587",
      "name": "Pineapple Juice 1 LTR",
      "brand": null,
      "category": "juices",
      "flavor": "apple",
      "volume_ml": 1000,
      "weight_g": null,
      "pack_units": null,
      "product_url": "https://eshop.kddc.com/en/Juices/Pineapple-Juice-1-LTR-7587",
      "product_code": "FJU1L4PAPPTG",
      "sku": "FJU1L4PAPPTG",
      "availability": "in_stock",
      "price_now_kwd": 6.0,
      "options_text": "Carton - 12 Pieces | 12 pieces | KWD 6.0 || Pack Of Four | 4 pieces | KWD 2.0",
      "price_notes": "carton_per_piece≈0.500 KWD",
      "reviews_count": 0,
      "rating_stars": null,
      "desc": "100% pineapple juice with no added sugar, colours, flavours or preservatives. Delicious tropical refresher for any time of the day. Nutrition Facts Per 100 ml. Nutrition Value Energy (Calories) 50 Calories from Fat (g) 0 Total Fat (g) 0 Saturated Fat (g) 0 Unsaturated Fat (g) 0 Trans Fat (g) 0 Cholesterol (g) 0 Sodium (mg) 0 Total Carbohydrate (g) 13 Dietary Fibres (g) 0 Total Sugars (g) 13 Added Sugar (g) 0 Protein (g) 0  KD 6.000 100 ml"
    }
  },
  {
    "type": "product",
    "title": "Pineapple Juice 250ml",
    "url": "https://eshop.kddc.com/en/Juices/Pineapple-Juice-250ml-7624",
    "category": "ice cream",
    "text": "Pineapple Juice 250ml | ice cream | 3.6 KWD | None | apple | 250 ml | | | Carton - 24 Pieces | 24 pieces | KWD 3.6 | 100% pineapple juice with no added sugar, colours, flavours or preservatives. Delicious tropical refresher for any time of the day. Nutrition Facts Per 100 ml. Nutrition Value Energy (Calories) 50 Calories from Fat (g) 0 Total Fat (g) 0 Saturated Fat (g) 0 Unsaturated Fat (g) 0 Trans Fat (g) 0 Cholesterol (g) 0 Sodium (mg) 0 Total Carbohydrate (g) 13 Dietary Fibres (g) 0 Total Sugars (g) 13 Added Sugar (g) 0 Protein (g) 0 KD 3.600 100 ml",
    "meta": {
      "dedup_key": "https://eshop.kddc.com/en/Juices/Pineapple-Juice-250ml-7624",
      "name": "Pineapple Juice 250ml",
      "brand": null,
      "category": "juices",
      "flavor": "apple",
      "volume_ml": 250,
      "weight_g": null,
      "pack_units": null,
      "product_url": "https://eshop.kddc.com/en/Juices/Pineapple-Juice-250ml-7624",
      "product_code": "FJUQL6PAPP",
      "sku": "FJUQL6PAPP",
      "availability": "in_stock",
      "price_now_kwd": 3.6,
      "options_text": "Carton - 24 Pieces | 24 pieces | KWD 3.6",
      "price_notes": "carton_per_piece≈0.150 KWD",
      "reviews_count": 0,
      "rating_stars": null,
      "desc": "100% pineapple juice with no added sugar, colours, flavours or preservatives. Delicious tropical refresher for any time of the day. Nutrition Facts Per 100 ml. Nutrition Value Energy (Calories) 50 Calories from Fat (g) 0 Total Fat (g) 0 Saturated Fat (g) 0 Unsaturated Fat (g) 0 Trans Fat (g) 0 Cholesterol (g) 0 Sodium (mg) 0 Total Carbohydrate (g) 13 Dietary Fibres (g) 0 Total Sugars (g) 13 Added Sugar (g) 0 Protein (g) 0  KD 3.600 100 ml"
    }
  },
  {
    "type": "product",
    "title": "Pineapple Juice 250ml (Prisma Pack)",
    "url": "https://eshop.kddc.com/en/Juices/Pineapple-Juice-250ml-(Prisma-Pack)-8195",
    "category": "ice cream",
    "text": "Pineapple Juice 250ml (Prisma Pack) | ice cream | 2.7 KWD | None | apple | 250 ml | | | Carton - 18 Pieces | 18 pieces | KWD 2.7 | 100% pineapple juice with no added sugar, colours, flavours or preservatives. Delicious tropical refresher for any time of the day. Nutrition Facts Per 100 ml. Nutrition Value Energy (Calories) 50 Calories from Fat (g) 0 Total Fat (g) 0 Saturated Fat (g) 0 Unsaturated Fat (g) 0 Trans Fat (g) 0 Cholesterol (g) 0 Sodium (mg) 0 Total Carbohydrate (g) 13 Dietary Fibres (g) 0 Total Sugars (g) 13 Added Sugar (g) 0 Protein (g) 0 KD 2.700 100 ml",
    "meta": {
      "dedup_key": "https://eshop.kddc.com/en/Juices/Pineapple-Juice-250ml-(Prisma-Pack)-8195",
      "name": "Pineapple Juice 250ml (Prisma Pack)",
      "brand": null,
      "category": "juices",
      "flavor": "apple",
      "volume_ml": 250,
      "weight_g": null,
      "pack_units": null,
      "product_url": "https://eshop.kddc.com/en/Juices/Pineapple-Juice-250ml-(Prisma-Pack)-8195",
      "product_code": "FJUQL6PSPAPP18",
      "sku": "FJUQL6PSPAPP18",
      "availability": "out_of_stock",
      "price_now_kwd": 2.7,
      "options_text": "Carton - 18 Pieces | 18 pieces | KWD 2.7",
      "price_notes": "carton_per_piece≈0.150 KWD",
      "reviews_count": 0,
      "rating_stars": null,
      "desc": "100% pineapple juice with no added sugar, colours, flavours or preservatives. Delicious tropical refresher for any time of the day. Nutrition Facts Per 100 ml. Nutrition Value Energy (Calories) 50 Calories from Fat (g) 0 Total Fat (g) 0 Saturated Fat (g) 0 Unsaturated Fat (g) 0 Trans Fat (g) 0 Cholesterol (g) 0 Sodium (mg) 0 Total Carbohydrate (g) 13 Dietary Fibres (g) 0 Total Sugars (g) 13 Added Sugar (g) 0 Protein (g) 0  KD 2.700 100 ml"
    }
  },
  {
    "type": "product",
    "title": "Pink Grapefruit Juice 250ml",
    "url": "https://eshop.kddc.com/en/Juices/Pink-Grapefruit-Juice-250ml-7614",
    "category": "ice cream",
    "text": "Pink Grapefruit Juice 250ml | ice cream | 3.6 KWD | None | None | 250 ml | | | Carton - 24 Pieces | 24 pieces | KWD 3.6 | 100% pink grapefruit juice with no added sugar, colours, flavours or preservatives. Perfect for the weight watchers looking for a healthy option. Nutrition Facts Per 100 ml. Nutrition Value Energy (Calories) 45 Calories from Fat (g) 0 Total Fat (g) 0 Saturated Fat (g) 0 Unsaturated Fat (g) 0 Trans Fat (g) 0 Cholesterol (g) 0 Sodium (mg) 0 Total Carbohydrate (g) 11 Dietary Fibres (g) 0 Total Sugars (g) 11 Added Sugar (g) 0 Protein (g) 0 KD 3.600 100 ml",
    "meta": {
      "dedup_key": "https://eshop.kddc.com/en/Juices/Pink-Grapefruit-Juice-250ml-7614",
      "name": "Pink Grapefruit Juice 250ml",
      "brand": null,
      "category": "juices",
      "flavor": null,
      "volume_ml": 250,
      "weight_g": null,
      "pack_units": null,
      "product_url": "https://eshop.kddc.com/en/Juices/Pink-Grapefruit-Juice-250ml-7614",
      "product_code": "FJUQL6GRFTP",
      "sku": "FJUQL6GRFTP",
      "availability": "in_stock",
      "price_now_kwd": 3.6,
      "options_text": "Carton - 24 Pieces | 24 pieces | KWD 3.6",
      "price_notes": "carton_per_piece≈0.150 KWD",
      "reviews_count": 0,
      "rating_stars": null,
      "desc": "100% pink grapefruit juice with no added sugar, colours, flavours or preservatives. Perfect for the weight watchers looking for a healthy option. Nutrition Facts Per 100 ml. Nutrition Value Energy (Calories) 45 Calories from Fat (g) 0 Total Fat (g) 0 Saturated Fat (g) 0 Unsaturated Fat (g) 0 Trans Fat (g) 0 Cholesterol (g) 0 Sodium (mg) 0 Total Carbohydrate (g) 11 Dietary Fibres (g) 0 Total Sugars (g) 11 Added Sugar (g) 0 Protein (g) 0  KD 3.600 100 ml"
    }
  },
  {
    "type": "product",
    "title": "Red Orange Juice 250ml (Prisma Pack)",
    "url": "https://eshop.kddc.com/en/Juices/Red-Orange-Juice-250ml-(Prisma-Pack)-8197",
    "category": "ice cream",
    "text": "Red Orange Juice 250ml (Prisma Pack) | ice cream | 2.7 KWD | None | orange | 250 ml | | | Carton - 18 Pieces | 18 pieces | KWD 2.7 | 100% red orange juice with no added sugar, colours, flavours or preservatives. Delicious juice that perfectly complements a healthy breakfast. Nutrition Facts Per 100 ml. Nutrition Value Energy (Calories) 45 Calories from Fat (g) 0 Total Fat (g) 0 Saturated Fat (g) 0 Unsaturated Fat (g) 0 Trans Fat (g) 0 Cholesterol (g) 0 Sodium (mg) 0 Total Carbohydrate (g) 11 Dietary Fibres (g) 0 Total Sugars (g) 11 Added Sugar (g) 0 Protein (g) 0 KD 2.700 100 ml",
    "meta": {
      "dedup_key": "https://eshop.kddc.com/en/Juices/Red-Orange-Juice-250ml-(Prisma-Pack)-8197",
      "name": "Red Orange Juice 250ml (Prisma Pack)",
      "brand": null,
      "category": "juices",
      "flavor": "orange",
      "volume_ml": 250,
      "weight_g": null,
      "pack_units": null,
      "product_url": "https://eshop.kddc.com/en/Juices/Red-Orange-Juice-250ml-(Prisma-Pack)-8197",
      "product_code": "FJUQL6PSRORG18",
      "sku": "FJUQL6PSRORG18",
      "availability": "in_stock",
      "price_now_kwd": 2.7,
      "options_text": "Carton - 18 Pieces | 18 pieces | KWD 2.7",
      "price_notes": "carton_per_piece≈0.150 KWD",
      "reviews_count": 0,
      "rating_stars": null,
      "desc": "100% red orange juice with no added sugar, colours, flavours or preservatives. Delicious juice that perfectly complements a healthy breakfast. Nutrition Facts Per 100 ml. Nutrition Value Energy (Calories) 45 Calories from Fat (g) 0 Total Fat (g) 0 Saturated Fat (g) 0 Unsaturated Fat (g) 0 Trans Fat (g) 0 Cholesterol (g) 0 Sodium (mg) 0 Total Carbohydrate (g) 11 Dietary Fibres (g) 0 Total Sugars (g) 11 Added Sugar (g) 0 Protein (g) 0  KD 2.700 100 ml"
    }
  },
  {
    "type": "product",
    "title": "Tomato Juice 1 LTR",
    "url": "https://eshop.kddc.com/en/Juices/Tomato-Juice-1-LTR-7590",
    "category": "ice cream",
    "text": "Tomato Juice 1 LTR | ice cream | 5.4 KWD | None | None | 1000 ml | | | Carton - 12 Pieces | 12 pieces | KWD 5.4 || Pack Of Four | 4 pieces | KWD 1.8 | Great tasting 100% tomato juice with no added sugar, colours, flavours or preservatives. Nutrition Facts Per 100 ml. Nutrition Value Energy (Calories) 25 Calories from Fat (g) 0 Total Fat (g) 0 Saturated Fat (g) 0 Unsaturated Fat (g) 0 Trans Fat (g) 0 Cholesterol (g) 0 Sodium (mg) 0.029 Total Carbohydrate (g) 5 Dietary Fibres (g) 0 Total Sugars (g) 3 Added Sugar (g) 0 Protein (g) 1 KD 5.400 100 ml",
    "meta": {
      "dedup_key": "https://eshop.kddc.com/en/Juices/Tomato-Juice-1-LTR-7590",
      "name": "Tomato Juice 1 LTR",
      "brand": null,
      "category": "juices",
      "flavor": null,
      "volume_ml": 1000,
      "weight_g": null,
      "pack_units": null,
      "product_url": "https://eshop.kddc.com/en/Juices/Tomato-Juice-1-LTR-7590",
      "product_code": "FJU1L4TJUCTG",
      "sku": "FJU1L4TJUCTG",
      "availability": "in_stock",
      "price_now_kwd": 5.4,
      "options_text": "Carton - 12 Pieces | 12 pieces | KWD 5.4 || Pack Of Four | 4 pieces | KWD 1.8",
      "price_notes": "carton_per_piece≈0.450 KWD",
      "reviews_count": 0,
      "rating_stars": null,
      "desc": "Great tasting 100% tomato juice with no added sugar, colours, flavours or preservatives. Nutrition Facts Per 100 ml. Nutrition Value Energy (Calories) 25 Calories from Fat (g) 0 Total Fat (g) 0 Saturated Fat (g) 0 Unsaturated Fat (g) 0 Trans Fat (g) 0 Cholesterol (g) 0 Sodium (mg) 0.029 Total Carbohydrate (g) 5 Dietary Fibres (g) 0 Total Sugars (g) 3 Added Sugar (g) 0 Protein (g) 1  KD 5.400 100 ml"
    }
  },
  {
    "type": "product",
    "title": "Tomato Juice 250ml",
    "url": "https://eshop.kddc.com/en/Juices/Tomato-Juice-250ml-7631",
    "category": "ice cream",
    "text": "Tomato Juice 250ml | ice cream | 3.6 KWD | None | None | 250 ml | | | Carton - 24 Pieces | 24 pieces | KWD 3.6 | Great tasting 100% tomato juice with no added sugar, colours, flavours or preservatives. Nutrition Facts Per 100 ml. Nutrition Value Energy (Calories) 25 Calories from Fat (g) 0 Total Fat (g) 0 Saturated Fat (g) 0 Unsaturated Fat (g) 0 Trans Fat (g) 0 Cholesterol (g) 0 Sodium (mg) 0.029 Total Carbohydrate (g) 5 Dietary Fibres (g) 0 Total Sugars (g) 3 Added Sugar (g) 0 Protein (g) 1 KD 3.600 100 ml",
    "meta": {
      "dedup_key": "https://eshop.kddc.com/en/Juices/Tomato-Juice-250ml-7631",
      "name": "Tomato Juice 250ml",
      "brand": null,
      "category": "juices",
      "flavor": null,
      "volume_ml": 250,
      "weight_g": null,
      "pack_units": null,
      "product_url": "https://eshop.kddc.com/en/Juices/Tomato-Juice-250ml-7631",
      "product_code": "FJUQL6TJUC",
      "sku": "FJUQL6TJUC",
      "availability": "in_stock",
      "price_now_kwd": 3.6,
      "options_text": "Carton - 24 Pieces | 24 pieces | KWD 3.6",
      "price_notes": "carton_per_piece≈0.150 KWD",
      "reviews_count": 0,
      "rating_stars": null,
      "desc": "Great tasting 100% tomato juice with no added sugar, colours, flavours or preservatives. Nutrition Facts Per 100 ml. Nutrition Value Energy (Calories) 25 Calories from Fat (g) 0 Total Fat (g) 0 Saturated Fat (g) 0 Unsaturated Fat (g) 0 Trans Fat (g) 0 Cholesterol (g) 0 Sodium (mg) 0.029 Total Carbohydrate (g) 5 Dietary Fibres (g) 0 Total Sugars (g) 3 Added Sugar (g) 0 Protein (g) 1  KD 3.600 100 ml"
    }
  },
  {
    "type": "career",
    "title": "Assistant Manager - Safety",
    "url": null,
    "department": "Safety",
    "location": "Sabhan",
    "text": "Title: Assistant Manager - Safety | Department: Safety | Location: Sabhan | Experience: 5-7 years | Skills: Occupational Safety Standards; Risk Assessment Techniques; Emergency Response Planning; Environmental Regulations Knowledge; Safety Training and Development; Project Management Skills; Data Analysis for Safety Metrics | Duties: Assist in developing, implementing, and maintaining KDD's Health, Safety, and Environment (HSE) policies and procedures. Monitor and ensure compliance with local labor laws, OSHA standards, and internal safety protocols. Conduct risk assessments, safety audits, and incident investigations to prevent accidents and injuries. Support training programs to educate employees on safety practices, emergency procedures, and safe equipment handling. Track and report safety performance metrics, suggesting improvements and corrective actions as needed. Collaborate with operations, production, and facilities teams to implement preventive measures and maintain safe work environments. Participate in emergency response planning and drills, ensuring readiness across all sites. Support management in promoting a safety-first culture throughout the organization. Bachelor's degree in occupational safety, Environmental Engineering, Industrial Engineering, or a related field. Relevant certifications (e.g., NEBOSH, IOSH, OSHA) are highly desirable. Minimum of 5-7 years of experience in industrial safety, HSE management, or operational safety within the FMCG, manufacturing, or food processing industry. Strong knowledge of safety regulations, standards, and compliance requirements. Experience in conducting risk assessments, audits, and incident investigations. Ability to develop and deliver safety training programs. Analytical and problem-solving skills with attention to detail. Effective communication and interpersonal skills to influence employees and management. | Requirements: Bachelor's degree in occupational safety, Environmental Engineering, Industrial Engineering, or a related field. Minimum of 5-7 years of experience in industrial safety, HSE management, or operational safety within the FMCG, manufacturing, or food processing industry. Experience in conducting risk assessments, audits, and incident investigations. | Skills: Occupational Safety Standards; Risk Assessment Techniques; Emergency Response Planning; Environmental Regulations Knowledge; Safety Training and Development; Project Management Skills; Data Analysis for Safety Metrics | Assist in developing, implementing, and maintaining KDD's Health, Safety, and Environment (HSE) policies and procedures. Monitor and ensure compliance with local labor laws, OSHA standards, and internal safety protocols. Conduct risk assessments, safety audits, and incident investigations to prevent accidents and injuries. Support training programs to educate employees on safety practices, emergency procedures, and safe equipment handling. Track and report safety performance metrics, suggesting improvements and corrective actions as needed. Collaborate with operations, production, and facilities teams to implement preventive measures and maintain safe work environments. Participate in emergency response planning and drills, ensuring readiness across all sites. Support management in promoting a safety-first culture throughout the organization. Bachelor's degree in occupational safety, Environmental Engineering, Industrial Engineering, or a related field. Relevant certifications (e.g., NEBOSH, IOSH, OSHA) are highly desirable. Minimum of 5-7 years of experience in industrial safety, HSE management, or operational safety within the FMCG, manufacturing, or food processing industry. Strong knowledge of safety regulations, standards, and compliance requirements. Experience in conducting risk assessments, audits, and incident investigations. Ability to develop and deliver safety training programs. Analytical and problem-solving skills with attention to detail. Effective communication and interpersonal skills to influence employees and management. Bachelor's degree in occupational safety, Environmental Engineering, Industrial Engineering, or a related field. Minimum of 5-7 years of experience in industrial safety, HSE management, or operational safety within the FMCG, manufacturing, or food processing industry. Experience in conducting risk assessments, audits, and incident investigations.",
    "meta": {
      "dedup_key": "f26ac0352390b618",
      "id_src": "77301",
      "title": "Assistant Manager - Safety",
      "url": null,
      "location": "Sabhan",
      "department_code": "730",
      "department_name": "Safety",
      "job_type": null,
      "min_years": 5,
      "max_years": 7,
      "skills_required": [
        "Occupational Safety Standards",
        "Risk Assessment Techniques",
        "Emergency Response Planning",
        "Environmental Regulations Knowledge",
        "Safety Training and Development",
        "Project Management Skills",
        "Data Analysis for Safety Metrics"
      ],
      "duties": [
        "Assist in developing, implementing, and maintaining KDD's Health, Safety, and Environment (HSE) policies and procedures.",
        "Monitor and ensure compliance with local labor laws, OSHA standards, and internal safety protocols.",
        "Conduct risk assessments, safety audits, and incident investigations to prevent accidents and injuries.",
        "Support training programs to educate employees on safety practices, emergency procedures, and safe equipment handling.",
        "Track and report safety performance metrics, suggesting improvements and corrective actions as needed.",
        "Collaborate with operations, production, and facilities teams to implement preventive measures and maintain safe work environments.",
        "Participate in emergency response planning and drills, ensuring readiness across all sites.",
        "Support management in promoting a safety-first culture throughout the organization.",
        "Bachelor's degree in occupational safety, Environmental Engineering, Industrial Engineering, or a related field.",
        "Relevant certifications (e.g., NEBOSH, IOSH, OSHA) are highly desirable.",
        "Minimum of 5-7 years of experience in industrial safety, HSE management, or operational safety within the FMCG, manufacturing, or food processing industry.",
        "Strong knowledge of safety regulations, standards, and compliance requirements.",
        "Experience in conducting risk assessments, audits, and incident investigations.",
        "Ability to develop and deliver safety training programs.",
        "Analytical and problem-solving skills with attention to detail.",
        "Effective communication and interpersonal skills to influence employees and management."
      ],
      "requirements": [
        "Bachelor's degree in occupational safety, Environmental Engineering, Industrial Engineering, or a related field.",
        "Minimum of 5-7 years of experience in industrial safety, HSE management, or operational safety within the FMCG, manufacturing, or food processing industry.",
        "Experience in conducting risk assessments, audits, and incident investigations."
      ],
      "embedding_text": "Title: Assistant Manager - Safety | Department: Safety | Location: Sabhan | Experience: 5-7 years | Skills: Occupational Safety Standards; Risk Assessment Techniques; Emergency Response Planning; Environmental Regulations Knowledge; Safety Training and Development; Project Management Skills; Data Analysis for Safety Metrics | Duties: Assist in developing, implementing, and maintaining KDD's Health, Safety, and Environment (HSE) policies and procedures. Monitor and ensure compliance with local labor laws, OSHA standards, and internal safety protocols. Conduct risk assessments, safety audits, and incident investigations to prevent accidents and injuries. Support training programs to educate employees on safety practices, emergency procedures, and safe equipment handling. Track and report safety performance metrics, suggesting improvements and corrective actions as needed. Collaborate with operations, production, and facilities teams to implement preventive measures and maintain safe work environments. Participate in emergency response planning and drills, ensuring readiness across all sites. Support management in promoting a safety-first culture throughout the organization. Bachelor's degree in occupational safety, Environmental Engineering, Industrial Engineering, or a related field. Relevant certifications (e.g., NEBOSH, IOSH, OSHA) are highly desirable. Minimum of 5-7 years of experience in industrial safety, HSE management, or operational safety within the FMCG, manufacturing, or food processing industry. Strong knowledge of safety regulations, standards, and compliance requirements. Experience in conducting risk assessments, audits, and incident investigations. Ability to develop and deliver safety training programs. Analytical and problem-solving skills with attention to detail. Effective communication and interpersonal skills to influence employees and management. | Requirements: Bachelor's degree in occupational safety, Environmental Engineering, Industrial Engineering, or a related field. Minimum of 5-7 years of experience in industrial safety, HSE management, or operational safety within the FMCG, manufacturing, or food processing industry. Experience in conducting risk assessments, audits, and incident investigations."
    }
  },
  {
    "type": "career",
    "title": "Senior Engineer - Mechanical",
    "url": null,
    "department": "Projects",
    "location": "Sabhan",
    "text": "Title: Senior Engineer - Mechanical | Department: Projects | Location: Sabhan | Skills: SolidWorks; Thermal Analysis; Root Cause Analysis; Project Management; Finite Element Analysis FEA; Manufacturing Processes Knowledge; Leadership Skills; CAD Software Proficiency | Duties: Efficiently manage, develop, and maintain overall KDD Mechanical systems in line with company and international standards. Oversee project execution, cycle, and operations to ensure timely completion within KDD standards and requirements. Coordinate with contractors and ensure that all project work runs on schedule and meets quality expectations. Control all aspects of the project including planning, materials delivery, and on-site supervision. Determine project specifications by studying user requirements, performance standards, and technical deliverables. Ensure that installation work is completed on time and to KDD standards, resolving any site or material delays. Participate in project meetings with stakeholders including surveyors, subcontractors, site foremen, and clients. Maintain quality control procedures, including regular testing and visual inspections of materials and work. Lead safety inspections to ensure compliance with KDD's health and safety regulations. Assist the Project Manager in planning, defining tasks, managing budgets, and preparing project documentation. Prepare and interpret blueprints, drawings, and technical specifications in coordination with AutoCAD Draftsmen. Conduct mechanical and electrical site inspections involving devices, components, control systems, and automated machinery. Determine project schedules, calculate time requirements, and maintain full-scale project plans and timelines. Create and review project documents related to scope, cost, time, specifications, procurement, BOQ, and tenders. Request and evaluate supplier quotations, conduct comparisons, and provide purchase recommendations. Coordinate with project teams and other departments to ensure smooth project execution. Comply with all Health, Safety, and Environmental regulations and company standards. Execute additional management directives as required. | Requirements: Proficient in LV, HV, FA, Control Systems & Automation; Project Design, Execution, and Validation Proficient in MS Office programs Skilled in AutoCAD Strong command of Project Management Tools and Methodologies Effective in managing teams and workforce coordination | Skills: SolidWorks; Thermal Analysis; Root Cause Analysis; Project Management; Finite Element Analysis FEA; Manufacturing Processes Knowledge; Leadership Skills; CAD Software Proficiency | Efficiently manage, develop, and maintain overall KDD Mechanical systems in line with company and international standards. Oversee project execution, cycle, and operations to ensure timely completion within KDD standards and requirements. Coordinate with contractors and ensure that all project work runs on schedule and meets quality expectations. Control all aspects of the project including planning, materials delivery, and on-site supervision. Determine project specifications by studying user requirements, performance standards, and technical deliverables. Ensure that installation work is completed on time and to KDD standards, resolving any site or material delays. Participate in project meetings with stakeholders including surveyors, subcontractors, site foremen, and clients. Maintain quality control procedures, including regular testing and visual inspections of materials and work. Lead safety inspections to ensure compliance with KDD's health and safety regulations. Assist the Project Manager in planning, defining tasks, managing budgets, and preparing project documentation. Prepare and interpret blueprints, drawings, and technical specifications in coordination with AutoCAD Draftsmen. Conduct mechanical and electrical site inspections involving devices, components, control systems, and automated machinery. Determine project schedules, calculate time requirements, and maintain full-scale project plans and timelines. Create and review project documents related to scope, cost, time, specifications, procurement, BOQ, and tenders. Request and evaluate supplier quotations, conduct comparisons, and provide purchase recommendations. Coordinate with project teams and other departments to ensure smooth project execution. Comply with all Health, Safety, and Environmental regulations and company standards. Execute additional management directives as required. Proficient in LV, HV, FA, Control Systems & Automation; Project Design, Execution, and Validation Proficient in MS Office programs Skilled in AutoCAD Strong command of Project Management Tools and Methodologies Effective in managing teams and workforce coordination",
    "meta": {
      "dedup_key": "4d197a30ab50a1c5",
      "id_src": "77293",
      "title": "Senior Engineer - Mechanical",
      "url": null,
      "location": "Sabhan",
      "department_code": "106",
      "department_name": "Projects",
      "job_type": null,
      "min_years": null,
      "max_years": null,
      "skills_required": [
        "SolidWorks",
        "Thermal Analysis",
        "Root Cause Analysis",
        "Project Management",
        "Finite Element Analysis FEA",
        "Manufacturing Processes Knowledge",
        "Leadership Skills",
        "CAD Software Proficiency"
      ],
      "duties": [
        "Efficiently manage, develop, and maintain overall KDD Mechanical systems in line with company and international standards.",
        "Oversee project execution, cycle, and operations to ensure timely completion within KDD standards and requirements.",
        "Coordinate with contractors and ensure that all project work runs on schedule and meets quality expectations.",
        "Control all aspects of the project including planning, materials delivery, and on-site supervision.",
        "Determine project specifications by studying user requirements, performance standards, and technical deliverables.",
        "Ensure that installation work is completed on time and to KDD standards, resolving any site or material delays.",
        "Participate in project meetings with stakeholders including surveyors, subcontractors, site foremen, and clients.",
        "Maintain quality control procedures, including regular testing and visual inspections of materials and work.",
        "Lead safety inspections to ensure compliance with KDD's health and safety regulations.",
        "Assist the Project Manager in planning, defining tasks, managing budgets, and preparing project documentation.",
        "Prepare and interpret blueprints, drawings, and technical specifications in coordination with AutoCAD Draftsmen.",
        "Conduct mechanical and electrical site inspections involving devices, components, control systems, and automated machinery.",
        "Determine project schedules, calculate time requirements, and maintain full-scale project plans and timelines.",
        "Create and review project documents related to scope, cost, time, specifications, procurement, BOQ, and tenders.",
        "Request and evaluate supplier quotations, conduct comparisons, and provide purchase recommendations.",
        "Coordinate with project teams and other departments to ensure smooth project execution.",
        "Comply with all Health, Safety, and Environmental regulations and company standards.",
        "Execute additional management directives as required."
      ],
      "requirements": [
        "Proficient in LV, HV, FA, Control Systems & Automation; Project Design, Execution, and Validation",
        "Proficient in MS Office programs",
        "Skilled in AutoCAD",
        "Strong command of Project Management Tools and Methodologies",
        "Effective in managing teams and workforce coordination"
      ],
      "embedding_text": "Title: Senior Engineer - Mechanical | Department: Projects | Location: Sabhan | Skills: SolidWorks; Thermal Analysis; Root Cause Analysis; Project Management; Finite Element Analysis FEA; Manufacturing Processes Knowledge; Leadership Skills; CAD Software Proficiency | Duties: Efficiently manage, develop, and maintain overall KDD Mechanical systems in line with company and international standards. Oversee project execution, cycle, and operations to ensure timely completion within KDD standards and requirements. Coordinate with contractors and ensure that all project work runs on schedule and meets quality expectations. Control all aspects of the project including planning, materials delivery, and on-site supervision. Determine project specifications by studying user requirements, performance standards, and technical deliverables. Ensure that installation work is completed on time and to KDD standards, resolving any site or material delays. Participate in project meetings with stakeholders including surveyors, subcontractors, site foremen, and clients. Maintain quality control procedures, including regular testing and visual inspections of materials and work. Lead safety inspections to ensure compliance with KDD's health and safety regulations. Assist the Project Manager in planning, defining tasks, managing budgets, and preparing project documentation. Prepare and interpret blueprints, drawings, and technical specifications in coordination with AutoCAD Draftsmen. Conduct mechanical and electrical site inspections involving devices, components, control systems, and automated machinery. Determine project schedules, calculate time requirements, and maintain full-scale project plans and timelines. Create and review project documents related to scope, cost, time, specifications, procurement, BOQ, and tenders. Request and evaluate supplier quotations, conduct comparisons, and provide purchase recommendations. Coordinate with project teams and other departments to ensure smooth project execution. Comply with all Health, Safety, and Environmental regulations and company standards. Execute additional management directives as required. | Requirements: Proficient in LV, HV, FA, Control Systems & Automation; Project Design, Execution, and Validation Proficient in MS Office programs Skilled in AutoCAD Strong command of Project Management Tools and Methodologies Effective in managing teams and workforce coordination"
    }
  },
  {
    "type": "career",
    "title": "Project Manager - Dairy",
    "url": null,
    "department": "Projects",
    "location": "Sabhan",
    "text": "Title: Project Manager - Dairy | Department: Projects | Location: Sabhan | Experience: 15-20 years | Skills: Project Management; Budgeting and Cost Management; Team Leadership; Risk Management; Communication Skills; Knowledge of Dairy Manufacturing Processes; Stakeholder Management; ProblemSolving Skills | Requirements: 15-20 years of experience in managing industrial or dairy processing projects within the FMCG or food manufacturing industry. Strong technical knowledge of dairy processing systems, utilities, and plant commissioning. Proven experience in project planning, cost control, and stakeholder management. Proficiency in MS Project or equivalent project management tools. Proficiency in AutoCAD Strong analytical, problem-solving, and leadership abilities. Excellent communication and coordination skills to manage cross-functional and multicultural teams. Ability to manage multiple priorities and deliver within strict deadlines. Fluency in English required; Arabic is an advantage. | Skills: Project Management; Budgeting and Cost Management; Team Leadership; Risk Management; Communication Skills; Knowledge of Dairy Manufacturing Processes; Stakeholder Management; ProblemSolving Skills | 15-20 years of experience in managing industrial or dairy processing projects within the FMCG or food manufacturing industry. Strong technical knowledge of dairy processing systems, utilities, and plant commissioning. Proven experience in project planning, cost control, and stakeholder management. Proficiency in MS Project or equivalent project management tools. Proficiency in AutoCAD Strong analytical, problem-solving, and leadership abilities. Excellent communication and coordination skills to manage cross-functional and multicultural teams. Ability to manage multiple priorities and deliver within strict deadlines. Fluency in English required; Arabic is an advantage.",
    "meta": {
      "dedup_key": "56bf27d7871ed61a",
      "id_src": "77255",
      "title": "Project Manager - Dairy",
      "url": null,
      "location": "Sabhan",
      "department_code": "106",
      "department_name": "Projects",
      "job_type": null,
      "min_years": 15,
      "max_years": 20,
      "skills_required": [
        "Project Management",
        "Budgeting and Cost Management",
        "Team Leadership",
        "Risk Management",
        "Communication Skills",
        "Knowledge of Dairy Manufacturing Processes",
        "Stakeholder Management",
        "ProblemSolving Skills"
      ],
      "duties": null,
      "requirements": [
        "15-20 years of experience in managing industrial or dairy processing projects within the FMCG or food manufacturing industry.",
        "Strong technical knowledge of dairy processing systems, utilities, and plant commissioning.",
        "Proven experience in project planning, cost control, and stakeholder management.",
        "Proficiency in MS Project or equivalent project management tools.",
        "Proficiency in AutoCAD",
        "Strong analytical, problem-solving, and leadership abilities.",
        "Excellent communication and coordination skills to manage cross-functional and multicultural teams.",
        "Ability to manage multiple priorities and deliver within strict deadlines.",
        "Fluency in English required; Arabic is an advantage."
      ],
      "embedding_text": "Title: Project Manager - Dairy | Department: Projects | Location: Sabhan | Experience: 15-20 years | Skills: Project Management; Budgeting and Cost Management; Team Leadership; Risk Management; Communication Skills; Knowledge of Dairy Manufacturing Processes; Stakeholder Management; ProblemSolving Skills | Requirements: 15-20 years of experience in managing industrial or dairy processing projects within the FMCG or food manufacturing industry. Strong technical knowledge of dairy processing systems, utilities, and plant commissioning. Proven experience in project planning, cost control, and stakeholder management. Proficiency in MS Project or equivalent project management tools. Proficiency in AutoCAD Strong analytical, problem-solving, and leadership abilities. Excellent communication and coordination skills to manage cross-functional and multicultural teams. Ability to manage multiple priorities and deliver within strict deadlines. Fluency in English required; Arabic is an advantage."
    }
  },
  {
    "type": "career",
    "title": "Senior Engineer - Electrical",
    "url": null,
    "department": "Projects",
    "location": "Sabhan",
    "text": "Title: Senior Engineer - Electrical | Department: Projects | Location: Sabhan | Skills: Circuit Design; Power Systems Analysis; Electronics Troubleshooting; Compliance and Safety Standards; Embedded Systems Programming; Project Management; Renewable Energy Technologies; AutoCAD Electrical | Duties: Work alongside the project manager to support the efficient management and execution of projects within the agreed scope, cost, and time Act as a subject matter expert for the dairy section Facilitate project studies and development by reviewing proposals, plans, and user requirements Coordinate with project stakeholders to define project objectives and scope Determine project schedules and calculate time requirements Request, review, and evaluate supplier proposals and cost estimates Assist the project manager in preparing and managing the project budget Create and review contractual, tender, and technical documents Plan, implement, track, and report on project progress Develop and maintain project schedules, plans, and specifications Control and report on project progress, costs, and performance Prepare BOQ, BOM, and technical specifications for equipment and components Facilitate and manage project meetings, follow-ups, and documentation Review design layouts, P&IDs, and other engineering drawings Liaise with vendors and suppliers for technical proposals and material support Support external projects within the assigned area of specialization Ensure compliance with health, safety, and environmental standards Perform other duties as assigned by line management | Requirements: Proficient in MS Office programs Proficient in MS Project Knowledgeable in AutoCAD Strong analytical, organizational, and project management skills Excellent communication and coordination abilities | Skills: Circuit Design; Power Systems Analysis; Electronics Troubleshooting; Compliance and Safety Standards; Embedded Systems Programming; Project Management; Renewable Energy Technologies; AutoCAD Electrical | Work alongside the project manager to support the efficient management and execution of projects within the agreed scope, cost, and time Act as a subject matter expert for the dairy section Facilitate project studies and development by reviewing proposals, plans, and user requirements Coordinate with project stakeholders to define project objectives and scope Determine project schedules and calculate time requirements Request, review, and evaluate supplier proposals and cost estimates Assist the project manager in preparing and managing the project budget Create and review contractual, tender, and technical documents Plan, implement, track, and report on project progress Develop and maintain project schedules, plans, and specifications Control and report on project progress, costs, and performance Prepare BOQ, BOM, and technical specifications for equipment and components Facilitate and manage project meetings, follow-ups, and documentation Review design layouts, P&IDs, and other engineering drawings Liaise with vendors and suppliers for technical proposals and material support Support external projects within the assigned area of specialization Ensure compliance with health, safety, and environmental standards Perform other duties as assigned by line management Proficient in MS Office programs Proficient in MS Project Knowledgeable in AutoCAD Strong analytical, organizational, and project management skills Excellent communication and coordination abilities",
    "meta": {
      "dedup_key": "c9054d83131f5523",
      "id_src": "77253",
      "title": "Senior Engineer - Electrical",
      "url": null,
      "location": "Sabhan",
      "department_code": "106",
      "department_name": "Projects",
      "job_type": null,
      "min_years": null,
      "max_years": null,
      "skills_required": [
        "Circuit Design",
        "Power Systems Analysis",
        "Electronics Troubleshooting",
        "Compliance and Safety Standards",
        "Embedded Systems Programming",
        "Project Management",
        "Renewable Energy Technologies",
        "AutoCAD Electrical"
      ],
      "duties": [
        "Work alongside the project manager to support the efficient management and execution of projects within the agreed scope, cost, and time",
        "Act as a subject matter expert for the dairy section",
        "Facilitate project studies and development by reviewing proposals, plans, and user requirements",
        "Coordinate with project stakeholders to define project objectives and scope",
        "Determine project schedules and calculate time requirements",
        "Request, review, and evaluate supplier proposals and cost estimates",
        "Assist the project manager in preparing and managing the project budget",
        "Create and review contractual, tender, and technical documents",
        "Plan, implement, track, and report on project progress",
        "Develop and maintain project schedules, plans, and specifications",
        "Control and report on project progress, costs, and performance",
        "Prepare BOQ, BOM, and technical specifications for equipment and components",
        "Facilitate and manage project meetings, follow-ups, and documentation",
        "Review design layouts, P&IDs, and other engineering drawings",
        "Liaise with vendors and suppliers for technical proposals and material support",
        "Support external projects within the assigned area of specialization",
        "Ensure compliance with health, safety, and environmental standards",
        "Perform other duties as assigned by line management"
      ],
      "requirements": [
        "Proficient in MS Office programs",
        "Proficient in MS Project",
        "Knowledgeable in AutoCAD",
        "Strong analytical, organizational, and project management skills",
        "Excellent communication and coordination abilities"
      ],
      "embedding_text": "Title: Senior Engineer - Electrical | Department: Projects | Location: Sabhan | Skills: Circuit Design; Power Systems Analysis; Electronics Troubleshooting; Compliance and Safety Standards; Embedded Systems Programming; Project Management; Renewable Energy Technologies; AutoCAD Electrical | Duties: Work alongside the project manager to support the efficient management and execution of projects within the agreed scope, cost, and time Act as a subject matter expert for the dairy section Facilitate project studies and development by reviewing proposals, plans, and user requirements Coordinate with project stakeholders to define project objectives and scope Determine project schedules and calculate time requirements Request, review, and evaluate supplier proposals and cost estimates Assist the project manager in preparing and managing the project budget Create and review contractual, tender, and technical documents Plan, implement, track, and report on project progress Develop and maintain project schedules, plans, and specifications Control and report on project progress, costs, and performance Prepare BOQ, BOM, and technical specifications for equipment and components Facilitate and manage project meetings, follow-ups, and documentation Review design layouts, P&IDs, and other engineering drawings Liaise with vendors and suppliers for technical proposals and material support Support external projects within the assigned area of specialization Ensure compliance with health, safety, and environmental standards Perform other duties as assigned by line management | Requirements: Proficient in MS Office programs Proficient in MS Project Knowledgeable in AutoCAD Strong analytical, organizational, and project management skills Excellent communication and coordination abilities"
    }
  },
  {
    "type": "career",
    "title": "Senior Engineer - Dairy",
    "url": null,
    "department": "Projects",
    "location": "Sabhan",
    "text": "Title: Senior Engineer - Dairy | Department: Projects | Location: Sabhan | Skills: Mechanical Engineering; Project Management; Process Optimization; Quality Assurance; Team Leadership; Regulatory Compliance; Root Cause Analysis | Duties: Work alongside the project manager to support the efficient management and execution of projects within agreed scope, cost, and time. Act as a subject matter expert for the dairy section. Facilitate project studies and development by reviewing proposals, plans, and user requirements. Coordinate with project stakeholders to define project objectives and develop scope. Determine project schedules and calculate time requirements. Request, review, and evaluate supplier proposals and cost estimates. Assist the project manager in preparing and managing the project budget. Create and review contractual documents, tender documents, submittals, and other related materials. Plan, implement, track, and report project progress. Develop and maintain project schedules, plans, and specifications. Control and report on project progress, costs, and performance metrics. Prepare B.O.Q., B.O.M., and technical specifications for equipment and components. Facilitate and manage meetings, follow-ups, and coordination among project teams. Review design layouts, P&IDs, and other engineering drawings. Liaise with vendors and suppliers for technical proposals and materials. Support external projects within the assigned area of specialization. Ensure compliance with health, safety, and environmental standards. Perform other duties as assigned by the line management. | Requirements: Proficient in MS Office programs Proficient in MS Project Knowledgeable in AutoCAD Strong analytical and project management abilities Excellent coordination and communication skills | Skills: Mechanical Engineering; Project Management; Process Optimization; Quality Assurance; Team Leadership; Regulatory Compliance; Root Cause Analysis | Work alongside the project manager to support the efficient management and execution of projects within agreed scope, cost, and time. Act as a subject matter expert for the dairy section. Facilitate project studies and development by reviewing proposals, plans, and user requirements. Coordinate with project stakeholders to define project objectives and develop scope. Determine project schedules and calculate time requirements. Request, review, and evaluate supplier proposals and cost estimates. Assist the project manager in preparing and managing the project budget. Create and review contractual documents, tender documents, submittals, and other related materials. Plan, implement, track, and report project progress. Develop and maintain project schedules, plans, and specifications. Control and report on project progress, costs, and performance metrics. Prepare B.O.Q., B.O.M., and technical specifications for equipment and components. Facilitate and manage meetings, follow-ups, and coordination among project teams. Review design layouts, P&IDs, and other engineering drawings. Liaise with vendors and suppliers for technical proposals and materials. Support external projects within the assigned area of specialization. Ensure compliance with health, safety, and environmental standards. Perform other duties as assigned by the line management. Proficient in MS Office programs Proficient in MS Project Knowledgeable in AutoCAD Strong analytical and project management abilities Excellent coordination and communication skills",
    "meta": {
      "dedup_key": "db2e067ff0f48ca2",
      "id_src": "77252",
      "title": "Senior Engineer - Dairy",
      "url": null,
      "location": "Sabhan",
      "department_code": "106",
      "department_name": "Projects",
      "job_type": null,
      "min_years": null,
      "max_years": null,
      "skills_required": [
        "Mechanical Engineering",
        "Project Management",
        "Process Optimization",
        "Quality Assurance",
        "Team Leadership",
        "Regulatory Compliance",
        "Root Cause Analysis"
      ],
      "duties": [
        "Work alongside the project manager to support the efficient management and execution of projects within agreed scope, cost, and time.",
        "Act as a subject matter expert for the dairy section.",
        "Facilitate project studies and development by reviewing proposals, plans, and user requirements.",
        "Coordinate with project stakeholders to define project objectives and develop scope.",
        "Determine project schedules and calculate time requirements.",
        "Request, review, and evaluate supplier proposals and cost estimates.",
        "Assist the project manager in preparing and managing the project budget.",
        "Create and review contractual documents, tender documents, submittals, and other related materials.",
        "Plan, implement, track, and report project progress.",
        "Develop and maintain project schedules, plans, and specifications.",
        "Control and report on project progress, costs, and performance metrics.",
        "Prepare B.O.Q., B.O.M., and technical specifications for equipment and components.",
        "Facilitate and manage meetings, follow-ups, and coordination among project teams.",
        "Review design layouts, P&IDs, and other engineering drawings.",
        "Liaise with vendors and suppliers for technical proposals and materials.",
        "Support external projects within the assigned area of specialization.",
        "Ensure compliance with health, safety, and environmental standards.",
        "Perform other duties as assigned by the line management."
      ],
      "requirements": [
        "Proficient in MS Office programs",
        "Proficient in MS Project",
        "Knowledgeable in AutoCAD",
        "Strong analytical and project management abilities",
        "Excellent coordination and communication skills"
      ],
      "embedding_text": "Title: Senior Engineer - Dairy | Department: Projects | Location: Sabhan | Skills: Mechanical Engineering; Project Management; Process Optimization; Quality Assurance; Team Leadership; Regulatory Compliance; Root Cause Analysis | Duties: Work alongside the project manager to support the efficient management and execution of projects within agreed scope, cost, and time. Act as a subject matter expert for the dairy section. Facilitate project studies and development by reviewing proposals, plans, and user requirements. Coordinate with project stakeholders to define project objectives and develop scope. Determine project schedules and calculate time requirements. Request, review, and evaluate supplier proposals and cost estimates. Assist the project manager in preparing and managing the project budget. Create and review contractual documents, tender documents, submittals, and other related materials. Plan, implement, track, and report project progress. Develop and maintain project schedules, plans, and specifications. Control and report on project progress, costs, and performance metrics. Prepare B.O.Q., B.O.M., and technical specifications for equipment and components. Facilitate and manage meetings, follow-ups, and coordination among project teams. Review design layouts, P&IDs, and other engineering drawings. Liaise with vendors and suppliers for technical proposals and materials. Support external projects within the assigned area of specialization. Ensure compliance with health, safety, and environmental standards. Perform other duties as assigned by the line management. | Requirements: Proficient in MS Office programs Proficient in MS Project Knowledgeable in AutoCAD Strong analytical and project management abilities Excellent coordination and communication skills"
    }
  },
  {
    "type": "career",
    "title": "Senior Business Intelligence Engineer",
    "url": null,
    "department": "MIS",
    "location": "Sabhan",
    "text": "Title: Senior Business Intelligence Engineer | Department: MIS | Location: Sabhan | Skills: SQL; Data Visualization; ETL; Data Warehousing; Python; Tableau; Advanced Excel; Power BI; R; Machine Learning | Duties: The Business Intelligence (BI) Engineer is responsible for the end-to-end design, development, and maintenance of BI solutions, including data warehousing, integration layers, and dashboard development using enterprise BI tools. The role requires close collaboration with various departments to translate raw data into structured, meaningful insights for optimized decision-making processes. The position demands a strong technical understanding of data architecture and business intelligence frameworks. Design, implement, and maintain the data warehouse architecture to ensure data integrity scalability and efficiency. Create and maintain data models to support reporting and analytics initiatives. Optimize ETL processes for data extraction, transformation, and loading, ensuring data integrity and accuracy. Ensure data from multiple sources is aggregated, cleansed, and stored accurately in data warehouses. Develop and maintain a variety of reports and dashboards using business intelligence tools (OBIE, Power BI). Implement and enforce data governance policies and procedures to ensure data quality and security. Use current change control standards and SDLC to successfully implement solutions. Collaborate with cross-functional teams to integrate Oracle applications with other enterprise tools and applications. Take ownership and resolve service requests within SLA timelines. Lead the planning and implementation of application and technology updates and upgrades. Ensure data integrity and security across Oracle platforms. Document technical processes and develop user guides for new applications. Develop and manage BI tools, dashboards, and reporting systems using tools such OBIE/OAC, Power BI, or other relevant platforms. Conduct data analysis to identify trends, patterns, and insights that can drive business decisions. Collaborate with business users to gather requirements and translate them into technical specifications. Optimize SQL queries, BI tools, and data pipelines to enhance performance and ensure efficient data retrieval. Document BI systems and processes to ensure transparency and facilitate maintenance and knowledge transfer. | Requirements: Oracle Database: SQL, PL/SQL, Java Application Development: Reports, BI publisher, Application APIs, Oracle Forms Application Technology: Oracle Alerts, Oracle Business Events, Workflow, Web ADI, OAF, APEX is a plus. Integration Technologies: Informatica, Data Warehouse Administration Console (DAC), Oracle Data integrator (ODI) Oracle Integration Cloud (OIC), Integration SOA Gateway, Rest APIs, familiar with XML, XSLT, and JSON data formats. Cloud: Oracle Cloud Infrastructure and cloud migration strategies. Reporting and analytics with Oracle BI, Power BI | Skills: SQL; Data Visualization; ETL; Data Warehousing; Python; Tableau; Advanced Excel; Power BI; R; Machine Learning | The Business Intelligence (BI) Engineer is responsible for the end-to-end design, development, and maintenance of BI solutions, including data warehousing, integration layers, and dashboard development using enterprise BI tools. The role requires close collaboration with various departments to translate raw data into structured, meaningful insights for optimized decision-making processes. The position demands a strong technical understanding of data architecture and business intelligence frameworks. Design, implement, and maintain the data warehouse architecture to ensure data integrity scalability and efficiency. Create and maintain data models to support reporting and analytics initiatives. Optimize ETL processes for data extraction, transformation, and loading, ensuring data integrity and accuracy. Ensure data from multiple sources is aggregated, cleansed, and stored accurately in data warehouses. Develop and maintain a variety of reports and dashboards using business intelligence tools (OBIE, Power BI). Implement and enforce data governance policies and procedures to ensure data quality and security. Use current change control standards and SDLC to successfully implement solutions. Collaborate with cross-functional teams to integrate Oracle applications with other enterprise tools and applications. Take ownership and resolve service requests within SLA timelines. Lead the planning and implementation of application and technology updates and upgrades. Ensure data integrity and security across Oracle platforms. Document technical processes and develop user guides for new applications. Develop and manage BI tools, dashboards, and reporting systems using tools such OBIE/OAC, Power BI, or other relevant platforms. Conduct data analysis to identify trends, patterns, and insights that can drive business decisions. Collaborate with business users to gather requirements and translate them into technical specifications. Optimize SQL queries, BI tools, and data pipelines to enhance performance and ensure efficient data retrieval. Document BI systems and processes to ensure transparency and facilitate maintenance and knowledge transfer. Oracle Database: SQL, PL/SQL, Java Application Development: Reports, BI publisher, Application APIs, Oracle Forms Application Technology: Oracle Alerts, Oracle Business Events, Workflow, Web ADI, OAF, APEX is a plus. Integration Technologies: Informatica, Data Warehouse Administration Console (DAC), Oracle Data integrator (ODI) Oracle Integration Cloud (OIC), Integration SOA Gateway, Rest APIs, familiar with XML, XSLT, and JSON data formats. Cloud: Oracle Cloud Infrastructure and cloud migration strategies. Reporting and analytics with Oracle BI, Power BI",
    "meta": {
      "dedup_key": "eeba76cd273f241b",
      "id_src": "77245",
      "title": "Senior Business Intelligence Engineer",
      "url": null,
      "location": "Sabhan",
      "department_code": "690",
      "department_name": "MIS",
      "job_type": null,
      "min_years": null,
      "max_years": null,
      "skills_required": [
        "SQL",
        "Data Visualization",
        "ETL",
        "Data Warehousing",
        "Python",
        "Tableau",
        "Advanced Excel",
        "Power BI",
        "R",
        "Machine Learning"
      ],
      "duties": [
        "The Business Intelligence (BI) Engineer is responsible for the end-to-end design, development, and maintenance of BI solutions, including data warehousing, integration layers, and dashboard development using enterprise BI tools. The role requires close collaboration with various departments to translate raw data into structured, meaningful insights for optimized decision-making processes. The position demands a strong technical understanding of data architecture and business intelligence frameworks.",
        "Design, implement, and maintain the data warehouse architecture to ensure data integrity scalability and efficiency.",
        "Create and maintain data models to support reporting and analytics initiatives.",
        "Optimize ETL processes for data extraction, transformation, and loading, ensuring data integrity and accuracy. Ensure data from multiple sources is aggregated, cleansed, and stored accurately in data warehouses.",
        "Develop and maintain a variety of reports and dashboards using business intelligence tools (OBIE, Power BI).",
        "Implement and enforce data governance policies and procedures to ensure data quality and security.",
        "Use current change control standards and SDLC to successfully implement solutions.",
        "Collaborate with cross-functional teams to integrate Oracle applications with other enterprise tools and applications.",
        "Take ownership and resolve service requests within SLA timelines.",
        "Lead the planning and implementation of application and technology updates and upgrades.",
        "Ensure data integrity and security across Oracle platforms.",
        "Document technical processes and develop user guides for new applications.",
        "Develop and manage BI tools, dashboards, and reporting systems using tools such OBIE/OAC, Power BI, or other relevant platforms.",
        "Conduct data analysis to identify trends, patterns, and insights that can drive business decisions. Collaborate with business users to gather requirements and translate them into technical specifications.",
        "Optimize SQL queries, BI tools, and data pipelines to enhance performance and ensure efficient data retrieval.",
        "Document BI systems and processes to ensure transparency and facilitate maintenance and knowledge transfer."
      ],
      "requirements": [
        "Oracle Database: SQL, PL/SQL, Java",
        "Application Development: Reports, BI publisher, Application APIs, Oracle Forms",
        "Application Technology: Oracle Alerts, Oracle Business Events, Workflow, Web ADI, OAF, APEX is a plus.",
        "Integration Technologies: Informatica, Data Warehouse Administration Console (DAC), Oracle Data integrator (ODI) Oracle Integration Cloud (OIC), Integration SOA Gateway, Rest APIs, familiar with XML, XSLT, and JSON data formats.",
        "Cloud: Oracle Cloud Infrastructure and cloud migration strategies.",
        "Reporting and analytics with Oracle BI, Power BI"
      ],
      "embedding_text": "Title: Senior Business Intelligence Engineer | Department: MIS | Location: Sabhan | Skills: SQL; Data Visualization; ETL; Data Warehousing; Python; Tableau; Advanced Excel; Power BI; R; Machine Learning | Duties: The Business Intelligence (BI) Engineer is responsible for the end-to-end design, development, and maintenance of BI solutions, including data warehousing, integration layers, and dashboard development using enterprise BI tools. The role requires close collaboration with various departments to translate raw data into structured, meaningful insights for optimized decision-making processes. The position demands a strong technical understanding of data architecture and business intelligence frameworks. Design, implement, and maintain the data warehouse architecture to ensure data integrity scalability and efficiency. Create and maintain data models to support reporting and analytics initiatives. Optimize ETL processes for data extraction, transformation, and loading, ensuring data integrity and accuracy. Ensure data from multiple sources is aggregated, cleansed, and stored accurately in data warehouses. Develop and maintain a variety of reports and dashboards using business intelligence tools (OBIE, Power BI). Implement and enforce data governance policies and procedures to ensure data quality and security. Use current change control standards and SDLC to successfully implement solutions. Collaborate with cross-functional teams to integrate Oracle applications with other enterprise tools and applications. Take ownership and resolve service requests within SLA timelines. Lead the planning and implementation of application and technology updates and upgrades. Ensure data integrity and security across Oracle platforms. Document technical processes and develop user guides for new applications. Develop and manage BI tools, dashboards, and reporting systems using tools such OBIE/OAC, Power BI, or other relevant platforms. Conduct data analysis to identify trends, patterns, and insights that can drive business decisions. Collaborate with business users to gather requirements and translate them into technical specifications. Optimize SQL queries, BI tools, and data pipelines to enhance performance and ensure efficient data retrieval. Document BI systems and processes to ensure transparency and facilitate maintenance and knowledge transfer. | Requirements: Oracle Database: SQL, PL/SQL, Java Application Development: Reports, BI publisher, Application APIs, Oracle Forms Application Technology: Oracle Alerts, Oracle Business Events, Workflow, Web ADI, OAF, APEX is a plus. Integration Technologies: Informatica, Data Warehouse Administration Console (DAC), Oracle Data integrator (ODI) Oracle Integration Cloud (OIC), Integration SOA Gateway, Rest APIs, familiar with XML, XSLT, and JSON data formats. Cloud: Oracle Cloud Infrastructure and cloud migration strategies. Reporting and analytics with Oracle BI, Power BI"
    }
  },
  {
    "type": "career",
    "title": "Installation Manager",
    "url": null,
    "department": "Projects",
    "location": "Sabhan",
    "text": "Title: Installation Manager | Department: Projects | Location: Sabhan | Skills: Leadership; Project Management; Safety Compliance; Communication; Organizational Skills; ProblemSolving; Time Management; Technical Proficiency in Installation Tools; Risk Management | Skills: Leadership; Project Management; Safety Compliance; Communication; Organizational Skills; ProblemSolving; Time Management; Technical Proficiency in Installation Tools; Risk Management |",
    "meta": {
      "dedup_key": "1513c12d1cf9f3c4",
      "id_src": "77244",
      "title": "Installation Manager",
      "url": null,
      "location": "Sabhan",
      "department_code": "106",
      "department_name": "Projects",
      "job_type": null,
      "min_years": null,
      "max_years": null,
      "skills_required": [
        "Leadership",
        "Project Management",
        "Safety Compliance",
        "Communication",
        "Organizational Skills",
        "ProblemSolving",
        "Time Management",
        "Technical Proficiency in Installation Tools",
        "Risk Management"
      ],
      "duties": null,
      "requirements": null,
      "embedding_text": "Title: Installation Manager | Department: Projects | Location: Sabhan | Skills: Leadership; Project Management; Safety Compliance; Communication; Organizational Skills; ProblemSolving; Time Management; Technical Proficiency in Installation Tools; Risk Management"
    }
  },
  {
    "type": "career",
    "title": "Junior Internal Auditor (Internal Audit Associate)",
    "url": null,
    "department": "Internal Audit",
    "location": "Sabhan",
    "text": "Title: Junior Internal Auditor (Internal Audit Associate) | Department: Internal Audit | Location: Sabhan | Skills: Analytical Skills; Attention to Detail; Risk Assessment; Report Writing; Knowledge of Auditing Standards; Communication Skills; Excel Proficiency; ProblemSolving Skills | Duties: The Internal Auditor is responsible for the overall execution of internal audit reviews and assignments consistent with the purpose, authority and responsibilities defined in the charter. | Requirements: Strong report writing and communication skills. Ability to prepare, update, and maintain comprehensive audit working papers. Sound knowledge of internal audit methodologies, including risk assessment, research, and audit planning. Analytical mindset with attention to detail and professional integrity. | Skills: Analytical Skills; Attention to Detail; Risk Assessment; Report Writing; Knowledge of Auditing Standards; Communication Skills; Excel Proficiency; ProblemSolving Skills | The Internal Auditor is responsible for the overall execution of internal audit reviews and assignments consistent with the purpose, authority and responsibilities defined in the charter. Strong report writing and communication skills. Ability to prepare, update, and maintain comprehensive audit working papers. Sound knowledge of internal audit methodologies, including risk assessment, research, and audit planning. Analytical mindset with attention to detail and professional integrity.",
    "meta": {
      "dedup_key": "1061e453e22a1e36",
      "id_src": "76964",
      "title": "Junior Internal Auditor (Internal Audit Associate)",
      "url": null,
      "location": "Sabhan",
      "department_code": "707",
      "department_name": "Internal Audit",
      "job_type": null,
      "min_years": null,
      "max_years": null,
      "skills_required": [
        "Analytical Skills",
        "Attention to Detail",
        "Risk Assessment",
        "Report Writing",
        "Knowledge of Auditing Standards",
        "Communication Skills",
        "Excel Proficiency",
        "ProblemSolving Skills"
      ],
      "duties": [
        "The Internal Auditor is responsible for the overall execution of internal audit reviews and assignments consistent with the purpose, authority and responsibilities defined in the charter."
      ],
      "requirements": [
        "Strong report writing and communication skills.",
        "Ability to prepare, update, and maintain comprehensive audit working papers.",
        "Sound knowledge of internal audit methodologies, including risk assessment, research, and audit planning.",
        "Analytical mindset with attention to detail and professional integrity."
      ],
      "embedding_text": "Title: Junior Internal Auditor (Internal Audit Associate) | Department: Internal Audit | Location: Sabhan | Skills: Analytical Skills; Attention to Detail; Risk Assessment; Report Writing; Knowledge of Auditing Standards; Communication Skills; Excel Proficiency; ProblemSolving Skills | Duties: The Internal Auditor is responsible for the overall execution of internal audit reviews and assignments consistent with the purpose, authority and responsibilities defined in the charter. | Requirements: Strong report writing and communication skills. Ability to prepare, update, and maintain comprehensive audit working papers. Sound knowledge of internal audit methodologies, including risk assessment, research, and audit planning. Analytical mindset with attention to detail and professional integrity."
    }
  },
  {
    "type": "career",
    "title": "FDP and Bakery Production Manager",
    "url": null,
    "department": "Ice Cream Production (IL)",
    "location": "Sabhan",
    "text": "Title: FDP and Bakery Production Manager | Department: Ice Cream Production (IL) | Location: Sabhan | Skills: Production Management; Quality Control Standards; Team Leadership; Food Safety Regulations; Process Optimization; Problem Solving; Communication Skills; Supply Chain Coordination; Data Analysis; Inventory Management | Skills: Production Management; Quality Control Standards; Team Leadership; Food Safety Regulations; Process Optimization; Problem Solving; Communication Skills; Supply Chain Coordination; Data Analysis; Inventory Management |",
    "meta": {
      "dedup_key": "7b005fe89c224269",
      "id_src": "76807",
      "title": "FDP and Bakery Production Manager",
      "url": null,
      "location": "Sabhan",
      "department_code": "610",
      "department_name": "Ice Cream Production (IL)",
      "job_type": null,
      "min_years": null,
      "max_years": null,
      "skills_required": [
        "Production Management",
        "Quality Control Standards",
        "Team Leadership",
        "Food Safety Regulations",
        "Process Optimization",
        "Problem Solving",
        "Communication Skills",
        "Supply Chain Coordination",
        "Data Analysis",
        "Inventory Management"
      ],
      "duties": null,
      "requirements": null,
      "embedding_text": "Title: FDP and Bakery Production Manager | Department: Ice Cream Production (IL) | Location: Sabhan | Skills: Production Management; Quality Control Standards; Team Leadership; Food Safety Regulations; Process Optimization; Problem Solving; Communication Skills; Supply Chain Coordination; Data Analysis; Inventory Management"
    }
  },
  {
    "type": "career",
    "title": "Project Manager - Buildings",
    "url": null,
    "department": "Building and Maintenance",
    "location": "Sabhan",
    "text": "Title: Project Manager - Buildings | Department: Building and Maintenance | Location: Sabhan | Skills: Project Management; Budget Management; Communication Skills; Risk Management; Team Leadership; Scheduling Software Proficiency; Quality Assurance; Negotiation Skills | Duties: Project requirement gathering and scoping the Project in alignment with all relevant stakeholders Conducting the technical feasibility for the Project and facilitating the financial feasibility Defining project tasks and resource requirements Developing, maintaining, and abiding by the project plans and timelines Defining all project stakeholders and managing them effectively Preparing and Managing Project Budget Managing Project Procurement Reviewing shop drawings, material submittals, coordination with Electro-mechanical discipline, time schedule and construction quality control aspects. Managing project resource allocation Monitoring and reporting project progress of a project on timely basis Defining the project risk register and managing the same throughout the project lifecycle Managing changes within the project by means of effective change management Supporting external project within the domain of my specialization Supporting the competency development of the team Complying with Health, Safety and Environment regulations and working practices of KDD and the State of Kuwait when carrying out duties. Executing Management directives as required. Functional Reporting to: Executive Manager - Building Maintenance & Development | Skills: Project Management; Budget Management; Communication Skills; Risk Management; Team Leadership; Scheduling Software Proficiency; Quality Assurance; Negotiation Skills | Project requirement gathering and scoping the Project in alignment with all relevant stakeholders Conducting the technical feasibility for the Project and facilitating the financial feasibility Defining project tasks and resource requirements Developing, maintaining, and abiding by the project plans and timelines Defining all project stakeholders and managing them effectively Preparing and Managing Project Budget Managing Project Procurement Reviewing shop drawings, material submittals, coordination with Electro-mechanical discipline, time schedule and construction quality control aspects. Managing project resource allocation Monitoring and reporting project progress of a project on timely basis Defining the project risk register and managing the same throughout the project lifecycle Managing changes within the project by means of effective change management Supporting external project within the domain of my specialization Supporting the competency development of the team Complying with Health, Safety and Environment regulations and working practices of KDD and the State of Kuwait when carrying out duties. Executing Management directives as required. Functional Reporting to: Executive Manager - Building Maintenance & Development",
    "meta": {
      "dedup_key": "47d1a6433485b32c",
      "id_src": "76609",
      "title": "Project Manager - Buildings",
      "url": null,
      "location": "Sabhan",
      "department_code": "709",
      "department_name": "Building and Maintenance",
      "job_type": null,
      "min_years": null,
      "max_years": null,
      "skills_required": [
        "Project Management",
        "Budget Management",
        "Communication Skills",
        "Risk Management",
        "Team Leadership",
        "Scheduling Software Proficiency",
        "Quality Assurance",
        "Negotiation Skills"
      ],
      "duties": [
        "Project requirement gathering and scoping the Project in alignment with all relevant stakeholders",
        "Conducting the technical feasibility for the Project and facilitating the financial feasibility",
        "Defining project tasks and resource requirements",
        "Developing, maintaining, and abiding by the project plans and timelines",
        "Defining all project stakeholders and managing them effectively",
        "Preparing and Managing Project Budget",
        "Managing Project Procurement",
        "Reviewing shop drawings, material submittals, coordination with Electro-mechanical discipline, time schedule and construction quality control aspects.",
        "Managing project resource allocation",
        "Monitoring and reporting project progress of a project on timely basis",
        "Defining the project risk register and managing the same throughout the project lifecycle",
        "Managing changes within the project by means of effective change management",
        "Supporting external project within the domain of my specialization",
        "Supporting the competency development of the team",
        "Complying with Health, Safety and Environment regulations and working practices of KDD and the State of Kuwait when carrying out duties.",
        "Executing Management directives as required.",
        "Functional Reporting to: Executive Manager - Building Maintenance & Development"
      ],
      "requirements": null,
      "embedding_text": "Title: Project Manager - Buildings | Department: Building and Maintenance | Location: Sabhan | Skills: Project Management; Budget Management; Communication Skills; Risk Management; Team Leadership; Scheduling Software Proficiency; Quality Assurance; Negotiation Skills | Duties: Project requirement gathering and scoping the Project in alignment with all relevant stakeholders Conducting the technical feasibility for the Project and facilitating the financial feasibility Defining project tasks and resource requirements Developing, maintaining, and abiding by the project plans and timelines Defining all project stakeholders and managing them effectively Preparing and Managing Project Budget Managing Project Procurement Reviewing shop drawings, material submittals, coordination with Electro-mechanical discipline, time schedule and construction quality control aspects. Managing project resource allocation Monitoring and reporting project progress of a project on timely basis Defining the project risk register and managing the same throughout the project lifecycle Managing changes within the project by means of effective change management Supporting external project within the domain of my specialization Supporting the competency development of the team Complying with Health, Safety and Environment regulations and working practices of KDD and the State of Kuwait when carrying out duties. Executing Management directives as required. Functional Reporting to: Executive Manager - Building Maintenance & Development"
    }
  },
  {
    "type": "career",
    "title": "Environmental Engineer - Data Analysis & Training Coordinator",
    "url": null,
    "department": "Environment",
    "location": "Sabhan",
    "text": "Title: Environmental Engineer - Data Analysis & Training Coordinator | Department: Environment | Location: Sabhan | Skills: Data Analysis; Environmental Regulations Knowledge; MS Excel Proficiency; Project Management; Communication Skills; ProblemSolving Skills; Training and Development Skills; Statistical Software Expertise | Duties: To support the Environmental Department in two key areas: environmental KPI data analysis and the management of our internal environmental training programs. This role is essential in ensuring our environmental performance is effectively measured, communicated, and improved through accurate data reporting and consistent employee training. | Skills: Data Analysis; Environmental Regulations Knowledge; MS Excel Proficiency; Project Management; Communication Skills; ProblemSolving Skills; Training and Development Skills; Statistical Software Expertise | To support the Environmental Department in two key areas: environmental KPI data analysis and the management of our internal environmental training programs. This role is essential in ensuring our environmental performance is effectively measured, communicated, and improved through accurate data reporting and consistent employee training.",
    "meta": {
      "dedup_key": "9a4819989c26a647",
      "id_src": "76188",
      "title": "Environmental Engineer - Data Analysis & Training Coordinator",
      "url": null,
      "location": "Sabhan",
      "department_code": "711",
      "department_name": "Environment",
      "job_type": null,
      "min_years": null,
      "max_years": null,
      "skills_required": [
        "Data Analysis",
        "Environmental Regulations Knowledge",
        "MS Excel Proficiency",
        "Project Management",
        "Communication Skills",
        "ProblemSolving Skills",
        "Training and Development Skills",
        "Statistical Software Expertise"
      ],
      "duties": [
        "To support the Environmental Department in two key areas: environmental KPI data analysis and the management of our internal environmental training programs. This role is essential in ensuring our environmental performance is effectively measured, communicated, and improved through accurate data reporting and consistent employee training."
      ],
      "requirements": null,
      "embedding_text": "Title: Environmental Engineer - Data Analysis & Training Coordinator | Department: Environment | Location: Sabhan | Skills: Data Analysis; Environmental Regulations Knowledge; MS Excel Proficiency; Project Management; Communication Skills; ProblemSolving Skills; Training and Development Skills; Statistical Software Expertise | Duties: To support the Environmental Department in two key areas: environmental KPI data analysis and the management of our internal environmental training programs. This role is essential in ensuring our environmental performance is effectively measured, communicated, and improved through accurate data reporting and consistent employee training."
    }
  },
  {
    "type": "career",
    "title": "Project and Service Delivery Manager - MIS",
    "url": null,
    "department": "MIS",
    "location": "Sabhan",
    "text": "Title: Project and Service Delivery Manager - MIS | Department: MIS | Location: Sabhan | Skills: ITIL; PMP; Analytic Thinking; Problem Solving; Verbal Communication; Written Communication; Team Leadership; Time Management; CustomerCentric Approach; Strategic Thinking | Duties: Setup the Project Management environment following best practice standards. This includes the methodology to be followed in managing projects, Phases, deliverables, templates to be used within each phase of the SDLC. Lead and manage IT projects from initiation to completion, ensuring they are delivered on time, within scope, and within budget. Provide oversight and follow-up on MIS/IT project portfolios to ensure they are progressing according to plan, budget, and deadlines. Collaborate with project managers and teams to ensure proper management of project is being followed to ensure success. Track the progress of projects within the portfolio of projects, providing regular updates to stakeholders on status, risks, and issues. Maintain clear and effective communication with project sponsors, stakeholders, and management to ensure alignment and support. Identify and mitigate risks across the project portfolio to ensure successful project delivery. Evaluate the performance of projects and the portfolio as a whole, identifying areas for improvement and implementing necessary changes. Establish and maintain project governance structures, processes, and standards to ensure consistency and quality in project delivery. Manage changes to the project portfolio, ensuring that changes are assessed, approved, and communicated effectively. Promote and implement continuous improvement initiatives within the project management processes and portfolio management practices. Supervise and lead a team of service desk agents and technicians, providing guidance, support, and feedback to ensure high-quality service delivery. Ensure the timely and effective delivery of IT services to end-users and customers, meeting or exceeding predefined service level agreements (SLAs). Oversee the handling of IT incidents and service requests, ensuring they are properly logged, categorized, prioritized, and resolved within acceptable timeframes. Interact with users to understand their needs, address concerns, and gather feedback to continuously improve service quality. Monitor and evaluate the team's performance, identifying areas for improvement and implementing corrective actions as needed. Organize training sessions to enhance the skills and knowledge of the team, keeping them up to date with the latest technologies and management best practices. Ensure accurate and up-to-date documentation of processes, procedures, and troubleshooting steps to facilitate knowledge sharing and consistency in service delivery. Continuously analyze service desk metrics and customer feedback to identify opportunities for process improvements and enhanced customer experiences. Handle and escalate complex or high-priority issues to appropriate teams or management for resolution. | Skills: ITIL; PMP; Analytic Thinking; Problem Solving; Verbal Communication; Written Communication; Team Leadership; Time Management; CustomerCentric Approach; Strategic Thinking | Setup the Project Management environment following best practice standards. This includes the methodology to be followed in managing projects, Phases, deliverables, templates to be used within each phase of the SDLC. Lead and manage IT projects from initiation to completion, ensuring they are delivered on time, within scope, and within budget. Provide oversight and follow-up on MIS/IT project portfolios to ensure they are progressing according to plan, budget, and deadlines. Collaborate with project managers and teams to ensure proper management of project is being followed to ensure success. Track the progress of projects within the portfolio of projects, providing regular updates to stakeholders on status, risks, and issues. Maintain clear and effective communication with project sponsors, stakeholders, and management to ensure alignment and support. Identify and mitigate risks across the project portfolio to ensure successful project delivery. Evaluate the performance of projects and the portfolio as a whole, identifying areas for improvement and implementing necessary changes. Establish and maintain project governance structures, processes, and standards to ensure consistency and quality in project delivery. Manage changes to the project portfolio, ensuring that changes are assessed, approved, and communicated effectively. Promote and implement continuous improvement initiatives within the project management processes and portfolio management practices. Supervise and lead a team of service desk agents and technicians, providing guidance, support, and feedback to ensure high-quality service delivery. Ensure the timely and effective delivery of IT services to end-users and customers, meeting or exceeding predefined service level agreements (SLAs). Oversee the handling of IT incidents and service requests, ensuring they are properly logged, categorized, prioritized, and resolved within acceptable timeframes. Interact with users to understand their needs, address concerns, and gather feedback to continuously improve service quality. Monitor and evaluate the team's performance, identifying areas for improvement and implementing corrective actions as needed. Organize training sessions to enhance the skills and knowledge of the team, keeping them up to date with the latest technologies and management best practices. Ensure accurate and up-to-date documentation of processes, procedures, and troubleshooting steps to facilitate knowledge sharing and consistency in service delivery. Continuously analyze service desk metrics and customer feedback to identify opportunities for process improvements and enhanced customer experiences. Handle and escalate complex or high-priority issues to appropriate teams or management for resolution.",
    "meta": {
      "dedup_key": "8c80bbaa3dd91872",
      "id_src": "76178",
      "title": "Project and Service Delivery Manager - MIS",
      "url": null,
      "location": "Sabhan",
      "department_code": "690",
      "department_name": "MIS",
      "job_type": null,
      "min_years": null,
      "max_years": null,
      "skills_required": [
        "ITIL",
        "PMP",
        "Analytic Thinking",
        "Problem Solving",
        "Verbal Communication",
        "Written Communication",
        "Team Leadership",
        "Time Management",
        "CustomerCentric Approach",
        "Strategic Thinking"
      ],
      "duties": [
        "Setup the Project Management environment following best practice standards. This includes the methodology to be followed in managing projects, Phases, deliverables, templates to be used within each phase of the SDLC.",
        "Lead and manage IT projects from initiation to completion, ensuring they are delivered on time, within scope, and within budget.",
        "Provide oversight and follow-up on MIS/IT project portfolios to ensure they are progressing according to plan, budget, and deadlines.",
        "Collaborate with project managers and teams to ensure proper management of project is being followed to ensure success.",
        "Track the progress of projects within the portfolio of projects, providing regular updates to stakeholders on status, risks, and issues.",
        "Maintain clear and effective communication with project sponsors, stakeholders, and management to ensure alignment and support.",
        "Identify and mitigate risks across the project portfolio to ensure successful project delivery.",
        "Evaluate the performance of projects and the portfolio as a whole, identifying areas for improvement and implementing necessary changes.",
        "Establish and maintain project governance structures, processes, and standards to ensure consistency and quality in project delivery.",
        "Manage changes to the project portfolio, ensuring that changes are assessed, approved, and communicated effectively.",
        "Promote and implement continuous improvement initiatives within the project management processes and portfolio management practices.",
        "Supervise and lead a team of service desk agents and technicians, providing guidance, support, and feedback to ensure high-quality service delivery.",
        "Ensure the timely and effective delivery of IT services to end-users and customers, meeting or exceeding predefined service level agreements (SLAs).",
        "Oversee the handling of IT incidents and service requests, ensuring they are properly logged, categorized, prioritized, and resolved within acceptable timeframes.",
        "Interact with users to understand their needs, address concerns, and gather feedback to continuously improve service quality.",
        "Monitor and evaluate the team's performance, identifying areas for improvement and implementing corrective actions as needed.",
        "Organize training sessions to enhance the skills and knowledge of the team, keeping them up to date with the latest technologies and management best practices.",
        "Ensure accurate and up-to-date documentation of processes, procedures, and troubleshooting steps to facilitate knowledge sharing and consistency in service delivery.",
        "Continuously analyze service desk metrics and customer feedback to identify opportunities for process improvements and enhanced customer experiences.",
        "Handle and escalate complex or high-priority issues to appropriate teams or management for resolution."
      ],
      "requirements": null,
      "embedding_text": "Title: Project and Service Delivery Manager - MIS | Department: MIS | Location: Sabhan | Skills: ITIL; PMP; Analytic Thinking; Problem Solving; Verbal Communication; Written Communication; Team Leadership; Time Management; CustomerCentric Approach; Strategic Thinking | Duties: Setup the Project Management environment following best practice standards. This includes the methodology to be followed in managing projects, Phases, deliverables, templates to be used within each phase of the SDLC. Lead and manage IT projects from initiation to completion, ensuring they are delivered on time, within scope, and within budget. Provide oversight and follow-up on MIS/IT project portfolios to ensure they are progressing according to plan, budget, and deadlines. Collaborate with project managers and teams to ensure proper management of project is being followed to ensure success. Track the progress of projects within the portfolio of projects, providing regular updates to stakeholders on status, risks, and issues. Maintain clear and effective communication with project sponsors, stakeholders, and management to ensure alignment and support. Identify and mitigate risks across the project portfolio to ensure successful project delivery. Evaluate the performance of projects and the portfolio as a whole, identifying areas for improvement and implementing necessary changes. Establish and maintain project governance structures, processes, and standards to ensure consistency and quality in project delivery. Manage changes to the project portfolio, ensuring that changes are assessed, approved, and communicated effectively. Promote and implement continuous improvement initiatives within the project management processes and portfolio management practices. Supervise and lead a team of service desk agents and technicians, providing guidance, support, and feedback to ensure high-quality service delivery. Ensure the timely and effective delivery of IT services to end-users and customers, meeting or exceeding predefined service level agreements (SLAs). Oversee the handling of IT incidents and service requests, ensuring they are properly logged, categorized, prioritized, and resolved within acceptable timeframes. Interact with users to understand their needs, address concerns, and gather feedback to continuously improve service quality. Monitor and evaluate the team's performance, identifying areas for improvement and implementing corrective actions as needed. Organize training sessions to enhance the skills and knowledge of the team, keeping them up to date with the latest technologies and management best practices. Ensure accurate and up-to-date documentation of processes, procedures, and troubleshooting steps to facilitate knowledge sharing and consistency in service delivery. Continuously analyze service desk metrics and customer feedback to identify opportunities for process improvements and enhanced customer experiences. Handle and escalate complex or high-priority issues to appropriate teams or management for resolution."
    }
  },
  {
    "type": "career",
    "title": "Supply Chain Assistant Manager",
    "url": null,
    "department": "Purchasing",
    "location": "Subhan",
    "text": "Title: Supply Chain Assistant Manager | Department: Purchasing | Location: Subhan | Skills: Supply Chain Management; Inventory Control; Data Analysis; Vendor Management; Communication Skills; Problem Solving; Project Management; Logistics Coordination; ERP Systems Proficiency e.g. Oracle Maximo; Regulatory Compliance Dairy Industry | Skills: Supply Chain Management; Inventory Control; Data Analysis; Vendor Management; Communication Skills; Problem Solving; Project Management; Logistics Coordination; ERP Systems Proficiency e.g. Oracle Maximo; Regulatory Compliance Dairy Industry |",
    "meta": {
      "dedup_key": "a2b436323c1bfc7e",
      "id_src": "75909",
      "title": "Supply Chain Assistant Manager",
      "url": null,
      "location": "Subhan",
      "department_code": "680",
      "department_name": "Purchasing",
      "job_type": null,
      "min_years": null,
      "max_years": null,
      "skills_required": [
        "Supply Chain Management",
        "Inventory Control",
        "Data Analysis",
        "Vendor Management",
        "Communication Skills",
        "Problem Solving",
        "Project Management",
        "Logistics Coordination",
        "ERP Systems Proficiency e.g. Oracle Maximo",
        "Regulatory Compliance Dairy Industry"
      ],
      "duties": null,
      "requirements": null,
      "embedding_text": "Title: Supply Chain Assistant Manager | Department: Purchasing | Location: Subhan | Skills: Supply Chain Management; Inventory Control; Data Analysis; Vendor Management; Communication Skills; Problem Solving; Project Management; Logistics Coordination; ERP Systems Proficiency e.g. Oracle Maximo; Regulatory Compliance Dairy Industry"
    }
  },
  {
    "type": "career",
    "title": "Manager - Institutional Sales",
    "url": null,
    "department": "Staff Dairy Sales",
    "location": "Sabhan",
    "text": "Title: Manager - Institutional Sales | Department: Staff Dairy Sales | Location: Sabhan | Skills: Strategic Planning; Sales Management; Market Analysis; Negotiation Skills; Customer Relationship Management CRM; Team Leadership; Financial Acumen; Manufacturing Sector Knowledge; Presentation Skills | Duties: Conduct market research to identify opportunities, trends, and competition within institutional channels. Develop and implement sales strategies to maximize penetration and revenue in each segment. Evaluate the existing product portfolio and recommend fitment for each channel. Identify missing pack sizes or products to enhance company penetration and revenues. Negotiate and finalize contracts with institutional customers. Ensure adherence to credit terms, minimize risks, and manage overdue payments. Maintain excellent relations with institutional clients. Train internal teams to optimize customer satisfaction. Collaborate with institutional clients for digital processes in order placement, invoicing, and payment. Explore opportunities for digital engagement to enhance operational efficiency. Ensure proper issuance of company assets against approved contracts. Prevent misuse of assets by customers for competitor products. Proactively identify and pursue new business opportunities. Develop clear work plans for the position and team members to achieve business goals. Stay updated with the latest information on available customers in each channel. Develop and maintain a comprehensive work plan to address gaps in product availability. Present an annual business plan with detailed strategies, targets, and key initiatives. Proficient in MS Office Suite for creating compelling presentations. Ability to entice customers and sell proposals effectively within the organization. Comply with Health, Safety and Environment regulations and working practices of KDD and the State of Kuwait when carrying out duties. | Requirements: Proven experience in sales, with a focus on institutional channels. Strong analytical and strategic thinking skills. Excellent negotiation, communication, and presentation skills. Familiarity with MS Office Suite Fluency in Arabic and English is a must. | Skills: Strategic Planning; Sales Management; Market Analysis; Negotiation Skills; Customer Relationship Management CRM; Team Leadership; Financial Acumen; Manufacturing Sector Knowledge; Presentation Skills | Conduct market research to identify opportunities, trends, and competition within institutional channels. Develop and implement sales strategies to maximize penetration and revenue in each segment. Evaluate the existing product portfolio and recommend fitment for each channel. Identify missing pack sizes or products to enhance company penetration and revenues. Negotiate and finalize contracts with institutional customers. Ensure adherence to credit terms, minimize risks, and manage overdue payments. Maintain excellent relations with institutional clients. Train internal teams to optimize customer satisfaction. Collaborate with institutional clients for digital processes in order placement, invoicing, and payment. Explore opportunities for digital engagement to enhance operational efficiency. Ensure proper issuance of company assets against approved contracts. Prevent misuse of assets by customers for competitor products. Proactively identify and pursue new business opportunities. Develop clear work plans for the position and team members to achieve business goals. Stay updated with the latest information on available customers in each channel. Develop and maintain a comprehensive work plan to address gaps in product availability. Present an annual business plan with detailed strategies, targets, and key initiatives. Proficient in MS Office Suite for creating compelling presentations. Ability to entice customers and sell proposals effectively within the organization. Comply with Health, Safety and Environment regulations and working practices of KDD and the State of Kuwait when carrying out duties. Proven experience in sales, with a focus on institutional channels. Strong analytical and strategic thinking skills. Excellent negotiation, communication, and presentation skills. Familiarity with MS Office Suite Fluency in Arabic and English is a must.",
    "meta": {
      "dedup_key": "fc4a2ee2553c5168",
      "id_src": "75409",
      "title": "Manager - Institutional Sales",
      "url": null,
      "location": "Sabhan",
      "department_code": "601",
      "department_name": "Staff Dairy Sales",
      "job_type": null,
      "min_years": null,
      "max_years": null,
      "skills_required": [
        "Strategic Planning",
        "Sales Management",
        "Market Analysis",
        "Negotiation Skills",
        "Customer Relationship Management CRM",
        "Team Leadership",
        "Financial Acumen",
        "Manufacturing Sector Knowledge",
        "Presentation Skills"
      ],
      "duties": [
        "Conduct market research to identify opportunities, trends, and competition within institutional channels.",
        "Develop and implement sales strategies to maximize penetration and revenue in each segment.",
        "Evaluate the existing product portfolio and recommend fitment for each channel.",
        "Identify missing pack sizes or products to enhance company penetration and revenues.",
        "Negotiate and finalize contracts with institutional customers.",
        "Ensure adherence to credit terms, minimize risks, and manage overdue payments.",
        "Maintain excellent relations with institutional clients.",
        "Train internal teams to optimize customer satisfaction.",
        "Collaborate with institutional clients for digital processes in order placement, invoicing, and payment.",
        "Explore opportunities for digital engagement to enhance operational efficiency.",
        "Ensure proper issuance of company assets against approved contracts.",
        "Prevent misuse of assets by customers for competitor products.",
        "Proactively identify and pursue new business opportunities.",
        "Develop clear work plans for the position and team members to achieve business goals.",
        "Stay updated with the latest information on available customers in each channel.",
        "Develop and maintain a comprehensive work plan to address gaps in product availability.",
        "Present an annual business plan with detailed strategies, targets, and key initiatives.",
        "Proficient in MS Office Suite for creating compelling presentations.",
        "Ability to entice customers and sell proposals effectively within the organization.",
        "Comply with Health, Safety and Environment regulations and working practices of KDD and the State of Kuwait when carrying out duties."
      ],
      "requirements": [
        "Proven experience in sales, with a focus on institutional channels.",
        "Strong analytical and strategic thinking skills.",
        "Excellent negotiation, communication, and presentation skills.",
        "Familiarity with MS Office Suite",
        "Fluency in Arabic and English is a must."
      ],
      "embedding_text": "Title: Manager - Institutional Sales | Department: Staff Dairy Sales | Location: Sabhan | Skills: Strategic Planning; Sales Management; Market Analysis; Negotiation Skills; Customer Relationship Management CRM; Team Leadership; Financial Acumen; Manufacturing Sector Knowledge; Presentation Skills | Duties: Conduct market research to identify opportunities, trends, and competition within institutional channels. Develop and implement sales strategies to maximize penetration and revenue in each segment. Evaluate the existing product portfolio and recommend fitment for each channel. Identify missing pack sizes or products to enhance company penetration and revenues. Negotiate and finalize contracts with institutional customers. Ensure adherence to credit terms, minimize risks, and manage overdue payments. Maintain excellent relations with institutional clients. Train internal teams to optimize customer satisfaction. Collaborate with institutional clients for digital processes in order placement, invoicing, and payment. Explore opportunities for digital engagement to enhance operational efficiency. Ensure proper issuance of company assets against approved contracts. Prevent misuse of assets by customers for competitor products. Proactively identify and pursue new business opportunities. Develop clear work plans for the position and team members to achieve business goals. Stay updated with the latest information on available customers in each channel. Develop and maintain a comprehensive work plan to address gaps in product availability. Present an annual business plan with detailed strategies, targets, and key initiatives. Proficient in MS Office Suite for creating compelling presentations. Ability to entice customers and sell proposals effectively within the organization. Comply with Health, Safety and Environment regulations and working practices of KDD and the State of Kuwait when carrying out duties. | Requirements: Proven experience in sales, with a focus on institutional channels. Strong analytical and strategic thinking skills. Excellent negotiation, communication, and presentation skills. Familiarity with MS Office Suite Fluency in Arabic and English is a must."
    }
  },
  {
    "type": "career",
    "title": "Marketing Manager",
    "url": null,
    "department": "Marketing",
    "location": "Sabhan",
    "text": "Title: Marketing Manager | Department: Marketing | Location: Sabhan | Skills: Strategic Planning; Team Leadership; Market Analysis; Communication Skills; Budget Management; Sales Strategy; Digital Marketing; Project Management; Negotiation Skills | Skills: Strategic Planning; Team Leadership; Market Analysis; Communication Skills; Budget Management; Sales Strategy; Digital Marketing; Project Management; Negotiation Skills |",
    "meta": {
      "dedup_key": "c1cec0f559f0c91e",
      "id_src": "74303",
      "title": "Marketing Manager",
      "url": null,
      "location": "Sabhan",
      "department_code": "600",
      "department_name": "Marketing",
      "job_type": null,
      "min_years": null,
      "max_years": null,
      "skills_required": [
        "Strategic Planning",
        "Team Leadership",
        "Market Analysis",
        "Communication Skills",
        "Budget Management",
        "Sales Strategy",
        "Digital Marketing",
        "Project Management",
        "Negotiation Skills"
      ],
      "duties": null,
      "requirements": null,
      "embedding_text": "Title: Marketing Manager | Department: Marketing | Location: Sabhan | Skills: Strategic Planning; Team Leadership; Market Analysis; Communication Skills; Budget Management; Sales Strategy; Digital Marketing; Project Management; Negotiation Skills"
    }
  },
  {
    "type": "career",
    "title": "IT Security Specialist - Information Security",
    "url": null,
    "department": "MIS",
    "location": "Sabhan",
    "text": "Title: IT Security Specialist - Information Security | Department: MIS | Location: Sabhan | Skills: Network Security; Threat Analysis; Incident Response; Vulnerability Assessment; Data Protection Techniques; Security Information and Event Management SIEM; Compliance Standards e.g. GDPR HIPAA; Communication Skills; Firewalls and VPNs; Security Frameworks e.g. NIST ISO 27001 | Duties: We are currently seeking a mid-level, knowledgeable IT Security Specialist to join our IT team. The candidate will be responsible for implementing and maintaining cybersecurity measures to protect our company's networks, systems, and data from potential threats. Identify and fix vulnerabilities within existing security systems. Develop organization-wide security measures. Document known security breaches and vulnerabilities. Maintain security policies, procedures, and guidelines to ensure compliance with regulatory frameworks and industry standards. Monitor and analyze security events and incidents to identify and respond to potential threats promptly. Perform penetration tests to assess potential security problems. Stay up to date with the latest threats, vulnerabilities, and security technologies to mitigate emerging risks. Collaborate with cross-functional teams to integrate security measures into the development of new systems and applications. Scan and discover network and system vulnerabilities using various tools, and perform penetration testing when required. Maintain documentation and reports related to cybersecurity incidents, actions taken, and compliance requirements. Perform configuration reviews for security systems like firewalls and Endpoint Detection and Response (EDR). Establish relationships with external cybersecurity partners, vendors, and service providers. Plan incident response activities, including investigating security breaches and recommending corrective actions. Participate in the change management process. | Skills: Network Security; Threat Analysis; Incident Response; Vulnerability Assessment; Data Protection Techniques; Security Information and Event Management SIEM; Compliance Standards e.g. GDPR HIPAA; Communication Skills; Firewalls and VPNs; Security Frameworks e.g. NIST ISO 27001 | We are currently seeking a mid-level, knowledgeable IT Security Specialist to join our IT team. The candidate will be responsible for implementing and maintaining cybersecurity measures to protect our company's networks, systems, and data from potential threats. Identify and fix vulnerabilities within existing security systems. Develop organization-wide security measures. Document known security breaches and vulnerabilities. Maintain security policies, procedures, and guidelines to ensure compliance with regulatory frameworks and industry standards. Monitor and analyze security events and incidents to identify and respond to potential threats promptly. Perform penetration tests to assess potential security problems. Stay up to date with the latest threats, vulnerabilities, and security technologies to mitigate emerging risks. Collaborate with cross-functional teams to integrate security measures into the development of new systems and applications. Scan and discover network and system vulnerabilities using various tools, and perform penetration testing when required. Maintain documentation and reports related to cybersecurity incidents, actions taken, and compliance requirements. Perform configuration reviews for security systems like firewalls and Endpoint Detection and Response (EDR). Establish relationships with external cybersecurity partners, vendors, and service providers. Plan incident response activities, including investigating security breaches and recommending corrective actions. Participate in the change management process.",
    "meta": {
      "dedup_key": "8a1d7de7a5af137d",
      "id_src": "69979",
      "title": "IT Security Specialist - Information Security",
      "url": null,
      "location": "Sabhan",
      "department_code": "690",
      "department_name": "MIS",
      "job_type": null,
      "min_years": null,
      "max_years": null,
      "skills_required": [
        "Network Security",
        "Threat Analysis",
        "Incident Response",
        "Vulnerability Assessment",
        "Data Protection Techniques",
        "Security Information and Event Management SIEM",
        "Compliance Standards e.g. GDPR HIPAA",
        "Communication Skills",
        "Firewalls and VPNs",
        "Security Frameworks e.g. NIST ISO 27001"
      ],
      "duties": [
        "We are currently seeking a mid-level, knowledgeable IT Security Specialist to join our IT team.",
        "The candidate will be responsible for implementing and maintaining cybersecurity measures to protect our company's networks, systems, and data from potential threats.",
        "Identify and fix vulnerabilities within existing security systems.",
        "Develop organization-wide security measures.",
        "Document known security breaches and vulnerabilities.",
        "Maintain security policies, procedures, and guidelines to ensure compliance with regulatory frameworks and industry standards.",
        "Monitor and analyze security events and incidents to identify and respond to potential threats promptly.",
        "Perform penetration tests to assess potential security problems.",
        "Stay up to date with the latest threats, vulnerabilities, and security technologies to mitigate emerging risks.",
        "Collaborate with cross-functional teams to integrate security measures into the development of new systems and applications.",
        "Scan and discover network and system vulnerabilities using various tools, and perform penetration testing when required.",
        "Maintain documentation and reports related to cybersecurity incidents, actions taken, and compliance requirements.",
        "Perform configuration reviews for security systems like firewalls and Endpoint Detection and Response (EDR).",
        "Establish relationships with external cybersecurity partners, vendors, and service providers.",
        "Plan incident response activities, including investigating security breaches and recommending corrective actions.",
        "Participate in the change management process."
      ],
      "requirements": null,
      "embedding_text": "Title: IT Security Specialist - Information Security | Department: MIS | Location: Sabhan | Skills: Network Security; Threat Analysis; Incident Response; Vulnerability Assessment; Data Protection Techniques; Security Information and Event Management SIEM; Compliance Standards e.g. GDPR HIPAA; Communication Skills; Firewalls and VPNs; Security Frameworks e.g. NIST ISO 27001 | Duties: We are currently seeking a mid-level, knowledgeable IT Security Specialist to join our IT team. The candidate will be responsible for implementing and maintaining cybersecurity measures to protect our company's networks, systems, and data from potential threats. Identify and fix vulnerabilities within existing security systems. Develop organization-wide security measures. Document known security breaches and vulnerabilities. Maintain security policies, procedures, and guidelines to ensure compliance with regulatory frameworks and industry standards. Monitor and analyze security events and incidents to identify and respond to potential threats promptly. Perform penetration tests to assess potential security problems. Stay up to date with the latest threats, vulnerabilities, and security technologies to mitigate emerging risks. Collaborate with cross-functional teams to integrate security measures into the development of new systems and applications. Scan and discover network and system vulnerabilities using various tools, and perform penetration testing when required. Maintain documentation and reports related to cybersecurity incidents, actions taken, and compliance requirements. Perform configuration reviews for security systems like firewalls and Endpoint Detection and Response (EDR). Establish relationships with external cybersecurity partners, vendors, and service providers. Plan incident response activities, including investigating security breaches and recommending corrective actions. Participate in the change management process."
    }
  },
  {
    "type": "career",
    "title": "Business Systems Analyst - Retail (Oodo System)",
    "url": null,
    "department": "MIS",
    "location": "Sabhan",
    "text": "Title: Business Systems Analyst - Retail (Oodo System) | Department: MIS | Location: Sabhan | Skills: Odoo System Knowledge; Business Process Analysis; Data Analysis and Reporting; Project Management; Stakeholder Communication; Retail Operations Understanding; SQL Proficiency; Technical Documentation | Duties: Analyze and document business processes related to retail operations, including POS, procurement, inventory, recipe management, pricing, promotions, and e-commerce. Collaborate with stakeholders from various departments to understand their requirements and objectives. Serve as a liaison between business units and IT to translate business needs into system requirements. Implement, configure, and maintain Odoo 16/17 business, financial, and marketing modules. Conduct regular system audits to ensure accurate and efficient operation. Provide training and support to staff on the use of Odoo systems. Collaborate with IT to manage system upgrades, patches, and other maintenance tasks. Monitor system usability and gather feedback from users to identify opportunities for continuous improvement. Ensure compliance with relevant laws, regulations, and best practices within the system's processes. Advise on the use of various Odoo options and recommend best practices for enhancements. | Requirements: Proven experience as a Business System Analyst. Excellent analytical and problem-solving skills. Outstanding communication and interpersonal skills. Analytical mindset with proficiency in data analysis and reporting tools. Ability to work effectively in a team environment as well as independently. Knowledge about various Odoo options and best practices for maintenance and enhancements. Experience in Odoo 16/17 is a Plus. | Skills: Odoo System Knowledge; Business Process Analysis; Data Analysis and Reporting; Project Management; Stakeholder Communication; Retail Operations Understanding; SQL Proficiency; Technical Documentation | Analyze and document business processes related to retail operations, including POS, procurement, inventory, recipe management, pricing, promotions, and e-commerce. Collaborate with stakeholders from various departments to understand their requirements and objectives. Serve as a liaison between business units and IT to translate business needs into system requirements. Implement, configure, and maintain Odoo 16/17 business, financial, and marketing modules. Conduct regular system audits to ensure accurate and efficient operation. Provide training and support to staff on the use of Odoo systems. Collaborate with IT to manage system upgrades, patches, and other maintenance tasks. Monitor system usability and gather feedback from users to identify opportunities for continuous improvement. Ensure compliance with relevant laws, regulations, and best practices within the system's processes. Advise on the use of various Odoo options and recommend best practices for enhancements. Proven experience as a Business System Analyst. Excellent analytical and problem-solving skills. Outstanding communication and interpersonal skills. Analytical mindset with proficiency in data analysis and reporting tools. Ability to work effectively in a team environment as well as independently. Knowledge about various Odoo options and best practices for maintenance and enhancements. Experience in Odoo 16/17 is a Plus.",
    "meta": {
      "dedup_key": "4fc3c29ae51d4796",
      "id_src": "69978",
      "title": "Business Systems Analyst - Retail (Oodo System)",
      "url": null,
      "location": "Sabhan",
      "department_code": "690",
      "department_name": "MIS",
      "job_type": null,
      "min_years": null,
      "max_years": null,
      "skills_required": [
        "Odoo System Knowledge",
        "Business Process Analysis",
        "Data Analysis and Reporting",
        "Project Management",
        "Stakeholder Communication",
        "Retail Operations Understanding",
        "SQL Proficiency",
        "Technical Documentation"
      ],
      "duties": [
        "Analyze and document business processes related to retail operations, including POS, procurement, inventory, recipe management, pricing, promotions, and e-commerce.",
        "Collaborate with stakeholders from various departments to understand their requirements and objectives.",
        "Serve as a liaison between business units and IT to translate business needs into system requirements.",
        "Implement, configure, and maintain Odoo 16/17 business, financial, and marketing modules.",
        "Conduct regular system audits to ensure accurate and efficient operation.",
        "Provide training and support to staff on the use of Odoo systems.",
        "Collaborate with IT to manage system upgrades, patches, and other maintenance tasks.",
        "Monitor system usability and gather feedback from users to identify opportunities for continuous improvement.",
        "Ensure compliance with relevant laws, regulations, and best practices within the system's processes.",
        "Advise on the use of various Odoo options and recommend best practices for enhancements."
      ],
      "requirements": [
        "Proven experience as a Business System Analyst.",
        "Excellent analytical and problem-solving skills.",
        "Outstanding communication and interpersonal skills.",
        "Analytical mindset with proficiency in data analysis and reporting tools.",
        "Ability to work effectively in a team environment as well as independently.",
        "Knowledge about various Odoo options and best practices for maintenance and enhancements.",
        "Experience in Odoo 16/17 is a Plus."
      ],
      "embedding_text": "Title: Business Systems Analyst - Retail (Oodo System) | Department: MIS | Location: Sabhan | Skills: Odoo System Knowledge; Business Process Analysis; Data Analysis and Reporting; Project Management; Stakeholder Communication; Retail Operations Understanding; SQL Proficiency; Technical Documentation | Duties: Analyze and document business processes related to retail operations, including POS, procurement, inventory, recipe management, pricing, promotions, and e-commerce. Collaborate with stakeholders from various departments to understand their requirements and objectives. Serve as a liaison between business units and IT to translate business needs into system requirements. Implement, configure, and maintain Odoo 16/17 business, financial, and marketing modules. Conduct regular system audits to ensure accurate and efficient operation. Provide training and support to staff on the use of Odoo systems. Collaborate with IT to manage system upgrades, patches, and other maintenance tasks. Monitor system usability and gather feedback from users to identify opportunities for continuous improvement. Ensure compliance with relevant laws, regulations, and best practices within the system's processes. Advise on the use of various Odoo options and recommend best practices for enhancements. | Requirements: Proven experience as a Business System Analyst. Excellent analytical and problem-solving skills. Outstanding communication and interpersonal skills. Analytical mindset with proficiency in data analysis and reporting tools. Ability to work effectively in a team environment as well as independently. Knowledge about various Odoo options and best practices for maintenance and enhancements. Experience in Odoo 16/17 is a Plus."
    }
  },
  {
    "type": "career",
    "title": "Software Development Manager",
    "url": null,
    "department": "MIS",
    "location": "Sabhan",
    "text": "Title: Software Development Manager | Department: MIS | Location: Sabhan | Skills: Leadership; Project Management; Agile Methodologies; Software Development Life Cycle SDLC; Java; C#; Database Management; Coding Standards; .NET; Team Collaboration; ITIL Certified; VBScript; Cloud Computing; DevOps; Microservices Architecture; API Development; Jest; Enzyme | Duties: • Leading a development unit that includes enterprise and custom development personnel. • Setting goals and objectives for the development team and ensuring they are met. • Providing mentorship and guidance to junior developers and other team members. • Evaluating the performance of team members and providing constructive feedback. • Facilitating continuous improvement within the development team and processes following best practice such as ITIL and other international standards. • Ensuring the team follows best practices for software development, security and operations (maintenance of different environments and code versions, QA and code testing, change / release management) • Maintaining and enhancing KDD Application and Enterprise footprint following best practices. • Developing front-end web architecture, designing user interactions on web pages, and ensuring web applications are optimized for mobile and desktop devices. • Building and maintaining back-end server-side applications and databases, designing and implementing efficient database structures, and integrating with third-party APIs. • Lead the efforts of setting up the reporting strategy that includes the backend data repository and from end reporting tools • Collaborating with cross-functional teams to identify, prioritize, and execute product features and functionality. • Writing reusable, testable, and efficient code as well as debugging and troubleshooting issues. • Developing and implementing security and data protection measures. • Ensuring the scalability and performance of applications and implementing necessary monitoring and optimization strategies. • Keeping up to date with emerging trends, technologies, and best practices in web development. • Providing technical guidance and reviewing code to ensure it meets established standards. • Responsible for setting goals and objectives, monitoring progress, and providing feedback to managers and team members. • Mentoring junior developers, sharing knowledge and best practices, and providing guidance on technical issues. • Creating technical documentation and user documentation such as user manuals, guides, or tutorials. • Executing Management directives as required. • Complying with Health, Safety and Environment regulations and working practices of KDD and the State of Kuwait when carrying out duties. | Requirements: • Proven ability to lead and manage a team of developers, fostering a collaborative and innovative environment. • Strong ability to motivate and inspire team members to achieve their full potential. • Expertise in project management methodologies such as Agile. • Skilled in strategic planning and setting long-term goals for the development team. • Ability to align development goals with organizational objectives. • Excellent written and verbal communication skills to effectively convey technical concepts to non-technical stakeholders. • Commitment to maintaining high-quality standards in software development. • Experience in resource allocation and optimizing the use of available resources. • Ability to promote a culture of innovation and continuous improvement within the team. • Demonstrated ability to identify and solve complex technical problems efficiently and effectively. • Excellent communication skills to collaborate with technical and non-technical stakeholders, including team members, project managers, and clients. • Strong time management skills to prioritize tasks and meet project deadlines. • Ability to adapt to changing project requirements and work effectively in a fast-paced, dynamic environment. • Proven experience in working collaboratively with other developers, designers, and stakeholders to achieve project goals. • Strong attention to detail to ensure that code is clean, efficient, and error-free. • Commitment to continuous learning and staying up to date with the latest technologies, tools, and best practices in web development. • Strong proficiency in programming languages such as C#, JavaScript, PHP, TypeScript, VB .NET, VBScript, and DAX. • Experience working with front-end frameworks such as Angular, AngularJS, and Knockout, and back-end frameworks like Node.js and PHP. • Experience with databases such as MySQL, Oracle, and SQL Server. • Knowledge of Oracle Development platforms (Forms, reports, PL/SQL). • Knowledge of Business Intelligence tools (OBIEE) and front-end reporting tools such as Power BI. • Knowledge of Oracle Cloud platform (OCI, APEX) and integration layer (OIC) is a plus • Expertise in IBM Maximo 7.6 development, and knowledge of Maximo Application Suit (MAS) 8 version is a plus. • Familiarity with DevOps tools such as Docker Kubernetes, Git and AWS. • Familiarity with SaaS cloud solutions and their integration. • Experience with Entity Framework Core and other modern ORM tools. • Familiarity with microservices architecture and containerization • Familiarity with CI/CD pipelines and automated testing frameworks. • Experience with web services such as RESTful APIs and SOAP. • Experience with desktop app development using WinForms. • Knowledge of dependency injection frameworks. • Familiarity with front-end technologies including CSS and HTML 5, as well as UI frameworks like Angular Material and Bootstrap. • Experience with server-side scripting languages such as Classic ASP, MVC, Razor, and WEB FORMS. • Experience with real-time communication technologies such as WebSocket and SignalR. • Familiarity with identity management tools such as ASP.NET Identity. • Experience with data access technologies including ADO, ADO.NET, Breeze, EF6, Oracle. Client, Oracle. Managed Data Access, and Oracle. Managed Data Access. Entity Framework is a plus • Experience in migrating applications to Microsoft Power Platform and upgrading to the latest tech stack and frameworks. • Familiarity with ITIL best practices, including change management, project management, incident management and incident management. • Experience with the software development life cycle (SDLC) • Experience with machine learning, data analysis, and generative AI is a plus. • Experience in integration with various systems (Oracle EBS, Oracle OIC, Maximo and others) • Experience in Java, J2EE, JavaScript, Python, Spring MVC, Spring JDBC, Web Services. • Experience with Application/Web Server: Weblogic 12c • Knowledge of integrating Maximo with other enterprise systems using IBM Maximo Integration Framework (MIF) is a plus • Knowledge in writing Maximo automation scripts using languages such as Python Jython, and JavaScript to automate routine tasks and enhance functionality is a plus. • Experience in developing and customizing BIRT (Business Intelligence and Reporting Tools) reports for Maximo is a plus • Familiarity with Maximo mobile solutions and mobile application development, knowledge in EzMaxMobile mobile solution for Maximo is a plus. | Skills: Leadership; Project Management; Agile Methodologies; Software Development Life Cycle SDLC; Java; C#; Database Management; Coding Standards; .NET; Team Collaboration; ITIL Certified; VBScript; Cloud Computing; DevOps; Microservices Architecture; API Development; Jest; Enzyme | • Leading a development unit that includes enterprise and custom development personnel. • Setting goals and objectives for the development team and ensuring they are met. • Providing mentorship and guidance to junior developers and other team members. • Evaluating the performance of team members and providing constructive feedback. • Facilitating continuous improvement within the development team and processes following best practice such as ITIL and other international standards. • Ensuring the team follows best practices for software development, security and operations (maintenance of different environments and code versions, QA and code testing, change / release management) • Maintaining and enhancing KDD Application and Enterprise footprint following best practices. • Developing front-end web architecture, designing user interactions on web pages, and ensuring web applications are optimized for mobile and desktop devices. • Building and maintaining back-end server-side applications and databases, designing and implementing efficient database structures, and integrating with third-party APIs. • Lead the efforts of setting up the reporting strategy that includes the backend data repository and from end reporting tools • Collaborating with cross-functional teams to identify, prioritize, and execute product features and functionality. • Writing reusable, testable, and efficient code as well as debugging and troubleshooting issues. • Developing and implementing security and data protection measures. • Ensuring the scalability and performance of applications and implementing necessary monitoring and optimization strategies. • Keeping up to date with emerging trends, technologies, and best practices in web development. • Providing technical guidance and reviewing code to ensure it meets established standards. • Responsible for setting goals and objectives, monitoring progress, and providing feedback to managers and team members. • Mentoring junior developers, sharing knowledge and best practices, and providing guidance on technical issues. • Creating technical documentation and user documentation such as user manuals, guides, or tutorials. • Executing Management directives as required. • Complying with Health, Safety and Environment regulations and working practices of KDD and the State of Kuwait when carrying out duties. • Proven ability to lead and manage a team of developers, fostering a collaborative and innovative environment. • Strong ability to motivate and inspire team members to achieve their full potential. • Expertise in project management methodologies such as Agile. • Skilled in strategic planning and setting long-term goals for the development team. • Ability to align development goals with organizational objectives. • Excellent written and verbal communication skills to effectively convey technical concepts to non-technical stakeholders. • Commitment to maintaining high-quality standards in software development. • Experience in resource allocation and optimizing the use of available resources. • Ability to promote a culture of innovation and continuous improvement within the team. • Demonstrated ability to identify and solve complex technical problems efficiently and effectively. • Excellent communication skills to collaborate with technical and non-technical stakeholders, including team members, project managers, and clients. • Strong time management skills to prioritize tasks and meet project deadlines. • Ability to adapt to changing project requirements and work effectively in a fast-paced, dynamic environment. • Proven experience in working collaboratively with other developers, designers, and stakeholders to achieve project goals. • Strong attention to detail to ensure that code is clean, efficient, and error-free. • Commitment to continuous learning and staying up to date with the latest technologies, tools, and best practices in web development. • Strong proficiency in programming languages such as C#, JavaScript, PHP, TypeScript, VB .NET, VBScript, and DAX. • Experience working with front-end frameworks such as Angular, AngularJS, and Knockout, and back-end frameworks like Node.js and PHP. • Experience with databases such as MySQL, Oracle, and SQL Server. • Knowledge of Oracle Development platforms (Forms, reports, PL/SQL). • Knowledge of Business Intelligence tools (OBIEE) and front-end reporting tools such as Power BI. • Knowledge of Oracle Cloud platform (OCI, APEX) and integration layer (OIC) is a plus • Expertise in IBM Maximo 7.6 development, and knowledge of Maximo Application Suit (MAS) 8 version is a plus. • Familiarity with DevOps tools such as Docker Kubernetes, Git and AWS. • Familiarity with SaaS cloud solutions and their integration. • Experience with Entity Framework Core and other modern ORM tools. • Familiarity with microservices architecture and containerization • Familiarity with CI/CD pipelines and automated testing frameworks. • Experience with web services such as RESTful APIs and SOAP. • Experience with desktop app development using WinForms. • Knowledge of dependency injection frameworks. • Familiarity with front-end technologies including CSS and HTML 5, as well as UI frameworks like Angular Material and Bootstrap. • Experience with server-side scripting languages such as Classic ASP, MVC, Razor, and WEB FORMS. • Experience with real-time communication technologies such as WebSocket and SignalR. • Familiarity with identity management tools such as ASP.NET Identity. • Experience with data access technologies including ADO, ADO.NET, Breeze, EF6, Oracle. Client, Oracle. Managed Data Access, and Oracle. Managed Data Access. Entity Framework is a plus • Experience in migrating applications to Microsoft Power Platform and upgrading to the latest tech stack and frameworks. • Familiarity with ITIL best practices, including change management, project management, incident management and incident management. • Experience with the software development life cycle (SDLC) • Experience with machine learning, data analysis, and generative AI is a plus. • Experience in integration with various systems (Oracle EBS, Oracle OIC, Maximo and others) • Experience in Java, J2EE, JavaScript, Python, Spring MVC, Spring JDBC, Web Services. • Experience with Application/Web Server: Weblogic 12c • Knowledge of integrating Maximo with other enterprise systems using IBM Maximo Integration Framework (MIF) is a plus • Knowledge in writing Maximo automation scripts using languages such as Python Jython, and JavaScript to automate routine tasks and enhance functionality is a plus. • Experience in developing and customizing BIRT (Business Intelligence and Reporting Tools) reports for Maximo is a plus • Familiarity with Maximo mobile solutions and mobile application development, knowledge in EzMaxMobile mobile solution for Maximo is a plus.",
    "meta": {
      "dedup_key": "ada55228954c519e",
      "id_src": "69010",
      "title": "Software Development Manager",
      "url": null,
      "location": "Sabhan",
      "department_code": "690",
      "department_name": "MIS",
      "job_type": null,
      "min_years": null,
      "max_years": null,
      "skills_required": [
        "Leadership",
        "Project Management",
        "Agile Methodologies",
        "Software Development Life Cycle SDLC",
        "Java",
        "C#",
        "Database Management",
        "Coding Standards",
        ".NET",
        "Team Collaboration",
        "ITIL Certified",
        "VBScript",
        "Cloud Computing",
        "DevOps",
        "Microservices Architecture",
        "API Development",
        "Jest",
        "Enzyme"
      ],
      "duties": [
        "• Leading a development unit that includes enterprise and custom development personnel.",
        "• Setting goals and objectives for the development team and ensuring they are met.",
        "• Providing mentorship and guidance to junior developers and other team members.",
        "• Evaluating the performance of team members and providing constructive feedback.",
        "• Facilitating continuous improvement within the development team and processes following best practice such as ITIL and other international standards.",
        "• Ensuring the team follows best practices for software development, security and operations (maintenance of different environments and",
        "code versions, QA and code testing, change / release management)",
        "• Maintaining and enhancing KDD Application and Enterprise footprint following best practices.",
        "• Developing front-end web architecture, designing user interactions on web pages, and ensuring web applications are optimized for mobile and desktop devices.",
        "• Building and maintaining back-end server-side applications and databases, designing and implementing efficient database structures, and integrating with third-party APIs.",
        "• Lead the efforts of setting up the reporting strategy that includes the backend data repository and from end reporting tools",
        "• Collaborating with cross-functional teams to identify, prioritize, and execute product features and functionality.",
        "• Writing reusable, testable, and efficient code as well as debugging and troubleshooting issues.",
        "• Developing and implementing security and data protection measures.",
        "• Ensuring the scalability and performance of applications and implementing necessary monitoring and optimization strategies.",
        "• Keeping up to date with emerging trends, technologies, and best practices in web development.",
        "• Providing technical guidance and reviewing code to ensure it meets established standards.",
        "• Responsible for setting goals and objectives, monitoring progress, and providing feedback to managers and team members.",
        "• Mentoring junior developers, sharing knowledge and best practices, and providing guidance on technical issues.",
        "• Creating technical documentation and user documentation such as user manuals, guides, or tutorials.",
        "• Executing Management directives as required.",
        "• Complying with Health, Safety and Environment regulations and working practices of KDD and the State of Kuwait when carrying out duties."
      ],
      "requirements": [
        "• Proven ability to lead and manage a team of developers, fostering a collaborative and innovative environment.",
        "• Strong ability to motivate and inspire team members to achieve their full potential.",
        "• Expertise in project management methodologies such as Agile.",
        "• Skilled in strategic planning and setting long-term goals for the development team.",
        "• Ability to align development goals with organizational objectives.",
        "• Excellent written and verbal communication skills to effectively convey technical concepts to non-technical stakeholders.",
        "• Commitment to maintaining high-quality standards in software development.",
        "• Experience in resource allocation and optimizing the use of available resources.",
        "• Ability to promote a culture of innovation and continuous improvement within the team.",
        "• Demonstrated ability to identify and solve complex technical problems efficiently and effectively.",
        "• Excellent communication skills to collaborate with technical and non-technical stakeholders, including team members, project managers, and clients.",
        "• Strong time management skills to prioritize tasks and meet project deadlines.",
        "• Ability to adapt to changing project requirements and work effectively in a fast-paced, dynamic environment.",
        "• Proven experience in working collaboratively with other developers, designers, and stakeholders to achieve project goals.",
        "• Strong attention to detail to ensure that code is clean, efficient, and error-free.",
        "• Commitment to continuous learning and staying up to date with the latest technologies, tools, and best practices in web development.",
        "• Strong proficiency in programming languages such as C#, JavaScript, PHP, TypeScript, VB .NET, VBScript, and DAX.",
        "• Experience working with front-end frameworks such as Angular, AngularJS, and Knockout, and back-end frameworks like Node.js and PHP.",
        "• Experience with databases such as MySQL, Oracle, and SQL Server.",
        "• Knowledge of Oracle Development platforms (Forms, reports, PL/SQL).",
        "• Knowledge of Business Intelligence tools (OBIEE) and front-end reporting tools such as Power BI.",
        "• Knowledge of Oracle Cloud platform (OCI, APEX) and integration layer (OIC) is a plus",
        "• Expertise in IBM Maximo 7.6 development, and knowledge of Maximo Application Suit (MAS) 8 version is a plus.",
        "• Familiarity with DevOps tools such as Docker Kubernetes, Git and AWS.",
        "• Familiarity with SaaS cloud solutions and their integration.",
        "• Experience with Entity Framework Core and other modern ORM tools.",
        "• Familiarity with microservices architecture and containerization",
        "• Familiarity with CI/CD pipelines and automated testing frameworks.",
        "• Experience with web services such as RESTful APIs and SOAP.",
        "• Experience with desktop app development using WinForms.",
        "• Knowledge of dependency injection frameworks.",
        "• Familiarity with front-end technologies including CSS and HTML 5, as well as UI frameworks like Angular Material and Bootstrap.",
        "• Experience with server-side scripting languages such as Classic ASP, MVC, Razor, and WEB FORMS.",
        "• Experience with real-time communication technologies such as WebSocket and SignalR.",
        "• Familiarity with identity management tools such as ASP.NET Identity.",
        "• Experience with data access technologies including ADO, ADO.NET, Breeze, EF6, Oracle. Client, Oracle. Managed Data Access, and Oracle. Managed Data Access. Entity Framework is a plus",
        "• Experience in migrating applications to Microsoft Power Platform and upgrading to the latest tech stack and frameworks.",
        "• Familiarity with ITIL best practices, including change management, project management, incident management and incident management.",
        "• Experience with the software development life cycle (SDLC)",
        "• Experience with machine learning, data analysis, and generative AI is a plus.",
        "• Experience in integration with various systems (Oracle EBS, Oracle OIC, Maximo and others)",
        "• Experience in Java, J2EE, JavaScript, Python, Spring MVC, Spring JDBC, Web Services.",
        "• Experience with Application/Web Server: Weblogic 12c",
        "• Knowledge of integrating Maximo with other enterprise systems using IBM Maximo Integration Framework (MIF) is a plus",
        "• Knowledge in writing Maximo automation scripts using languages such as Python Jython, and JavaScript to automate routine tasks and enhance functionality is a plus.",
        "• Experience in developing and customizing BIRT (Business Intelligence and Reporting Tools) reports for Maximo is a plus",
        "• Familiarity with Maximo mobile solutions and mobile application development, knowledge in EzMaxMobile mobile solution for Maximo is a plus."
      ],
      "embedding_text": "Title: Software Development Manager | Department: MIS | Location: Sabhan | Skills: Leadership; Project Management; Agile Methodologies; Software Development Life Cycle SDLC; Java; C#; Database Management; Coding Standards; .NET; Team Collaboration; ITIL Certified; VBScript; Cloud Computing; DevOps; Microservices Architecture; API Development; Jest; Enzyme | Duties: • Leading a development unit that includes enterprise and custom development personnel. • Setting goals and objectives for the development team and ensuring they are met. • Providing mentorship and guidance to junior developers and other team members. • Evaluating the performance of team members and providing constructive feedback. • Facilitating continuous improvement within the development team and processes following best practice such as ITIL and other international standards. • Ensuring the team follows best practices for software development, security and operations (maintenance of different environments and code versions, QA and code testing, change / release management) • Maintaining and enhancing KDD Application and Enterprise footprint following best practices. • Developing front-end web architecture, designing user interactions on web pages, and ensuring web applications are optimized for mobile and desktop devices. • Building and maintaining back-end server-side applications and databases, designing and implementing efficient database structures, and integrating with third-party APIs. • Lead the efforts of setting up the reporting strategy that includes the backend data repository and from end reporting tools • Collaborating with cross-functional teams to identify, prioritize, and execute product features and functionality. • Writing reusable, testable, and efficient code as well as debugging and troubleshooting issues. • Developing and implementing security and data protection measures. • Ensuring the scalability and performance of applications and implementing necessary monitoring and optimization strategies. • Keeping up to date with emerging trends, technologies, and best practices in web development. • Providing technical guidance and reviewing code to ensure it meets established standards. • Responsible for setting goals and objectives, monitoring progress, and providing feedback to managers and team members. • Mentoring junior developers, sharing knowledge and best practices, and providing guidance on technical issues. • Creating technical documentation and user documentation such as user manuals, guides, or tutorials. • Executing Management directives as required. • Complying with Health, Safety and Environment regulations and working practices of KDD and the State of Kuwait when carrying out duties. | Requirements: • Proven ability to lead and manage a team of developers, fostering a collaborative and innovative environment. • Strong ability to motivate and inspire team members to achieve their full potential. • Expertise in project management methodologies such as Agile. • Skilled in strategic planning and setting long-term goals for the development team. • Ability to align development goals with organizational objectives. • Excellent written and verbal communication skills to effectively convey technical concepts to non-technical stakeholders. • Commitment to maintaining high-quality standards in software development. • Experience in resource allocation and optimizing the use of available resources. • Ability to promote a culture of innovation and continuous improvement within the team. • Demonstrated ability to identify and solve complex technical problems efficiently and effectively. • Excellent communication skills to collaborate with technical and non-technical stakeholders, including team members, project managers, and clients. • Strong time management skills to prioritize tasks and meet project deadlines. • Ability to adapt to changing project requirements and work effectively in a fast-paced, dynamic environment. • Proven experience in working collaboratively with other developers, designers, and stakeholders to achieve project goals. • Strong attention to detail to ensure that code is clean, efficient, and error-free. • Commitment to continuous learning and staying up to date with the latest technologies, tools, and best practices in web development. • Strong proficiency in programming languages such as C#, JavaScript, PHP, TypeScript, VB .NET, VBScript, and DAX. • Experience working with front-end frameworks such as Angular, AngularJS, and Knockout, and back-end frameworks like Node.js and PHP. • Experience with databases such as MySQL, Oracle, and SQL Server. • Knowledge of Oracle Development platforms (Forms, reports, PL/SQL). • Knowledge of Business Intelligence tools (OBIEE) and front-end reporting tools such as Power BI. • Knowledge of Oracle Cloud platform (OCI, APEX) and integration layer (OIC) is a plus • Expertise in IBM Maximo 7.6 development, and knowledge of Maximo Application Suit (MAS) 8 version is a plus. • Familiarity with DevOps tools such as Docker Kubernetes, Git and AWS. • Familiarity with SaaS cloud solutions and their integration. • Experience with Entity Framework Core and other modern ORM tools. • Familiarity with microservices architecture and containerization • Familiarity with CI/CD pipelines and automated testing frameworks. • Experience with web services such as RESTful APIs and SOAP. • Experience with desktop app development using WinForms. • Knowledge of dependency injection frameworks. • Familiarity with front-end technologies including CSS and HTML 5, as well as UI frameworks like Angular Material and Bootstrap. • Experience with server-side scripting languages such as Classic ASP, MVC, Razor, and WEB FORMS. • Experience with real-time communication technologies such as WebSocket and SignalR. • Familiarity with identity management tools such as ASP.NET Identity. • Experience with data access technologies including ADO, ADO.NET, Breeze, EF6, Oracle. Client, Oracle. Managed Data Access, and Oracle. Managed Data Access. Entity Framework is a plus • Experience in migrating applications to Microsoft Power Platform and upgrading to the latest tech stack and frameworks. • Familiarity with ITIL best practices, including change management, project management, incident management and incident management. • Experience with the software development life cycle (SDLC) • Experience with machine learning, data analysis, and generative AI is a plus. • Experience in integration with various systems (Oracle EBS, Oracle OIC, Maximo and others) • Experience in Java, J2EE, JavaScript, Python, Spring MVC, Spring JDBC, Web Services. • Experience with Application/Web Server: Weblogic 12c • Knowledge of integrating Maximo with other enterprise systems using IBM Maximo Integration Framework (MIF) is a plus • Knowledge in writing Maximo automation scripts using languages such as Python Jython, and JavaScript to automate routine tasks and enhance functionality is a plus. • Experience in developing and customizing BIRT (Business Intelligence and Reporting Tools) reports for Maximo is a plus • Familiarity with Maximo mobile solutions and mobile application development, knowledge in EzMaxMobile mobile solution for Maximo is a plus."
    }
  }
]